Workbook

Sheet BELEM
A1: ESTUDO BELEM
A2: IBGE 2024/ CENSO 2022
A7: INVESTIMENTO BELEM CAPITAL OOH 2024 | B7: 1641632.8
A8: INVESTIMENTO PARÁ OOH 2024 | B8: 2328715
A10: R$ BRUTO BELÉM CAPITAL - 2025 OOH | B10: 3295226.5
A11: BUDGET BRUTO PARÁ - 2025 OOH (100%) | B11: 4453008.8
A14: Exclusão de Bronze
A15: CICLOS/MEDALHAS | C15: % BUDGET/CICLO | D15: R$ MEDALHA | E15: R$ UNIT. MEDALHAS
A16: Datas | B16: 3 - 2 produto/1 promo | C16: 0.37 | D16: 1219233.8 | E16: 406411.27
A17: Ouro | B17: 5 - 4 produto/ 1 promo | C17: 0.4 | D17: 1318090.6 | E17: 329522.65
A18: Prata | B18: 3 | C18: 0.23 | D18: 757902.09 | E18: 189475.52
B19: 11 ciclos | C19: 1
A21: População Target - AS ABC 18/49 | B21: 584877
A22: Popuação Capital - 1.1303.403 | B22: 1103403
E24: Cobertura total - Data Produto | F24: 70% | H24: Cobertura total - Data Promo | J24: 0.73
E25: Frequencia | F25: 39 | H25: Frequencia | J25: 42
E26: TRP | F26: 2.623 | H26: TRP | J26: 3042
E27: OTS | F27: 15.338.810 | H27: OTS | J27: 17791934
A29: Programação - Ciclo Data Produto
A31: 1 CICLO | S31: TOTAL ANO / CLUSTER
A32: Praça | B32: Exibidores | C32: Pen/Aff | D32: Canais | E32: Formato | F32: Range de volume ideal | G32: Qtdade | H32: Periodicidade | I32: Mês Base | M32: TT | N32: R$ Unit Bruto | O32: Desconto | P32: R$ Unit Bruto | Q32: R$ TT Bruto | R32: % | S32: R$ Total | T32: AMBIENTES | Y32: FORMATO | AB32: EMPRESAS
I33: S1 | J33: S2 | K33: S3 | L33: S4 | M33: Flight | N33: Tabela | O33: (%) | P33: Negociado | Q33: Negociado | S33: ano
A34: DATAS MÃES/NATAL | T34: GDES | U34: MUB | V34: TRANSP | W34: AERO | X34: OPORT | Y34: ESTÁTICO | Z34: DIGITAL | AB34: ELETROMIDIA | AC34: WEOOH | AD34: BME | AE34: ULTRA OOH | AF34: GREEN OOH | AG34: S2X | AH34: PRISMA OOH | AI34: PURAKA | AJ34: BUREAU | AK34: KALLAS
A36: Belem - PA | B36: Eletromidia | C36: 50/156 | D36: Painel de Led | E36: Digital | F36: 6/12 | G36: 1 | H36: Semanal | I36: 1 | K36: 1 | M36: 1 | N36: 5929 | O36: 0.6 | P36: =N36*(1-O36) -> 2371.6 | Q36: =P36*M36*G36 -> 2371.6 | R36: =Q36/$Q$59 -> 0.0058381117 | S36: =Q36*2 -> 4743.2 | T36: =S36 -> 4743.2 | Z36: =S36 -> 4743.2 | AB36: =S36 -> 4743.2
A37: Belem - PA | B37: WeOOH | C37: 50/156 | D37: Painel de Led | E37: Digital | F37: 6/12 | G37: 1 | H37: Mensal | I37: 1 | M37: 1 | N37: 27024.15 | O37: 0.75 | P37: =N37*(1-O37) -> 6756.0375 | Q37: =P37*M37*G37 -> 6756.0375 | R37: =Q37/$Q$59 -> 0.016631178 | S37: =Q37*2 -> 13512.075 | T37: =S37 -> 13512.075 | Z37: =S37 -> 13512.075 | AC37: =S37 -> 13512.075
A38: Belem - PA | B38: Brasil Midia Exterior | C38: 50/156 | D38: Painel de Led | E38: Digital | F38: 6/12 | G38: 1 | H38: Mensal | I38: 1 | M38: 1 | N38: 7000 | O38: 0.1 | P38: =N38*(1-O38) -> 6300 | Q38: =P38*M38*G38 -> 6300 | R38: =Q38/$Q$59 -> 0.015508561 | S38: =Q38*2 -> 12600 | T38: =S38 -> 12600 | Z38: =S38 -> 12600 | AD38: =S38 -> 12600
A39: Belem - PA | B39: Brasil Midia Exterior | C39: 50/156 | D39: Frontlight | E39: Estático | F39: 4/8 | G39: 1 | H39: Mensal | I39: 1 | M39: 1 | N39: 7500 | O39: 0.1 | P39: =N39*(1-O39) -> 6750 | Q39: =P39*M39*G39 -> 6750 | R39: =Q39/$Q$59 -> 0.016616316 | S39: =Q39*2 -> 13500 | T39: =S39 -> 13500 | Y39: =S39 -> 13500 | AD39: =S39 -> 13500
A40: Belem - PA | B40: Brasil Midia Exterior | C40: 50/156 | D40: Outdoor lonado | E40: Estático | F40: 15/30 | G40: 25 | H40: Mensal | I40: 25 | M40: 1 | N40: 2650 | O40: 0.1 | P40: =N40*(1-O40) -> 2385 | Q40: =P40*M40*G40 -> 59625 | R40: =Q40/$Q$59 -> 0.14677745 | S40: =Q40*2 -> 119250 | T40: =S40 -> 119250 | Y40: =S40 -> 119250 | AD40: =S40 -> 119250
A41: Belem - PA | B41: Ultra OOH | C41: 50/156 | D41: Painel de Led | E41: Digital | F41: 6/12 | G41: 1 | H41: Mensal | I41: 1 | M41: 1 | N41: 5593 | O41: 0.25 | P41: =N41*(1-O41) -> 4194.75 | Q41: =P41*M41*G41 -> 4194.75 | R41: =Q41/$Q$59 -> 0.010326117 | S41: =Q41*2 -> 8389.5 | T41: =S41 -> 8389.5 | Z41: =S41 -> 8389.5 | AE41: =S41 -> 8389.5
A42: Belem - PA | B42: Ultra OOH | C42: 50/156 | D42: Frontlight | E42: Estático | F42: 4/8 | G42: 2 | H42: Mensal | I42: 2 | M42: 1 | N42: =(10000+6680)/2 -> 8340 | O42: 0.3 | P42: =N42*(1-O42) -> 5838 | Q42: =P42*M42*G42 -> 11676 | R42: =Q42/$Q$59 -> 0.028742534 | S42: =Q42*2 -> 23352 | T42: =S42 -> 23352 | Y42: =S42 -> 23352 | AE42: =S42 -> 23352
A43: Belem - PA | B43: Ultra OOH | C43: 50/156 | D43: Empena | E43: Estático | F43: 2/5 | G43: 3 | H43: Mensal | I43: 3 | M43: 1 | N43: =(13400+28000+16000)/3 -> 19133.333 | O43: 0.25 | P43: =N43*(1-O43) -> 14350 | Q43: =P43*M43*G43 -> 43050 | R43: =Q43/$Q$59 -> 0.10597517 | S43: =Q43*2 -> 86100 | T43: =S43 -> 86100 | Y43: =S43 -> 86100 | AE43: =S43 -> 86100
A44: Belem - PA | B44: Green Outdoor | C44: 50/156 | D44: Painel de Led | E44: Digital | F44: 6/12 | G44: 1 | H44: Mensal | I44: 1 | M44: 1 | N44: 2362 | O44: 0.2 | P44: =N44*(1-O44) -> 1889.6 | Q44: =P44*M44*G44 -> 1889.6 | R44: =Q44/$Q$59 -> 0.0046515837 | S44: =Q44*2 -> 3779.2 | T44: =S44 -> 3779.2 | Z44: =S44 -> 3779.2 | AF44: =S44 -> 3779.2
A45: Belem - PA | B45: Green Outdoor | C45: 50/156 | D45: Outdoor lonado | E45: Estática | F45: 15/30 | G45: 25 | H45: Mensal | K45: 25 | M45: 1 | N45: 2650 | O45: 0.2 | P45: =N45*(1-O45) -> 2120 | Q45: =P45*M45*G45 -> 53000 | R45: =Q45/$Q$59 -> 0.13046885 | S45: =Q45*2 -> 106000 | T45: =S45 -> 106000 | Y45: =S45 -> 106000 | AF45: =S45 -> 106000
A46: Belem - PA | B46: S2X Promoções | C46: 30/155 | D46: Carro de Som | E46: Som | F46: 7/30 | G46: 7 | H46: Diaria 8 horas | I46: 7 | K46: 7 | M46: 2 | N46: =265*8 -> 2120 | O46: 0.4 | P46: =N46*(1-O46) -> 1272 | Q46: =P46*M46*G46 -> 17808 | R46: =Q46/$Q$59 -> 0.043837533 | S46: =Q46*2 -> 35616 | T46: =S46 -> 35616 | AG46: =S46 -> 35616
A47: Belem - PA | B47: Prisma OOH | C47: 50/156 | D47: Painel de Led | E47: Digital | F47: 6/12 | G47: 2 | H47: Mensal | I47: 2 | M47: 1 | N47: 7920 | O47: 0.25 | P47: =N47*(1-O47) -> 5940 | Q47: =P47*M47*G47 -> 11880 | R47: =Q47/$Q$59 -> 0.029244716 | S47: =Q47*2 -> 23760 | T47: =S47 -> 23760 | Z47: =S47 -> 23760 | AH47: =S47 -> 23760
A48: Belem - PA | B48: Puraka | C48: 50/156 | D48: Painel de Led | E48: Digital | F48: 6/12 | G48: 2 | H48: Mensal | I48: 2 | M48: 1 | N48: 18500 | O48: 0.6 | P48: =N48*(1-O48) -> 7400 | Q48: =P48*M48*G48 -> 14800 | R48: =Q48/$Q$59 -> 0.036432811 | S48: =Q48*2 -> 29600 | T48: =S48 -> 29600 | Z48: =S48 -> 29600 | AI48: =S48 -> 29600
A49: Belem - PA | B49: Puraka | C49: 50/156 | D49: Frontlight | E49: Estático | F49: 4/8 | G49: 2 | H49: Mensal | I49: 2 | M49: 1 | N49: 20500 | O49: 0.58 | P49: =N49*(1-O49) -> 8610 | Q49: =P49*M49*G49 -> 17220 | R49: =Q49/$Q$59 -> 0.042390067 | S49: =Q49*2 -> 34440 | T49: =S49 -> 34440 | Y49: =S49 -> 34440 | AI49: =S49 -> 34440
A50: Belem - PA | B50: Bureau de Mídia | C50: 50/156 | D50: Painel de Led | E50: Digital | F50: 6/12 | G50: 1 | H50: Mensal | I50: 1 | M50: 1 | N50: 8125 | O50: 0.15 | P50: =N50*(1-O50) -> 6906.25 | Q50: =P50*M50*G50 -> 6906.25 | R50: =Q50/$Q$59 -> 0.017000953 | S50: =Q50*2 -> 13812.5 | T50: =S50 -> 13812.5 | Z50: =S50 -> 13812.5 | AJ50: =S50 -> 13812.5
A51: Belem - PA | B51: Bureau de Mídia | C51: 50/156 | D51: Envelopamento Barco | E51: Estático | F51: 1 | G51: 1 | H51: Mensal | I51: 1 | M51: 1 | N51: 73000 | O51: 0 | P51: =N51*(1-O51) -> 73000 | Q51: =P51*M51*G51 -> 73000 | R51: =Q51/$Q$59 -> 0.17970238 | S51: =Q51*2 -> 146000 | V51: =S51 -> 146000 | Z51: =S51 -> 146000 | AJ51: =S51 -> 146000
A56: Belem - PA | B56: Aeroporto | S56: =Q56*2 -> 0 | W56: =S56 -> 0
A57: Belem - PA | B57: Oportunidades | D57: Marítimos / Ativação | Q57: 69000 | R57: =Q57/Q59 -> 0.16985567 | S57: =Q57*2 -> 138000 | X57: =S57 -> 138000
I58: =I59/M59 -> 0.60714286 | K58: =K59/M59 -> 0.39285714
A59: Total faces compra | I59: =I44+I43+I42+I41+I40+I39+I38+I37+I46+I36+I47+I48+I49+I50+I51 -> 51 | K59: =K46+K36+K45 -> 33 | M59: =SUM(I59:L59) -> 84 | Q59: =SUM(Q36:Q58) -> 406227.24 | R59: =SUM(R36:R57) -> 1 | S59: =SUM(S36:S58) -> 812454.48 | T59: =SUM(T36:T57) -> 528454.48 | U59: =SUM(U36:U57) -> 0 | V59: =SUM(V36:V57) -> 146000 | W59: =SUM(W36:W57) -> 0 | X59: =SUM(X36:X57) -> 138000 | Y59: =SUM(Y36:Y57) -> 382642 | Z59: =SUM(Z36:Z57) -> 256196.48 | AB59: =SUM(AB35:AB58) -> 4743.2 | AC59: =SUM(AC35:AC58) -> 13512.075 | AD59: =SUM(AD35:AD58) -> 145350 | AE59: =SUM(AE35:AE58) -> 117841.5 | AF59: =SUM(AF35:AF58) -> 109779.2 | AG59: =SUM(AG35:AG58) -> 35616 | AH59: =SUM(AH35:AH58) -> 23760 | AI59: =SUM(AI35:AI58) -> 64040 | ... AK59: =SUM(AK35:AK58) -> 0
A60: Total faces simulação | I60: =I44+I43+I42+I41+I40+I39+I38+I37+I46+I36+I47+I48+I49+I50+I51 -> 51 | J60: =I44+I43+I42+I41+I40+I39+I38+I37+I47+I48+I49+I50+I51 -> 43 | K60: =K45+I44+I43+I42+I41+I39+I38+I37+K46+K36+I47+I48+I49+I50+I51 -> 51 | L60: =K45+I44+I43+I42+I41+I39+I38+I37+I47+I48+I49+I50+I51 -> 43 | M60: =SUM(I60:L60) -> 188 | T60: =T59/S59 -> 0.65044195 | U60: =U59/S59 -> 0 | V60: =V59/S59 -> 0.17970238 | W60: =W59/S59 -> 0 | X60: =X59/S59 -> 0.16985567 | Y60: =Y59/S59 -> 0.47097039 | Z60: =Z59/S59 -> 0.31533641 | AA60: =Y61+Z61 -> 70
A61: Grandes Formatos | I61: =I60/$M$60 -> 0.2712766 | J61: =J60/$M$60 -> 0.2287234 | K61: =K60/$M$60 -> 0.2712766 | L61: =L60/$M$60 -> 0.2287234 | Q61: =T59/2 -> 264227.24 | R61: =Q61/Q66 -> 0.65044195 | Y61: =I39+I40+I42+I43+K45+I49 -> 58 | Z61: =I36+K36+I37+I38+I41+I44+I47+I48+I50+I51 -> 12 | AA61: volume de faces
A62: MUB | Q62: =U59/2 -> 0 | R62: =Q62/Q66 -> 0 | S62: =Q59/M59 -> 4836.0385 | T62: CPFACE | Y62: =Y61/M59 -> 0.69047619 | Z62: =Z61/M59 -> 0.14285714
A63: Transportes | Q63: =V59/2 -> 73000 | R63: =Q63/Q66 -> 0.17970238 | Y63: SHARE FACES
A64: Oportunidades | Q64: =X59/2 -> 69000 | R64: =Q64/Q66 -> 0.16985567
A65: Aeroporto | Q65: =W59/2 -> 0 | R65: =Q65/Q66 -> 0
Q66: =SUM(Q61:Q65) -> 406227.24 | R66: =SUM(R61:R65) -> 1
A70: Programação - Ciclo Data Promo
A72: 1 CICLO | S72: TOTAL ANO / CLUSTER
A73: Praça | B73: Exibidores | C73: Pen/Aff | D73: Canais | E73: Formato | F73: Range de volume ideal | G73: Qtdade | H73: Periodicidade | I73: Mês Base | M73: TT | N73: R$ Unit Bruto | O73: Desconto | P73: R$ Unit Bruto | Q73: R$ TT Bruto | R73: % | S73: R$ Total | T73: AMBIENTES | Y73: FORMATO | AB73: EMPRESAS
I74: S1 | J74: S2 | K74: S3 | L74: S4 | M74: Flight | N74: Tabela | O74: (%) | P74: Negociado | Q74: Negociado | S74: ano
A75: DATAS BW | T75: GDES | U75: MUB | V75: TRANSP | W75: AERO | X75: OPORT | Y75: ESTÁTICO | Z75: DIGITAL | AB75: ELETROMIDIA | AC75: WEOOH | AD75: BME | AE75: ULTRA OOH | AF75: GREEN OOH | AG75: S2X | AH75: PRISMA OOH | AI75: PURAKA | AJ75: BUREAU | AK75: KALLAS
A77: Belem - PA | B77: Eletromidia | C77: 50/156 | D77: Painel de Led | E77: Digital | F77: 6/12 | G77: 1 | H77: Semanal | I77: 1 | K77: 1 | M77: 1 | N77: 5929 | O77: 0.6 | P77: =N77*(1-O77) -> 2371.6 | Q77: =P77*M77*G77 -> 2371.6 | R77: =Q77/$Q$99 -> 0.0058369093 | S77: =Q77 -> 2371.6 | T77: =S77 -> 2371.6 | Z77: =S77 -> 2371.6 | AB77: =S77 -> 2371.6
A78: Belem - PA | B78: WeOOH | C78: 50/156 | D78: Painel de Led | E78: Digital | F78: 6/12 | G78: 2 | H78: Mensal | I78: 2 | M78: 1 | N78: 27024.15 | O78: 0.75 | P78: =N78*(1-O78) -> 6756.0375 | Q78: =P78*M78*G78 -> 13512.075 | R78: =Q78/$Q$99 -> 0.033255505 | S78: =Q78 -> 13512.075 | T78: =S78 -> 13512.075 | Z78: =S78 -> 13512.075 | AC78: =S78 -> 13512.075
A79: Belem - PA | B79: Brasil Midia Exterior | C79: 50/156 | D79: Painel de Led | E79: Digital | F79: 6/12 | G79: 2 | H79: Mensal | I79: 2 | M79: 1 | N79: 7000 | O79: 0.1 | P79: =N79*(1-O79) -> 6300 | Q79: =P79*M79*G79 -> 12600 | R79: =Q79/$Q$99 -> 0.031010734 | S79: =Q79 -> 12600 | T79: =S79 -> 12600 | Z79: =S79 -> 12600 | AD79: =S79 -> 12600
A80: Belem - PA | B80: Brasil Midia Exterior | C80: 50/156 | D80: Frontlight | E80: Estático | F80: 4/8 | G80: 1 | H80: Mensal | I80: 1 | M80: 1 | N80: 7500 | O80: 0.1 | P80: =N80*(1-O80) -> 6750 | Q80: =P80*M80*G80 -> 6750 | R80: =Q80/$Q$99 -> 0.016612893 | S80: =Q80 -> 6750 | T80: =S80 -> 6750 | Y80: =S80 -> 6750 | AD80: =S80 -> 6750
A81: Belem - PA | B81: Brasil Midia Exterior | C81: 50/156 | D81: Outdoor lonado | E81: Estático | F81: 15/30 | G81: 30 | H81: Mensal | I81: 30 | M81: 1 | N81: 2650 | O81: 0.1 | P81: =N81*(1-O81) -> 2385 | Q81: =P81*M81*G81 -> 71550 | R81: =Q81/$Q$99 -> 0.17609667 | S81: =Q81 -> 71550 | T81: =S81 -> 71550 | Y81: =S81 -> 71550 | AD81: =S81 -> 71550
A82: Belem - PA | B82: Ultra OOH | C82: 50/156 | D82: Painel de Led | E82: Digital | F82: 6/12 | G82: 1 | H82: Mensal | I82: 1 | M82: 1 | N82: 5593 | O82: 0.25 | P82: =N82*(1-O82) -> 4194.75 | Q82: =P82*M82*G82 -> 4194.75 | R82: =Q82/$Q$99 -> 0.01032399 | S82: =Q82 -> 4194.75 | T82: =S82 -> 4194.75 | Z82: =S82 -> 4194.75 | AE82: =S82 -> 4194.75
A83: Belem - PA | B83: Ultra OOH | C83: 50/156 | D83: Frontlight | E83: Estático | F83: 4/8 | G83: 2 | H83: Mensal | I83: 2 | M83: 1 | N83: =(10000+6680)/2 -> 8340 | O83: 0.3 | P83: =N83*(1-O83) -> 5838 | Q83: =P83*M83*G83 -> 11676 | R83: =Q83/$Q$99 -> 0.028736613 | S83: =Q83 -> 11676 | T83: =S83 -> 11676 | Y83: =S83 -> 11676 | AE83: =S83 -> 11676
A84: Belem - PA | B84: Green Outdoor | C84: 50/156 | D84: Painel de Led | E84: Digital | F84: 6/12 | G84: 1 | H84: Mensal | I84: 1 | M84: 1 | N84: 2362 | O84: 0.2 | P84: =N84*(1-O84) -> 1889.6 | Q84: =P84*M84*G84 -> 1889.6 | R84: =Q84/$Q$99 -> 0.0046506256 | S84: =Q84 -> 1889.6 | T84: =S84 -> 1889.6 | Z84: =S84 -> 1889.6 | AF84: =S84 -> 1889.6
A85: Belem - PA | B85: Green Outdoor | C85: 50/156 | D85: Outdoor lonado | E85: Estática | F85: 15/30 | G85: 30 | H85: Mensal | K85: 30 | M85: 1 | N85: 2650 | O85: 0.2 | P85: =N85*(1-O85) -> 2120 | Q85: =P85*M85*G85 -> 63600 | R85: =Q85/$Q$99 -> 0.15653037 | S85: =Q85 -> 63600 | T85: =S85 -> 63600 | Y85: =S85 -> 63600 | AF85: =S85 -> 63600
A86: Belem - PA | B86: S2X Promoções | C86: 30/155 | D86: Carro de Som | E86: Som | F86: 7/30 | G86: 7 | H86: Diaria 8 horas | I86: 7 | J86: 7 | K86: 7 | L86: 7 | M86: 4 | N86: =265*8 -> 2120 | O86: 0.4 | P86: =N86*(1-O86) -> 1272 | Q86: =P86*M86*G86 -> 35616 | R86: =Q86/$Q$99 -> 0.087657008 | S86: =Q86 -> 35616 | T86: =S86 -> 35616 | AG86: =S86 -> 35616
A87: Belem - PA | B87: Prisma OOH | C87: 50/156 | D87: Painel de Led | E87: Digital | F87: 6/12 | G87: 2 | H87: Mensal | I87: 2 | M87: 1 | N87: 7920 | O87: 0.25 | P87: =N87*(1-O87) -> 5940 | Q87: =P87*M87*G87 -> 11880 | R87: =Q87/$Q$99 -> 0.029238692 | S87: =Q87 -> 11880 | T87: =S87 -> 11880 | Z87: =S87 -> 11880 | AH87: =S87 -> 11880
A88: Belem - PA | B88: Puraka | C88: 50/156 | D88: Painel de Led | E88: Digital | F88: 6/12 | G88: 3 | H88: Mensal | I88: 3 | M88: 1 | N88: 18500 | O88: 0.6 | P88: =N88*(1-O88) -> 7400 | Q88: =P88*M88*G88 -> 22200 | R88: =Q88/$Q$99 -> 0.05463796 | S88: =Q88 -> 22200 | T88: =S88 -> 22200 | Z88: =S88 -> 22200 | AI88: =S88 -> 22200
A89: Belem - PA | B89: Puraka | C89: 50/156 | D89: Frontlight | E89: Estático | F89: 4/8 | G89: 2 | H89: Mensal | I89: 2 | M89: 1 | N89: 20500 | O89: 0.58 | P89: =N89*(1-O89) -> 8610 | Q89: =P89*M89*G89 -> 17220 | R89: =Q89/$Q$99 -> 0.042381336 | S89: =Q89 -> 17220 | T89: =S89 -> 17220 | Y89: =S89 -> 17220 | AI89: =S89 -> 17220
A90: Belem - PA | B90: Bureau de Mídia | C90: 50/156 | D90: Painel de Led | E90: Digital | F90: 6/12 | G90: 2 | H90: Mensal | I90: 2 | M90: 1 | N90: 8125 | O90: 0.15 | P90: =N90*(1-O90) -> 6906.25 | Q90: =P90*M90*G90 -> 13812.5 | R90: =Q90/$Q$99 -> 0.033994902 | S90: =Q90 -> 13812.5 | T90: =S90 -> 13812.5 | Z90: =S90 -> 13812.5 | AJ90: =S90 -> 13812.5
A91: Belem - PA | B91: Bureau de Mídia | D91: BikeDoor | E91: Estático | F91: 5/10 | G91: 4 | H91: Diario | I91: 4 | J91: 4 | K91: 4 | L91: 4 | M91: 4 | N91: 1944 | O91: 0.15 | P91: =N91*(1-O91) -> 1652.4 | Q91: =P91*M91*G91 -> 26438.4 | R91: =Q91/$Q$99 -> 0.06506938 | S91: =Q91 -> 26438.4 | V91: =S91 -> 26438.4 | Y91: =S91 -> 26438.4 | AJ91: =S91 -> 26438.4
A92: Belem - PA | B92: Cartaxi | C92: 30/155 | D92: Taxi - vidro traseiro | E92: Estático | F92: 10/35 | G92: 20 | H92: Mensal | I92: 20 | M92: 1 | N92: 1600 | O92: 0.5 | P92: =N92*(1-O92) -> 800 | Q92: =P92*M92*G92 -> 16000 | R92: =Q92/$Q$99 -> 0.03937871 | S92: =Q92 -> 16000 | V92: =S92 -> 16000 | AJ92: =S92 -> 16000 | AK92: =S92 -> 16000
A96: Belem - PA | B96: Aeroporto | Q96: =P96*M96*G96 -> 0 | R96: =Q96/Q99 -> 0 | S96: =Q96 -> 0 | W96: =S96 -> 0 | Z96: =W96 -> 0
A97: Belem - PA | B97: Oportunidades | D97: Marítimos / Ativação | Q97: 75000 | R97: =Q97/Q99 -> 0.1845877 | S97: =Q97 -> 75000 | X97: =S97 -> 75000
I98: =I99/M99 -> 0.55555556 | J98: =J99/M99 -> 0.076388889 | K98: =K99/M99 -> 0.29166667 | L98: =L99/M99 -> 0.076388889
A99: Total faces compra | I99: =I87+I86+I84+I83+I82+I81+I80+I79+I78+I77+I88+I90+I89+I91+I92 -> 80 | J99: =J86+J91 -> 11 | K99: =K86+K77+K85+K91 -> 42 | L99: =L86+L91 -> 11 | M99: =SUM(I99:L99) -> 144 | Q99: =SUM(Q76:Q98) -> 406310.93 | R99: =SUM(R76:R97) -> 1 | S99: =SUM(S76:S98) -> 406310.93 | T99: =SUM(T76:T97) -> 288872.53 | U99: =SUM(U76:U97) -> 0 | V99: =SUM(V76:V97) -> 42438.4 | W99: =SUM(W76:W97) -> 0 | X99: =SUM(X76:X97) -> 75000 | Y99: =SUM(Y76:Y97) -> 197234.4 | Z99: =SUM(Z76:Z97) -> 82460.525 | AB99: =SUM(AB76:AB98) -> 2371.6 | AC99: =SUM(AC76:AC98) -> 13512.075 | AD99: =SUM(AD76:AD98) -> 90900 | AE99: =SUM(AE76:AE98) -> 15870.75 | AF99: =SUM(AF76:AF98) -> 65489.6 | AG99: =SUM(AG76:AG98) -> 35616 | AH99: =SUM(AH76:AH98) -> 11880 | AI99: =SUM(AI76:AI98) -> 39420 | ... AK99: =SUM(AK76:AK98) -> 16000
A100: Total faces simulação | I100: =I84+I83+I81+I80+I79+I78+I86+I77+I87+I82+I88+I89+I90+I91+I92 -> 80 | J100: =I87+J86+I84+I83+I82+I81+I80+I79+I78+I88+I89+I90+I91+J91+I92 -> 83 | K100: =I87+K86+K85+I84+I83+I82+I80+I79+I78+K77+I88+I89+I90++K91+I92 -> 80 | L100: =I87+L86+K85+I84+I83+I82+I80+I79+I78+I88+I89+I90+L91+I92 -> 79 | M100: =SUM(I100:L100) -> 322 | T100: =T99/S99 -> 0.71096421 | U100: =U99/S99 -> 0 | V100: =V99/S99 -> 0.10444809 | W100: =W99/S99 -> 0 | X100: =X99/S99 -> 0.1845877 | Y100: =Y99/S99 -> 0.48542726 | Z100: =Z99/S99 -> 0.20294932 | AA100: =Y101+Z101 -> 116
A101: Grandes Formatos | I101: =I100/M100 -> 0.2484472 | J101: =J100/M100 -> 0.25776398 | K101: =K100/M100 -> 0.2484472 | L101: =L100/M100 -> 0.24534161 | Q101: =T99 -> 288872.53 | R101: =Q101/Q106 -> 0.71096421 | Y101: =I80+I81+I83+K85+I89+I91+J91+K91+L91 -> 81 | Z101: =I77+K77+I78+I79+I82+I84+I87+I88+I90+I92 -> 35 | AA101: volume de faces
A102: MUB | Q102: =U99 -> 0 | R102: =Q102/Q106 -> 0 | S102: =Q99/M99 -> 2821.6036 | T102: CPFACE | Y102: =Y101/M99 -> 0.5625 | Z102: =Z101/M99 -> 0.24305556
A103: Transportes | Q103: =V99 -> 42438.4 | R103: =Q103/Q106 -> 0.10444809 | Y103: SHARE FACES
A104: Oportunidades | Q104: =X99 -> 75000 | R104: =Q104/Q106 -> 0.1845877
A105: Aeroporto | Q105: =W99 -> 0 | R105: =Q105/Q106 -> 0
Q106: =SUM(Q101:Q105) -> 406310.93 | R106: =SUM(R101:R105) -> 1
E113: Cobertura total - Ouro Produto | F113: 60% | G113: Cobertura total - Ouro Promo | I113: 0.74
E114: Frequencia | F114: 36 | G114: Frequencia | I114: 42
E115: TRP | F115: 2133 | G115: TRP | I115: 3154
E116: OTS | F116: 12.474.261 | G116: OTS | I116: 18445834
A118: Programação - Ciclo Ouro Produto
A120: 1 CICLO | S120: TOTAL ANO / CLUSTER
A121: Praça | B121: Exibidores | C121: Pen/Aff | D121: Canais | E121: Formato | F121: Range de volume ideal | G121: Qtdade | H121: Periodicidade | I121: Mês Base | M121: TT | N121: R$ Unit Bruto | O121: Desconto | P121: R$ Unit Bruto | Q121: R$ TT Bruto | R121: % | S121: R$ Total | T121: AMBIENTES | Y121: FORMATO | AB121: EMPRESAS
I122: S1 | J122: S2 | K122: S3 | L122: S4 | M122: Flight | N122: Tabela | O122: (%) | P122: Negociado | Q122: Negociado | S122: ano
A123: OURO PRODUTO | T123: GDES | U123: MUB | V123: TRANSP | W123: AERO | X123: OPORT | Y123: ESTÁTICO | Z123: DIGITAL | AB123: ELETROMIDIA | AC123: WEOOH | AD123: BME | AE123: ULTRA OOH | AF123: GREEN OOH | AG123: S2X | AH123: PRISMA OOH | AI123: PURAKA | AJ123: BUREAU | AK123: KALLAS
A125: Belem - PA | B125: WeOOH | C125: 50/156 | D125: Painel de Led | E125: Digital | F125: 4/8 | G125: 1 | H125: Mensal | I125: 1 | M125: 1 | N125: 27024.15 | O125: 0.75 | P125: =N125*(1-O125) -> 6756.0375 | Q125: =P125*M125*G125 -> 6756.0375 | R125: =Q125/$Q$147 -> 0.020520184 | S125: =Q125*3 -> 20268.113 | T125: =S125 -> 20268.113 | Z125: =S125 -> 20268.113 | AC125: =S125 -> 20268.113
A126: Belem - PA | B126: Brasil Midia Exterior | C126: 50/156 | D126: Painel de Led | E126: Digital | F126: 4/8 | G126: 1 | H126: Mensal | I126: 1 | M126: 1 | N126: 7000 | O126: 0.1 | P126: =N126*(1-O126) -> 6300 | Q126: =P126*M126*G126 -> 6300 | R126: =Q126/$Q$147 -> 0.019135057 | S126: =Q126*3 -> 18900 | T126: =S126 -> 18900 | Z126: =S126 -> 18900 | AD126: =S126 -> 18900
A127: Belem - PA | B127: Brasil Midia Exterior | C127: 50/156 | D127: Frontlight | E127: Estático | F127: 3/6 | G127: 1 | H127: Mensal | I127: 1 | M127: 1 | N127: 7500 | O127: 0.1 | P127: =N127*(1-O127) -> 6750 | Q127: =P127*M127*G127 -> 6750 | R127: =Q127/$Q$147 -> 0.020501846 | S127: =Q127*3 -> 20250 | T127: =S127 -> 20250 | Y127: =S127 -> 20250 | AD127: =S127 -> 20250
A128: Belem - PA | B128: Brasil Midia Exterior | C128: 50/156 | D128: Outdoor lonado | E128: Estático | F128: 10/20 | G128: 18 | H128: Mensal | I128: 18 | M128: 1 | N128: 2650 | O128: 0.1 | P128: =N128*(1-O128) -> 2385 | Q128: =P128*M128*G128 -> 42930 | R128: =Q128/$Q$147 -> 0.13039174 | S128: =Q128*3 -> 128790 | T128: =S128 -> 128790 | Y128: =S128 -> 128790 | AD128: =S128 -> 128790
A129: Belem - PA | B129: Ultra OOH | C129: 50/156 | D129: Painel de Led | E129: Digital | F129: 4/8 | G129: 1 | H129: Mensal | I129: 1 | M129: 1 | N129: 5593 | O129: 0.25 | P129: =N129*(1-O129) -> 4194.75 | Q129: =P129*M129*G129 -> 4194.75 | R129: =Q129/$Q$147 -> 0.012740759 | S129: =Q129*3 -> 12584.25 | T129: =S129 -> 12584.25 | Z129: =S129 -> 12584.25 | AE129: =S129 -> 12584.25
A130: Belem - PA | B130: Ultra OOH | C130: 50/156 | D130: Frontlight | E130: Estático | F130: 3/6 | G130: 2 | H130: Mensal | I130: 2 | M130: 1 | N130: =(10000+6680)/2 -> 8340 | O130: 0.3 | P130: =N130*(1-O130) -> 5838 | Q130: =P130*M130*G130 -> 11676 | R130: =Q130/$Q$147 -> 0.035463638 | S130: =Q130*3 -> 35028 | T130: =S130 -> 35028 | Y130: =S130 -> 35028 | AE130: =S130 -> 35028
A131: Belem - PA | B131: Ultra OOH | C131: 50/156 | D131: Empena | E131: Estático | F131: 1/3 | G131: 3 | H131: Mensal | I131: 3 | M131: 1 | N131: =(13400+28000+16000)/3 -> 19133.333 | O131: 0.25 | P131: =N131*(1-O131) -> 14350 | Q131: =P131*M131*G131 -> 43050 | R131: =Q131/$Q$147 -> 0.13075622 | S131: =Q131*3 -> 129150 | T131: =S131 -> 129150 | Y131: =S131 -> 129150 | AE131: =S131 -> 129150
A132: Belem - PA | B132: Green Outdoor | C132: 50/156 | D132: Painel de Led | E132: Digital | F132: 4/8 | G132: 1 | H132: Mensal | I132: 1 | M132: 1 | N132: 2362 | O132: 0.2 | P132: =N132*(1-O132) -> 1889.6 | Q132: =P132*M132*G132 -> 1889.6 | R132: =Q132/$Q$147 -> 0.0057393021 | S132: =Q132*3 -> 5668.8 | T132: =S132 -> 5668.8 | Z132: =S132 -> 5668.8 | AF132: =S132 -> 5668.8
A133: Belem - PA | B133: Green Outdoor | C133: 50/156 | D133: Outdoor lonado | E133: Estática | F133: 10/20 | G133: 18 | H133: Mensal | K133: 18 | M133: 1 | N133: 2650 | O133: 0.2 | P133: =N133*(1-O133) -> 2120 | Q133: =P133*M133*G133 -> 38160 | R133: =Q133/$Q$147 -> 0.11590377 | S133: =Q133*3 -> 114480 | T133: =S133 -> 114480 | Y133: =S133 -> 114480 | AF133: =S133 -> 114480
...

Sheet Pesos
A1: 1 | B1: 0.9
A2: 2 | B2: 0.8
A3: 3 | B3: 0.7
A4: 4 | B4: 0.6
A5: 5 | B5: 0.5
A6: 6 | B6: 0.4
A7: 7 | B7: 0.3
A8: 8 | B8: 0.2
A9: 9 | B9: 0.1
A10: 10 | B10: 0.05
A11: 11 | B11: 0.03
A12: 12 | B12: 0.02

Sheet BELEM PLAN
A1: ciclos | B1: regional_boticario | C1: uf | D1: praca | E1: exibidores | F1: formato | G1: ranking | H1: pesos | I1: estatico | J1: digital | K1: range_minimo | L1: range_maximo | M1: quantidade | N1: periodicidade | O1: s1 | P1: s2 | Q1: s3 | R1: s4 | S1: flight | T1: unitario_bruto_tabela | U1: desconto | V1: unitario_bruto_negociado | W1: total_bruto_negociado
A2: data produto | B2: norte | C2: pa | D2: belem | E2: eletromidia | F2: Painel de Led | G2: 2 | H2: =VLOOKUP(G2,Pesos!A:B,2,0) -> 0.8 | J2: X | K2: 6 | L2: 12 | M2: 1 | N2: semanal | O2: 1 | Q2: 1 | S2: 2 | T2: 5929 | U2: 0.6 | V2: =T2*(1-U2) -> 2371.6 | W2: =V2*S2*M2 -> 4743.2
A3: data produto | B3: norte | C3: pa | D3: belem | E3: WeOOH | F3: Painel de Led | G3: 2 | H3: =VLOOKUP(G3,Pesos!A:B,2,0) -> 0.8 | J3: X | K3: 6 | L3: 12 | M3: 1 | N3: Mensal | O3: 1 | S3: 1 | T3: 27024.1 | U3: 0.75 | V3: =T3*(1-U3) -> 6756.025 | W3: =V3*S3*M3 -> 6756.025
A4: data produto | B4: norte | C4: pa | D4: belem | E4: Brasil Midia Exterior | F4: Painel de Led | G4: 2 | H4: =VLOOKUP(G4,Pesos!A:B,2,0) -> 0.8 | J4: X | K4: 6 | L4: 12 | M4: 1 | N4: Mensal | O4: 1 | S4: 1 | T4: 7000 | U4: 0.1 | V4: =T4*(1-U4) -> 6300 | W4: =V4*S4*M4 -> 6300
A5: data produto | B5: norte | C5: pa | D5: belem | E5: Brasil Midia Exterior | F5: Frontlight | G5: 5 | H5: =VLOOKUP(G5,Pesos!A:B,2,0) -> 0.5 | I5: X | K5: 4 | L5: 8 | M5: 1 | N5: Mensal | O5: 1 | S5: 1 | T5: 7500 | U5: 0.1 | V5: =T5*(1-U5) -> 6750 | W5: =V5*S5*M5 -> 6750
A6: data produto | B6: norte | C6: pa | D6: belem | E6: Brasil Midia Exterior | F6: Outdoor lonado | G6: 1 | H6: =VLOOKUP(G6,Pesos!A:B,2,0) -> 0.9 | I6: X | K6: 15 | L6: 30 | M6: 25 | N6: Bisemanal | O6: 25 | S6: 1 | T6: 2650 | U6: 0.1 | V6: =T6*(1-U6) -> 2385 | W6: =V6*S6*M6 -> 59625
A7: data produto | B7: norte | C7: pa | D7: belem | E7: Ultra OOH | F7: Painel de Led | G7: 2 | H7: =VLOOKUP(G7,Pesos!A:B,2,0) -> 0.8 | J7: X | K7: 6 | L7: 12 | M7: 1 | N7: Mensal | O7: 1 | S7: 1 | T7: 5593 | U7: 0.25 | V7: =T7*(1-U7) -> 4194.75 | W7: =V7*S7*M7 -> 4194.75
A8: data produto | B8: norte | C8: pa | D8: belem | E8: Ultra OOH | F8: Frontlight | G8: 5 | H8: =VLOOKUP(G8,Pesos!A:B,2,0) -> 0.5 | I8: X | K8: 4 | L8: 8 | M8: 2 | N8: Mensal | O8: 2 | S8: 1 | T8: =(10000+6680)/2 -> 8340 | U8: 0.3 | V8: =T8*(1-U8) -> 5838 | W8: =V8*S8*M8 -> 11676
A9: data produto | B9: norte | C9: pa | D9: belem | E9: Ultra OOH | F9: Empena | G9: 4 | H9: =VLOOKUP(G9,Pesos!A:B,2,0) -> 0.6 | I9: X | K9: 2 | L9: 5 | M9: 3 | N9: Mensal | O9: 3 | S9: 1 | T9: =(13400+28000+16000)/3 -> 19133.333 | U9: 0.25 | V9: =T9*(1-U9) -> 14350 | W9: =V9*S9*M9 -> 43050
A10: data produto | B10: norte | C10: pa | D10: belem | E10: Green Outdoor | F10: Painel de Led | G10: 2 | H10: =VLOOKUP(G10,Pesos!A:B,2,0) -> 0.8 | J10: X | K10: 6 | L10: 12 | M10: 1 | N10: Mensal | O10: 1 | S10: 1 | T10: 2362 | U10: 0.2 | V10: =T10*(1-U10) -> 1889.6 | W10: =V10*S10*M10 -> 1889.6
A11: data produto | B11: norte | C11: pa | D11: belem | E11: Green Outdoor | F11: Outdoor lonado | G11: 1 | H11: =VLOOKUP(G11,Pesos!A:B,2,0) -> 0.9 | I11: X | K11: 15 | L11: 30 | M11: 25 | N11: Mensal | Q11: 25 | S11: 1 | T11: 2650 | U11: 0.2 | V11: =T11*(1-U11) -> 2120 | W11: =V11*S11*M11 -> 53000
A12: data produto | B12: norte | C12: pa | D12: belem | E12: S2X Promoções | F12: Carro de Som | G12: 6 | H12: =VLOOKUP(G12,Pesos!A:B,2,0) -> 0.4 | K12: 7 | L12: 30 | M12: 7 | N12: Diaria 8 horas | O12: 7 | Q12: 7 | S12: 2 | T12: =265*8 -> 2120 | U12: 0.4 | V12: =T12*(1-U12) -> 1272 | W12: =V12*S12*M12 -> 17808
A13: data produto | B13: norte | C13: pa | D13: belem | E13: Prisma OOH | F13: Painel de Led | G13: 2 | H13: =VLOOKUP(G13,Pesos!A:B,2,0) -> 0.8 | J13: X | K13: 6 | L13: 12 | M13: 2 | N13: Mensal | O13: 2 | S13: 1 | T13: 7920 | U13: 0.25 | V13: =T13*(1-U13) -> 5940 | W13: =V13*S13*M13 -> 11880
A14: data produto | B14: norte | C14: pa | D14: belem | E14: Puraka | F14: Painel de Led | G14: 2 | H14: =VLOOKUP(G14,Pesos!A:B,2,0) -> 0.8 | J14: X | K14: 6 | L14: 12 | M14: 2 | N14: Mensal | O14: 2 | S14: 1 | T14: 18500 | U14: 0.6 | V14: =T14*(1-U14) -> 7400 | W14: =V14*S14*M14 -> 14800
A15: data produto | B15: norte | C15: pa | D15: belem | E15: Puraka | F15: Frontlight | G15: 5 | H15: =VLOOKUP(G15,Pesos!A:B,2,0) -> 0.5 | I15: X | K15: 6 | L15: 12 | M15: 2 | N15: Mensal | O15: 2 | S15: 1 | T15: 20500 | U15: 0.58 | V15: =T15*(1-U15) -> 8610 | W15: =V15*S15*M15 -> 17220
A16: data produto | B16: norte | C16: pa | D16: belem | E16: Bureau de Mídia | F16: Painel de Led | G16: 2 | H16: =VLOOKUP(G16,Pesos!A:B,2,0) -> 0.8 | J16: X | K16: 6 | L16: 12 | M16: 1 | N16: Mensal | O16: 1 | S16: 1 | T16: 8125 | U16: 0.15 | V16: =T16*(1-U16) -> 6906.25 | W16: =V16*S16*M16 -> 6906.25
A17: data produto | B17: norte | C17: pa | D17: belem | E17: Bureau de Mídia | F17: Envelopamento Barco | G17: 3 | H17: =VLOOKUP(G17,Pesos!A:B,2,0) -> 0.7 | I17: X | K17: 1 | L17: 3 | M17: 1 | N17: Mensal | O17: 1 | S17: 1 | T17: 73000 | U17: 0 | V17: =T17*(1-U17) -> 73000 | W17: =V17*S17*M17 -> 73000
A19: data promo | B19: norte | C19: pa | D19: belem | E19: Eletromidia | F19: Painel de Led | G19: 1 | H19: =VLOOKUP(G19,Pesos!A:B,2,0) -> 0.9 | J19: x | K19: 6 | L19: 12 | M19: 1 | N19: Semanal | O19: 1 | Q19: 1 | S19: 1 | T19: 5929 | U19: 0.6 | V19: =T19*(1-U19) -> 2371.6 | W19: =V19*S19*M19 -> 2371.6
A20: data promo | B20: norte | C20: pa | D20: belem | E20: WeOOH | F20: Painel de Led | G20: 1 | H20: =VLOOKUP(G20,Pesos!A:B,2,0) -> 0.9 | J20: x | K20: 6 | L20: 12 | M20: 2 | N20: Mensal | O20: 2 | S20: 1 | T20: 27024.15 | U20: 0.75 | V20: =T20*(1-U20) -> 6756.0375 | W20: =V20*S20*M20 -> 13512.075
A21: data promo | B21: norte | C21: pa | D21: belem | E21: Brasil Midia Exterior | F21: Painel de Led | G21: 1 | H21: =VLOOKUP(G21,Pesos!A:B,2,0) -> 0.9 | J21: x | K21: 6 | L21: 12 | M21: 2 | N21: Mensal | O21: 2 | S21: 1 | T21: 7000 | U21: 0.1 | V21: =T21*(1-U21) -> 6300 | W21: =V21*S21*M21 -> 12600
A22: data promo | B22: norte | C22: pa | D22: belem | E22: Brasil Midia Exterior | F22: Frontlight | G22: 5 | H22: =VLOOKUP(G22,Pesos!A:B,2,0) -> 0.5 | I22: x | K22: 4 | L22: 8 | M22: 1 | N22: Mensal | O22: 1 | S22: 1 | T22: 7500 | U22: 0.1 | V22: =T22*(1-U22) -> 6750 | W22: =V22*S22*M22 -> 6750
A23: data promo | B23: norte | C23: pa | D23: belem | E23: Brasil Midia Exterior | F23: Outdoor lonado | G23: 2 | H23: =VLOOKUP(G23,Pesos!A:B,2,0) -> 0.8 | I23: x | K23: 15 | L23: 30 | M23: 30 | N23: Mensal | O23: 30 | S23: 1 | T23: 2650 | U23: 0.1 | V23: =T23*(1-U23) -> 2385 | W23: =V23*S23*M23 -> 71550
A24: data promo | B24: norte | C24: pa | D24: belem | E24: Ultra OOH | F24: Painel de Led | G24: 1 | H24: =VLOOKUP(G24,Pesos!A:B,2,0) -> 0.9 | J24: x | K24: 6 | L24: 12 | M24: 1 | N24: Mensal | O24: 1 | S24: 1 | T24: 5593 | U24: 0.25 | V24: =T24*(1-U24) -> 4194.75 | W24: =V24*S24*M24 -> 4194.75
A25: data promo | B25: norte | C25: pa | D25: belem | E25: Ultra OOH | F25: Frontlight | G25: 5 | H25: =VLOOKUP(G25,Pesos!A:B,2,0) -> 0.5 | I25: x | K25: 4 | L25: 8 | M25: 2 | N25: Mensal | O25: 2 | S25: 1 | T25: =(10000+6680)/2 -> 8340 | U25: 0.3 | V25: =T25*(1-U25) -> 5838 | W25: =V25*S25*M25 -> 11676
A26: data promo | B26: norte | C26: pa | D26: belem | E26: Green Outdoor | F26: Painel de Led | G26: 1 | H26: =VLOOKUP(G26,Pesos!A:B,2,0) -> 0.9 | J26: x | K26: 6 | L26: 12 | M26: 1 | N26: Mensal | O26: 1 | S26: 1 | T26: 2362 | U26: 0.2 | V26: =T26*(1-U26) -> 1889.6 | W26: =V26*S26*M26 -> 1889.6
A27: data promo | B27: norte | C27: pa | D27: belem | E27: Green Outdoor | F27: Outdoor lonado | G27: 2 | H27: =VLOOKUP(G27,Pesos!A:B,2,0) -> 0.8 | I27: x | K27: 15 | L27: 30 | M27: 30 | N27: Mensal | O27: 30 | S27: 1 | T27: 2650 | U27: 0.2 | V27: =T27*(1-U27) -> 2120 | W27: =V27*S27*M27 -> 63600
A28: data promo | B28: norte | C28: pa | D28: belem | E28: S2X Promoções | F28: Carro de Som | G28: 3 | H28: =VLOOKUP(G28,Pesos!A:B,2,0) -> 0.7 | I28: x | K28: 7 | L28: 30 | M28: 7 | N28: Diaria 8 horas | O28: 7 | S28: 1 | T28: =265*8 -> 2120 | U28: 0.4 | V28: =T28*(1-U28) -> 1272 | W28: =V28*S28*M28 -> 8904
A29: data promo | B29: norte | C29: pa | D29: belem | E29: Prisma OOH | F29: Painel de Led | G29: 1 | H29: =VLOOKUP(G29,Pesos!A:B,2,0) -> 0.9 | J29: x | K29: 6 | L29: 12 | M29: 2 | N29: Mensal | O29: 2 | S29: 1 | T29: 7920 | U29: 0.25 | V29: =T29*(1-U29) -> 5940 | W29: =V29*S29*M29 -> 11880
A30: data promo | B30: norte | C30: pa | D30: belem | E30: Puraka | F30: Painel de Led | G30: 1 | H30: =VLOOKUP(G30,Pesos!A:B,2,0) -> 0.9 | J30: x | K30: 6 | L30: 12 | M30: 3 | N30: Mensal | O30: 3 | S30: 1 | T30: 18500 | U30: 0.6 | V30: =T30*(1-U30) -> 7400 | W30: =V30*S30*M30 -> 22200
A31: data promo | B31: norte | C31: pa | D31: belem | E31: Puraka | F31: Frontlight | G31: 5 | H31: =VLOOKUP(G31,Pesos!A:B,2,0) -> 0.5 | I31: x | K31: 4 | L31: 8 | M31: 2 | N31: Mensal | O31: 2 | S31: 1 | T31: 20500 | U31: 0.58 | V31: =T31*(1-U31) -> 8610 | W31: =V31*S31*M31 -> 17220
A32: data promo | B32: norte | C32: pa | D32: belem | E32: Bureau de Mídia | F32: Painel de Led | G32: 1 | H32: =VLOOKUP(G32,Pesos!A:B,2,0) -> 0.9 | J32: x | K32: 6 | L32: 12 | M32: 2 | N32: Mensal | O32: 2 | S32: 1 | T32: 8125 | U32: 0.15 | V32: =T32*(1-U32) -> 6906.25 | W32: =V32*S32*M32 -> 13812.5
A33: data promo | B33: norte | C33: pa | D33: belem | E33: Bureau de Mídia | F33: BikeDoor | G33: 6 | H33: =VLOOKUP(G33,Pesos!A:B,2,0) -> 0.4 | I33: x | K33: 5 | L33: 10 | M33: 4 | N33: Diario | O33: 4 | P33: 4 | Q33: 4 | R33: 4 | S33: 4 | T33: 1944 | U33: 0.15 | V33: =T33*(1-U33) -> 1652.4 | W33: =V33*S33*M33 -> 26438.4
A34: data promo | B34: norte | C34: pa | D34: belem | E34: Cartaxi | F34: Taxi - vidro traseiro | G34: 4 | H34: =VLOOKUP(G34,Pesos!A:B,2,0) -> 0.6 | I34: x | K34: 10 | L34: 35 | M34: 20 | N34: Mensal | O34: 20 | S34: 1 | T34: 1600 | U34: 0.5 | V34: =T34*(1-U34) -> 800 | W34: =V34*S34*M34 -> 16000
A36: ouro produto | B36: norte | C36: pa | D36: belem | E36: WeOOH | F36: Painel de Led | G36: 2 | H36: =VLOOKUP(G36,Pesos!A:B,2,0) -> 0.8 | J36: x | K36: 4 | L36: 8 | M36: 1 | N36: Mensal | O36: 1 | S36: 1 | T36: 27024.15 | U36: 0.75 | V36: =T36*(1-U36) -> 6756.0375 | W36: =V36*S36*M36 -> 6756.0375
A37: ouro produto | B37: norte | C37: pa | D37: belem | E37: Brasil Midia Exterior | F37: Painel de Led | G37: 2 | H37: =VLOOKUP(G37,Pesos!A:B,2,0) -> 0.8 | J37: x | K37: 4 | L37: 8 | M37: 1 | N37: Mensal | O37: 1 | S37: 1 | T37: 7000 | U37: 0.1 | V37: =T37*(1-U37) -> 6300 | W37: =V37*S37*M37 -> 6300
A38: ouro produto | B38: norte | C38: pa | D38: belem | E38: Brasil Midia Exterior | F38: Frontlight | G38: 5 | H38: =VLOOKUP(G38,Pesos!A:B,2,0) -> 0.5 | I38: x | K38: 3 | L38: 6 | M38: 1 | N38: Mensal | O38: 1 | S38: 1 | T38: 7500 | U38: 0.1 | V38: =T38*(1-U38) -> 6750 | W38: =V38*S38*M38 -> 6750
A39: ouro produto | B39: norte | C39: pa | D39: belem | E39: Brasil Midia Exterior | F39: Outdoor lonado | G39: 1 | H39: =VLOOKUP(G39,Pesos!A:B,2,0) -> 0.9 | I39: x | K39: 10 | L39: 20 | M39: 18 | N39: Mensal | O39: 18 | S39: 1 | T39: 2650 | U39: 0.1 | V39: =T39*(1-U39) -> 2385 | W39: =V39*S39*M39 -> 42930
A40: ouro produto | B40: norte | C40: pa | D40: belem | E40: Ultra OOH | F40: Painel de Led | G40: 2 | H40: =VLOOKUP(G40,Pesos!A:B,2,0) -> 0.8 | J40: x | K40: 4 | L40: 8 | M40: 1 | N40: Mensal | O40: 1 | S40: 1 | T40: 5593 | U40: 0.25 | V40: =T40*(1-U40) -> 4194.75 | W40: =V40*S40*M40 -> 4194.75
A41: ouro produto | B41: norte | C41: pa | D41: belem | E41: Ultra OOH | F41: Frontlight | G41: 5 | H41: =VLOOKUP(G41,Pesos!A:B,2,0) -> 0.5 | I41: x | K41: 3 | L41: 6 | M41: 2 | N41: Mensal | O41: 2 | S41: 1 | T41: =(10000+6680)/2 -> 8340 | U41: 0.3 | V41: =T41*(1-U41) -> 5838 | W41: =V41*S41*M41 -> 11676
A42: ouro produto | B42: norte | C42: pa | D42: belem | E42: Ultra OOH | F42: Empena | G42: 4 | H42: =VLOOKUP(G42,Pesos!A:B,2,0) -> 0.6 | I42: x | K42: 1 | L42: 3 | M42: 3 | N42: Mensal | O42: 3 | S42: 1 | T42: =(13400+28000+16000)/3 -> 19133.333 | U42: 0.25 | V42: =T42*(1-U42) -> 14350 | W42: =V42*S42*M42 -> 43050
A43: ouro produto | B43: norte | C43: pa | D43: belem | E43: Green Outdoor | F43: Painel de Led | G43: 2 | H43: =VLOOKUP(G43,Pesos!A:B,2,0) -> 0.8 | J43: x | K43: 4 | L43: 8 | M43: 1 | N43: Mensal | O43: 1 | S43: 1 | T43: 2362 | U43: 0.2 | V43: =T43*(1-U43) -> 1889.6 | W43: =V43*S43*M43 -> 1889.6
A44: ouro produto | B44: norte | C44: pa | D44: belem | E44: Green Outdoor | F44: Outdoor lonado | G44: 1 | H44: =VLOOKUP(G44,Pesos!A:B,2,0) -> 0.9 | I44: x | K44: 10 | L44: 20 | M44: 18 | N44: Mensal | O44: 18 | S44: 1 | T44: 2650 | U44: 0.2 | V44: =T44*(1-U44) -> 2120 | W44: =V44*S44*M44 -> 38160
A45: ouro produto | B45: norte | C45: pa | D45: belem | E45: S2X Promoções | F45: Carro de Som | G45: 6 | H45: =VLOOKUP(G45,Pesos!A:B,2,0) -> 0.4 | I45: x | K45: 5 | L45: 20 | M45: 4 | N45: Diaria 8 horas | O45: 5 | Q45: 5 | S45: 2 | T45: =265*8 -> 2120 | U45: 0.4 | V45: =T45*(1-U45) -> 1272 | W45: =V45*S45*M45 -> 10176
A46: ouro produto | B46: norte | C46: pa | D46: belem | E46: Prisma OOH | F46: Painel de Led | G46: 2 | H46: =VLOOKUP(G46,Pesos!A:B,2,0) -> 0.8 | J46: x | K46: 4 | L46: 8 | M46: 1 | N46: Mensal | O46: 1 | S46: 1 | T46: 7920 | U46: 0.25 | V46: =T46*(1-U46) -> 5940 | W46: =V46*S46*M46 -> 5940
A47: ouro produto | B47: norte | C47: pa | D47: belem | E47: Puraka | F47: Painel de Led | G47: 2 | H47: =VLOOKUP(G47,Pesos!A:B,2,0) -> 0.8 | J47: x | K47: 4 | L47: 8 | M47: 1 | N47: Mensal | O47: 1 | S47: 1 | T47: 18500 | U47: 0.6 | V47: =T47*(1-U47) -> 7400 | W47: =V47*S47*M47 -> 7400
A48: ouro produto | B48: norte | C48: pa | D48: belem | E48: Puraka | F48: Frontlight | G48: 5 | H48: =VLOOKUP(G48,Pesos!A:B,2,0) -> 0.5 | I48: x | K48: 3 | L48: 6 | M48: 1 | N48: Mensal | O48: 1 | S48: 1 | T48: 20500 | U48: 0.58 | V48: =T48*(1-U48) -> 8610 | W48: =V48*S48*M48 -> 8610
A49: ouro produto | B49: norte | C49: pa | D49: belem | E49: Bureau de Mídia | F49: Painel de Led | G49: 2 | H49: =VLOOKUP(G49,Pesos!A:B,2,0) -> 0.8 | J49: x | K49: 4 | L49: 8 | M49: 1 | N49: Mensal | O49: 1 | S49: 1 | T49: 8125 | U49: 0.15 | V49: =T49*(1-U49) -> 6906.25 | W49: =V49*S49*M49 -> 6906.25
A50: ouro produto | B50: norte | C50: pa | D50: belem | E50: Bureau de Mídia | F50: Envelopamento Barco | G50: 3 | H50: =VLOOKUP(G50,Pesos!A:B,2,0) -> 0.7 | I50: x | K50: 1 | L50: 3 | M50: 1 | N50: Mensal | O50: 1 | S50: 1 | T50: 73000 | U50: 0 | V50: =T50*(1-U50) -> 73000 | W50: =V50*S50*M50 -> 73000
A52: ouro promo | B52: norte | C52: pa | D52: belem | E52: WeOOH | F52: Painel de Led | G52: 1 | H52: =VLOOKUP(G52,Pesos!A:B,2,0) -> 0.9 | J52: x | K52: 4 | L52: 8 | M52: 1 | N52: Mensal | O52: 1 | S52: 1 | T52: 27024.15 | U52: 0.75 | V52: =T52*(1-U52) -> 6756.0375 | W52: =V52*S52*M52 -> 6756.0375
A53: ouro promo | B53: norte | C53: pa | D53: belem | E53: Brasil Midia Exterior | F53: Painel de Led | G53: 1 | H53: =VLOOKUP(G53,Pesos!A:B,2,0) -> 0.9 | J53: x | K53: 4 | L53: 8 | M53: 1 | N53: Mensal | O53: 1 | S53: 1 | T53: 7000 | U53: 0.1 | V53: =T53*(1-U53) -> 6300 | W53: =V53*S53*M53 -> 6300
A54: ouro promo | B54: norte | C54: pa | D54: belem | E54: Brasil Midia Exterior | F54: Frontlight | I54: x | K54: 3 | L54: 6 | M54: 1 | N54: Mensal | O54: 1 | S54: 1 | T54: 7500 | U54: 0.1 | V54: =T54*(1-U54) -> 6750 | W54: =V54*S54*M54 -> 6750
A55: ouro promo | B55: norte | C55: pa | D55: belem | E55: Brasil Midia Exterior | F55: Outdoor lonado | G55: 2 | H55: =VLOOKUP(G55,Pesos!A:B,2,0) -> 0.8 | I55: x | K55: 10 | L55: 20 | M55: 18 | N55: Mensal | O55: 18 | S55: 1 | T55: 2650 | U55: 0.1 | V55: =T55*(1-U55) -> 2385 | W55: =V55*S55*M55 -> 42930
A56: ouro promo | B56: norte | C56: pa | D56: belem | E56: Ultra OOH | F56: Painel de Led | G56: 1 | H56: =VLOOKUP(G56,Pesos!A:B,2,0) -> 0.9 | J56: x | K56: 4 | L56: 8 | M56: 1 | N56: Mensal | O56: 1 | S56: 1 | T56: 5593 | U56: 0.25 | V56: =T56*(1-U56) -> 4194.75 | W56: =V56*S56*M56 -> 4194.75
A57: ouro promo | B57: norte | C57: pa | D57: belem | E57: Ultra OOH | F57: Frontlight | G57: 5 | H57: =VLOOKUP(G57,Pesos!A:B,2,0) -> 0.5 | I57: x | K57: 3 | L57: 6 | M57: 2 | N57: Mensal | O57: 2 | S57: 1 | T57: =(10000+6680)/2 -> 8340 | U57: 0.3 | V57: =T57*(1-U57) -> 5838 | W57: =V57*S57*M57 -> 11676
A58: ouro promo | B58: norte | C58: pa | D58: belem | E58: Green Outdoor | F58: Painel de Led | G58: 1 | H58: =VLOOKUP(G58,Pesos!A:B,2,0) -> 0.9 | J58: x | K58: 4 | L58: 8 | M58: 1 | N58: Mensal | O58: 1 | S58: 1 | T58: 2362 | U58: 0.2 | V58: =T58*(1-U58) -> 1889.6 | W58: =V58*S58*M58 -> 1889.6
A59: ouro promo | B59: norte | C59: pa | D59: belem | E59: Green Outdoor | F59: Outdoor lonado | G59: 2 | H59: =VLOOKUP(G59,Pesos!A:B,2,0) -> 0.8 | I59: x | K59: 10 | L59: 20 | M59: 18 | N59: Mensal | O59: 18 | S59: 1 | T59: 2650 | U59: 0.2 | V59: =T59*(1-U59) -> 2120 | W59: =V59*S59*M59 -> 38160
A60: ouro promo | B60: norte | C60: pa | D60: belem | E60: S2X Promoções | F60: Carro de Som | G60: 3 | H60: =VLOOKUP(G60,Pesos!A:B,2,0) -> 0.7 | I60: x | K60: 5 | L60: 20 | M60: 4 | N60: Diaria 8 horas | O60: 5 | Q60: 5 | S60: 2 | T60: =265*8 -> 2120 | U60: 0.4 | V60: =T60*(1-U60) -> 1272 | W60: =V60*S60*M60 -> 10176
A61: ouro promo | B61: norte | C61: pa | D61: belem | E61: Prisma OOH | F61: Painel de Led | G61: 1 | H61: =VLOOKUP(G61,Pesos!A:B,2,0) -> 0.9 | J61: x | K61: 4 | L61: 8 | M61: 1 | N61: Mensal | O61: 1 | S61: 1 | T61: 7920 | U61: 0.25 | V61: =T61*(1-U61) -> 5940 | W61: =V61*S61*M61 -> 5940
A62: ouro promo | B62: norte | C62: pa | D62: belem | E62: Puraka | F62: Painel de Led | G62: 1 | H62: =VLOOKUP(G62,Pesos!A:B,2,0) -> 0.9 | J62: x | K62: 4 | L62: 8 | M62: 1 | N62: Mensal | O62: 1 | S62: 1 | T62: 18500 | U62: 0.6 | V62: =T62*(1-U62) -> 7400 | W62: =V62*S62*M62 -> 7400
A63: ouro promo | B63: norte | C63: pa | D63: belem | E63: Puraka | F63: Frontlight | G63: 5 | H63: =VLOOKUP(G63,Pesos!A:B,2,0) -> 0.5 | I63: x | K63: 3 | L63: 6 | M63: 1 | N63: Mensal | O63: 1 | S63: 1 | T63: 20500 | U63: 0.58 | V63: =T63*(1-U63) -> 8610 | W63: =V63*S63*M63 -> 8610
A64: ouro promo | B64: norte | C64: pa | D64: belem | E64: Bureau de Mídia | F64: Painel de Led | G64: 1 | H64: =VLOOKUP(G64,Pesos!A:B,2,0) -> 0.9 | J64: x | K64: 4 | L64: 8 | M64: 1 | N64: Mensal | O64: 1 | S64: 1 | T64: 8125 | U64: 0.15 | V64: =T64*(1-U64) -> 6906.25 | W64: =V64*S64*M64 -> 6906.25
A65: ouro promo | B65: norte | C65: pa | D65: belem | E65: Bureau de Mídia | F65: BikeDoor | G65: 6 | H65: =VLOOKUP(G65,Pesos!A:B,2,0) -> 0.4 | I65: x | K65: 5 | L65: 10 | M65: 4 | N65: Diario | O65: 4 | P65: 4 | Q65: 4 | R65: 4 | S65: 4 | T65: 1944 | U65: 0.15 | V65: =T65*(1-U65) -> 1652.4 | W65: =V65*S65*M65 -> 26438.4
A66: ouro promo | B66: norte | C66: pa | D66: belem | E66: Cartaxi | F66: Taxi - vidro traseiro | G66: 4 | H66: =VLOOKUP(G66,Pesos!A:B,2,0) -> 0.6 | I66: x | K66: 10 | L66: 35 | M66: 20 | N66: Mensal | O66: 20 | S66: 1 | T66: 1600 | U66: 0.5 | V66: =T66*(1-U66) -> 800 | W66: =V66*S66*M66 -> 16000
A68: prata | B68: norte | C68: pa | D68: belem | E68: WeOOH | F68: Painel de Led | G68: 2 | H68: =VLOOKUP(G68,Pesos!A:B,2,0) -> 0.8 | J68: x | K68: 6 | L68: 12 | M68: 1 | N68: Mensal | O68: 1 | S68: 1 | T68: 27024.15 | U68: 0.75 | V68: =T68*(1-U68) -> 6756.0375 | W68: =V68*S68*M68 -> 6756.0375
A69: prata | B69: norte | C69: pa | D69: belem | E69: Brasil Midia Exterior | F69: Painel de Led | G69: 2 | H69: =VLOOKUP(G69,Pesos!A:B,2,0) -> 0.8 | J69: x | K69: 6 | L69: 12 | M69: 1 | N69: Mensal | O69: 1 | S69: 1 | T69: 7000 | U69: 0.1 | V69: =T69*(1-U69) -> 6300 | W69: =V69*S69*M69 -> 6300
A70: prata | B70: norte | C70: pa | D70: belem | E70: Brasil Midia Exterior | F70: Frontlight | G70: 3 | H70: =VLOOKUP(G70,Pesos!A:B,2,0) -> 0.7 | I70: x | K70: 4 | L70: 8 | M70: 1 | N70: Mensal | O70: 1 | S70: 1 | T70: 7500 | U70: 0.1 | V70: =T70*(1-U70) -> 6750 | W70: =V70*S70*M70 -> 6750
A71: prata | B71: norte | C71: pa | D71: belem | E71: Brasil Midia Exterior | F71: Outdoor lonado | G71: 1 | H71: =VLOOKUP(G71,Pesos!A:B,2,0) -> 0.9 | I71: x | K71: 15 | L71: 30 | M71: 13 | N71: Mensal | O71: 13 | S71: 1 | T71: 2650 | U71: 0.1 | V71: =T71*(1-U71) -> 2385 | W71: =V71*S71*M71 -> 31005
A72: prata | B72: norte | C72: pa | D72: belem | E72: Ultra OOH | F72: Painel de Led | G72: 2 | H72: =VLOOKUP(G72,Pesos!A:B,2,0) -> 0.8 | J72: x | K72: 6 | L72: 12 | M72: 1 | N72: Mensal | O72: 1 | S72: 1 | T72: 5593 | U72: 0.25 | V72: =T72*(1-U72) -> 4194.75 | W72: =V72*S72*M72 -> 4194.75
A73: prata | B73: norte | C73: pa | D73: belem | E73: Ultra OOH | F73: Frontlight | G73: 3 | H73: =VLOOKUP(G73,Pesos!A:B,2,0) -> 0.7 | I73: x | K73: 4 | L73: 8 | M73: 2 | N73: Mensal | O73: 2 | S73: 1 | T73: =(10000+6680)/2 -> 8340 | U73: 0.3 | V73: =T73*(1-U73) -> 5838 | W73: =V73*S73*M73 -> 11676
A74: prata | B74: norte | C74: pa | D74: belem | E74: Green Outdoor | F74: Painel de Led | G74: 2 | H74: =VLOOKUP(G74,Pesos!A:B,2,0) -> 0.8 | J74: x | K74: 6 | L74: 12 | M74: 1 | N74: Mensal | O74: 1 | S74: 1 | T74: 2362 | U74: 0.2 | V74: =T74*(1-U74) -> 1889.6 | W74: =V74*S74*M74 -> 1889.6
A75: prata | B75: norte | C75: pa | D75: belem | E75: Green Outdoor | F75: Outdoor lonado | G75: 1 | H75: =VLOOKUP(G75,Pesos!A:B,2,0) -> 0.9 | I75: x | K75: 15 | L75: 30 | M75: 13 | N75: Mensal | O75: 13 | S75: 1 | T75: 2650 | U75: 0.2 | V75: =T75*(1-U75) -> 2120 | W75: =V75*S75*M75 -> 27560
A76: prata | B76: norte | C76: pa | D76: belem | E76: S2X Promoções | F76: Carro de Som | G76: 4 | H76: =VLOOKUP(G76,Pesos!A:B,2,0) -> 0.6 | I76: x | K76: 7 | L76: 30 | M76: 2 | N76: Diaria 8 horas | O76: 2 | Q76: 2 | S76: 4 | T76: =265*8 -> 2120 | U76: 0.4 | V76: =T76*(1-U76) -> 1272 | W76: =V76*S76*M76 -> 10176
A77: prata | B77: norte | C77: pa | D77: belem | E77: Prisma OOH | F77: Painel de Led | G77: 2 | H77: =VLOOKUP(G77,Pesos!A:B,2,0) -> 0.8 | J77: x | K77: 6 | L77: 12 | M77: 2 | N77: Mensal | O77: 2 | S77: 1 | T77: 7920 | U77: 0.25 | V77: =T77*(1-U77) -> 5940 | W77: =V77*S77*M77 -> 11880
A78: prata | B78: norte | C78: pa | D78: belem | E78: Puraka | F78: Painel de Led | G78: 2 | H78: =VLOOKUP(G78,Pesos!A:B,2,0) -> 0.8 | J78: x | K78: 6 | L78: 12 | M78: 2 | N78: Mensal | O78: 2 | S78: 1 | T78: 18500 | U78: 0.6 | V78: =T78*(1-U78) -> 7400 | W78: =V78*S78*M78 -> 14800
A79: prata | B79: norte | C79: pa | D79: belem | E79: Puraka | F79: Frontlight | G79: 3 | H79: =VLOOKUP(G79,Pesos!A:B,2,0) -> 0.7 | I79: x | K79: 4 | L79: 8 | M79: 2 | N79: Mensal | O79: 2 | S79: 1 | T79: 20500 | U79: 0.58 | V79: =T79*(1-U79) -> 8610 | W79: =V79*S79*M79 -> 17220
A80: prata | B80: norte | C80: pa | D80: belem | E80: Bureau de Mídia | F80: Painel de Led | G80: 2 | H80: =VLOOKUP(G80,Pesos!A:B,2,0) -> 0.8 | J80: x | K80: 6 | L80: 12 | M80: 1 | N80: Mensal | O80: 1 | S80: 1 | T80: 8125 | U80: 0.15 | V80: =T80*(1-U80) -> 6906.25 | W80: =V80*S80*M80 -> 6906.25
E86: cpf mínimo | F86: cpf plano | G86: cpf máximo
A87: DATA PRODUTO | E87: =F87*(1-10%) -> 4352.4347 | F87: =BELEM!S62 -> 4836.0385 | G87: =F87*(1+15%) -> 5561.4443
A88: DATA PROMO | E88: =F88*(1-25%) -> 2116.2027 | F88: =BELEM!S102 -> 2821.6036 | G88: =F88*(1+5%) -> 2962.6838
A89: OURO PRODUTO | E89: =F89*(1-15%) -> 4587.7515 | F89: =BELEM!S150 -> 5397.3547 | G89: =F89*(1+15%) -> 6206.9579
A90: OURO PROMO | E90: =F90*(1-25%) -> 2267.0036 | F90: =BELEM!S192 -> 3022.6714 | G90: =F90*(1+5%) -> 3173.805
A91: PRATA | E91: =F91*(1-25%) -> 3189.437 | F91: =BELEM!S234 -> 4252.5827 | G91: =F91*(1+5%) -> 4465.2118
E93: ranking semanas - distribuição investimento
A94: DATA PRODUTO | E94: =BELEM!I58 -> 0.60714286 | G94: =BELEM!K58 -> 0.39285714
A95: DATA PROMO | E95: 0.55555556 | F95: 0.076388889 | G95: 0.29166667 | H95: 0.076388889
A96: OURO PRODUTO | E96: 0.62295082 | G96: 0.37704918
A97: OURO PROMO | E97: 0.55045872 | F97: 0.08 | G97: 0.37
A98: PRATA | E98: 0.65909091 | G98: 0.34090909
E102: ranking semanas - distribuição audiência
A103: DATA PRODUTO | E103: =BELEM!I61 -> 0.2712766 | F103: =BELEM!J61 -> 0.2287234 | G103: =BELEM!K61 -> 0.2712766 | H103: =BELEM!L61 -> 0.2287234
A104: DATA PROMO | E104: 0.2484472 | F104: 0.25776398 | G104: 0.2484472 | H104: 0.24534161
A105: OURO PRODUTO | E105: 0.35 | F105: 0.3 | G105: 0.35
A106: OURO PROMO | E106: 0.35 | F106: 0.29 | G106: 0.36
A107: PRATA | E107: 0.35 | F107: 0.29 | G107: 0.36

Sheet BOA VISTA
A1: ESTUDO BOA VISTA
A2: IBGE 2024/ CENSO 2022
A7: INVESTIMENTO BOA VISTA CAPITAL OOH 2024 | B7: 249713.29
A8: INVESTIMENTO RORAIMA OOH 2024 | B8: 249713.29
A10: R$ BRUTO BOA VISTA CAPITAL - 2025 OOH | B10: 657396.25
A11: BUDGET BRUTO RORAIMA 2025 OOH (100%) | B11: 657396.25
A14: Exclusão de Bronze
A15: CICLOS/MEDALHAS | C15: % BUDGET/CICLO | D15: R$ MEDALHA | E15: R$ UNIT. MEDALHAS
A16: Data | B16: 3 - 2 produto/1 promo | C16: 0.44 | D16: 289254.35 | E16: 96418.117
A17: Ouro | B17: 5 - 4 produto/ 1 promo | C17: 0.48 | D17: 315550.2 | E17: 63110.04
A18: Prata | B18: 2 | C18: 0.08 | D18: 52591.7 | E18: 26295.85
B19: 10 ciclos | C19: 1 | D19: 657396.25
A21: População Capital | B21: 413486
A22: População Target - AS ABC 18/49 (logan) | B22: 223605
E23: Cobertura total - Data Produto | F23: 39% | H23: Cobertura total - Data Promo | J23: 0.49
E24: Frequencia | F24: 26 | H24: Frequencia | J24: 35
E25: TRP | F25: 326 | H25: TRP | J25: 590
E26: OTS | F26: 1.345.892 | H26: OTS | J26: 2145987
A28: Programação - Ciclo Data Produto
A30: 1 CICLO | T30: TOTAL ANO / CICLO
A31: Praça | B31: Exibidores | C31: Pen/Aff | D31: Canais | E31: Formato | F31: Range de volume ideal | G31: Qtdade | H31: Periodicidade | I31: Mês Base | M31: TT | N31: R$ Unit Bruto | O31: Desconto | P31: R$ Unit Bruto | Q31: R$ TT Bruto | R31: C.P.M. Formato | S31: % | T31: R$ Total | U31: AMBIENTES | Z31: FORMATO | AB31: EMPRESAS
I32: S1 | J32: S2 | K32: S3 | L32: S4 | M32: Flight | N32: Tabela | O32: (%) | P32: Negociado | Q32: Negociado | T32: ano
A33: DATAS MÃES/NATAL | U33: GDES | V33: MUB | W33: TRANSP | X33: AERO | Y33: OPORT | Z33: ESTÁTICO | AA33: DIGITAL | AB33: M2 | AC33: TELAS PROMO | AD33: KALLAS
A35: Boa Vista - RR | B35: M2 comunicações | C35: 50/156 | D35: Frontlight | E35: Estático | F35: 3/5 | G35: 3 | H35: Mensal | I35: 3 | M35: 1 | N35: 4480 | O35: 0.2 | P35: =N35*(1-O35) -> 3584 | Q35: =P35*M35*G35 -> 10752 | R35: =(Q35+Q36+#REF!+#REF!)/E11*1000 -> #REF! | S35: =Q35/$Q$43 -> 0.25844911 | T35: =Q35*2 -> 21504 | U35: =T35 -> 21504 | AA35: =T35 -> 21504 | AB35: =T35 -> 21504
A36: Boa Vista - RR | B36: Telas Promo | C36: 50/156 | D36: Painel de Led | E36: Digital | F36: 2/4 | G36: 2 | H36: Mensal | I36: 2 | M36: 1 | N36: 5000 | O36: 0.25 | P36: =N36*(1-O36) -> 3750 | Q36: =P36*M36*G36 -> 7500 | R36: =(Q36+Q37+#REF!+#REF!)/E12*1000 -> #REF! | S36: =Q36/$Q$43 -> 0.18027979 | T36: =Q36*2 -> 15000 | U36: =T36 -> 15000 | Z36: =T36 -> 15000 | AC36: =T36 -> 15000
A37: Boa Vista - RR | B37: Telas Promo | C37: 50/156 | D37: Circuito interno Led | E37: Digital | F37: 1/2 | G37: 2 | H37: Mensal | I37: 2 | M37: 1 | N37: 5000 | O37: 0.25 | P37: =N37*(1-O37) -> 3750 | Q37: =P37*M37*G37 -> 7500 | S37: =Q37/$Q$43 -> 0.18027979 | T37: =Q37*2 -> 15000 | V37: =T37 -> 15000 | Z37: =T37 -> 15000 | AC37: =T37 -> 15000
A38: Boa Vista - RR | B38: Telas Promo | C38: 50/156 | D38: Frontlight | E38: Estático | F38: 3/5 | G38: 2 | H38: Mensal | I38: 2 | M38: 1 | N38: 5500 | O38: 0.25 | P38: =N38*(1-O38) -> 4125 | Q38: =P38*M38*G38 -> 8250 | S38: =Q38/$Q$43 -> 0.19830777 | T38: =Q38*2 -> 16500 | U38: =T38 -> 16500 | AA38: =T38 -> 16500 | AC38: =U38 -> 16500
AD39: =T39 -> 0
A40: Boa Vista - RR | B40: Aeroporto | T40: =Q40*2 -> 0 | X40: =T40 -> 0
A41: Boa Vista - RR | B41: Oportunidades | D41: Marítimos / Ativação | Q41: 7600 | S41: =Q41/Q43 -> 0.18268352 | T41: =Q41*2 -> 15200 | Y41: =T41 -> 15200
A43: Total faces compra | I43: =I38+I37+I36+I35 -> 9 | M43: =SUM(I43:L43) -> 9 | Q43: =SUM(Q35:Q42) -> 41602 | S43: =SUM(S35:S41) -> 1 | T43: =SUM(T35:T42) -> 83204 | U43: =SUM(U35:U41) -> 53004 | V43: =SUM(V35:V41) -> 15000 | W43: =SUM(W35:W41) -> 0 | X43: =SUM(X35:X41) -> 0 | Y43: =SUM(Y35:Y41) -> 15200 | Z43: =SUM(Z35:Z41) -> 30000 | AA43: =SUM(AA35:AA41) -> 38004 | AB43: =SUM(AB35:AB42) -> 21504 | AC43: =SUM(AC34:AC40) -> 46500 | AD43: =SUM(AD34:AD40) -> 0
A44: Total faces simulação | I44: =I38+I37+I36+I35 -> 9 | J44: =I38+I37+I36+I35 -> 9 | K44: =I38+I37+I36+I35 -> 9 | L44: =I38+I37+I36+I35 -> 9 | M44: =SUM(I44:L44) -> 36 | U44: =U43/T43 -> 0.63703668 | V44: =V43/T43 -> 0.18027979 | W44: =W43/T43 -> 0 | X44: =X43/T43 -> 0 | Y44: =Y43/T43 -> 0.18268352 | Z44: =Z43/T43 -> 0.36055959 | AA44: =AA43/T43 -> 0.45675689
A45: Grandes Formatos | Q45: =U43/2 -> 26502 | S45: =Q45/Q50 -> 0.63703668 | Y45: =SUM(U35:Y42) -> 83204 | Z45: =I36+I37 -> 4 | AA45: =I35+I38 -> 5
A46: MUB | Q46: =V43/2 -> 7500 | S46: =Q46/Q50 -> 0.18027979 | T46: =Q43/M43 -> 4622.4444 | U46: CPFACE | Z46: =Z45/M43 -> 0.44444444 | AA46: =AA45/M43 -> 0.55555556
A47: Transportes | Q47: =W43/2 -> 0 | S47: =Q47/Q50 -> 0 | Z47: SHARE FACES
A48: Oportunidades | Q48: =Y43/2 -> 7600 | S48: =Q48/Q50 -> 0.18268352
A49: Aeroporto | Q49: =X43/2 -> 0 | S49: =Q49/Q50 -> 0
Q50: =SUM(Q45:Q49) -> 41602 | S50: =SUM(S45:S49) -> 1
A52: Programação - Ciclo Data Promo
A54: 1 CICLO | T54: TOTAL ANO / CICLO
A55: Praça | B55: Exibidores | C55: Pen/Aff | D55: Canais | E55: Formato | F55: Range de volume ideal | G55: Qtdade | H55: Periodicidade | I55: Mês Base | M55: TT | N55: R$ Unit Bruto | O55: Desconto | P55: R$ Unit Bruto | Q55: R$ TT Bruto | R55: C.P.M. Formato | S55: % | T55: R$ Total | U55: AMBIENTES | Z55: FORMATO | AB55: EMPRESAS
I56: S1 | J56: S2 | K56: S3 | L56: S4 | M56: Flight | N56: Tabela | O56: (%) | P56: Negociado | Q56: Negociado | T56: ano
A57: DATAS BW | U57: GDES | V57: MUB | W57: TRANSP | X57: AERO | Y57: OPORT | Z57: ESTÁTICO | AA57: DIGITAL | AB57: M2 | AC57: TELAS PROMO | AD57: KALLAS
A59: Boa Vista - RR | B59: M2 comunicações | C59: 50/156 | D59: Frontlight | E59: Estático | F59: 2/3 | G59: 2 | H59: Mensal | I59: 2 | M59: 1 | N59: 4480 | O59: 0.2 | P59: =N59*(1-O59) -> 3584 | Q59: =P59*M59*G59 -> 7168 | R59: =(Q59+Q60+#REF!+#REF!)/E35*1000 -> #REF! | S59: =Q59/$Q$70 -> 0.17012793 | T59: =Q59 -> 7168 | U59: =T59 -> 7168 | AA59: =T59 -> 7168 | AB59: =T59 -> 7168
A60: Boa Vista - RR | B60: Telas Promo | C60: 50/156 | D60: Painel de Led | E60: Digital | F60: 2/4 | G60: 2 | H60: Mensal | I60: 2 | M60: 1 | N60: 5000 | O60: 0.25 | P60: =N60*(1-O60) -> 3750 | Q60: =P60*M60*G60 -> 7500 | R60: =(Q60+Q61+#REF!+#REF!)/E36*1000 -> #REF! | S60: =Q60/$Q$70 -> 0.17800774 | T60: =Q60 -> 7500 | U60: =T60 -> 7500 | Z60: =T60 -> 7500 | AC60: =T60 -> 7500
A61: Boa Vista - RR | B61: Telas Promo | C61: 50/156 | D61: Circuito interno Led | E61: Digital | F61: 1/2 | G61: 2 | H61: Mensal | I61: 2 | M61: 1 | N61: 5000 | O61: 0.25 | P61: =N61*(1-O61) -> 3750 | Q61: =P61*M61*G61 -> 7500 | S61: =Q61/$Q$70 -> 0.17800774 | T61: =Q61 -> 7500 | V61: =T61 -> 7500 | Z61: =T61 -> 7500 | AC61: =T61 -> 7500
A62: Boa Vista - RR | B62: Telas Promo | C62: 50/156 | D62: Frontlight | E62: Estático | F62: 1/2 | G62: 1 | H62: Mensal | I62: 1 | M62: 1 | N62: 5500 | O62: 0.25 | P62: =N62*(1-O62) -> 4125 | Q62: =P62*M62*G62 -> 4125 | S62: =Q62/$Q$70 -> 0.097904256 | T62: =Q62 -> 4125 | U62: =T62 -> 4125 | AA62: =T62 -> 4125 | AC62: =T62 -> 4125
A63: Boa Vista - RR | B63: Cartaxi | C63: 30/155 | D63: Vidro traseiro + interno | E63: Estático | F63: 3/8 | G63: 8 | H63: Mensal | I63: 8 | M63: 1 | N63: 1600 | O63: 0.7 | P63: =N63*(1-O63) -> 480 | Q63: =P63*M63*G63 -> 3840 | S63: =Q63/$Q$70 -> 0.091139962 | T63: =Q63 -> 3840 | W63: =T63 -> 3840 | AD63: =T63 -> 3840
A64: Boa Vista - RR | B64: Telas Promo | C64: 63/153 | D64: Busdoor | E64: Estático | F64: 2/5 | G64: 4 | H64: Mensal | I64: 4 | M64: 1 | N64: 2000 | O64: 0.45 | P64: =N64*(1-O64) -> 1100 | Q64: =P64*M64*G64 -> 4400 | S64: =Q64/$Q$70 -> 0.10443121 | T64: =Q64 -> 4400 | W64: =T64 -> 4400 | AC64: =T64 -> 4400
A67: Boa Vista - RR | B67: Aeroporto | T67: =Q67*2 -> 0 | X67: =T67 -> 0
A68: Boa Vista - RR | B68: Oportunidades | D68: Marítimos / Ativação | Q68: 7600 | S68: =Q68/Q70 -> 0.18038117 | T68: =Q68 -> 7600 | Y68: =T68 -> 7600
A70: Total faces compra | I70: =I62+I61+I60+I59+I63+I64 -> 19 | M70: =SUM(I70:L70) -> 19 | Q70: =SUM(Q59:Q69) -> 42133 | S70: =SUM(S59:S68) -> 1 | T70: =SUM(T59:T69) -> 42133 | U70: =SUM(U59:U68) -> 18793 | V70: =SUM(V59:V68) -> 7500 | W70: =SUM(W59:W68) -> 8240 | X70: =SUM(X59:X68) -> 0 | Y70: =SUM(Y59:Y68) -> 7600 | Z70: =SUM(Z59:Z68) -> 15000 | AA70: =SUM(AA59:AA68) -> 11293 | AB70: =SUM(AB59:AB69) -> 7168 | AC70: =SUM(AC59:AC69) -> 23525 | AD70: =SUM(AD59:AD69) -> 3840
A71: Total faces simulação | I71: =I62+I61+I60+I59+I63+I64 -> 19 | J71: =I62+I61+I60+I59+I63+I64 -> 19 | K71: =I62+I61+I60+I59+I63+I64 -> 19 | L71: =I62+I61+I60+I59+I63+I64 -> 19 | M71: =SUM(I71:L71) -> 76 | U71: =U70/T70 -> 0.44603992 | V71: =V70/T70 -> 0.17800774 | W71: =W70/T70 -> 0.19557117 | X71: =X70/T70 -> 0 | Y71: =Y70/T70 -> 0.18038117 | Z71: =Z70/T70 -> 0.35601547 | AA71: =AA70/T70 -> 0.26803218
A72: Grandes Formatos | Q72: =U70/2 -> 9396.5 | S72: =Q72/Q77 -> 0.44603992 | Y72: =SUM(U59:Y69) -> 42133 | Z72: =I60+I61+I63+I64 -> 16 | AA72: =I59+I62 -> 3
A73: MUB | Q73: =V70/2 -> 3750 | S73: =Q73/Q77 -> 0.17800774 | T73: =Q70/M70 -> 2217.5263 | U73: CPFACE | Z73: =Z72/M70 -> 0.84210526 | AA73: =AA72/M70 -> 0.15789474
A74: Transportes | Q74: =W70/2 -> 4120 | S74: =Q74/Q77 -> 0.19557117 | Z74: SHARE FACES
A75: Oportunidades | Q75: =Y70/2 -> 3800 | S75: =Q75/Q77 -> 0.18038117
A76: Aeroporto | Q76: =X70/2 -> 0 | S76: =Q76/Q77 -> 0
Q77: =SUM(Q72:Q76) -> 21066.5 | S77: =SUM(S72:S76) -> 1
E79: Cobertura total - Ouro Produto | F79: 32% | G79: Cobertura total - Ouro Promo | I79: 0.42
E80: Frequencia | F80: 20 | G80: Frequencia | I80: 28
E81: TRP | F81: 234 | G81: TRP | I81: 412
E82: OTS | F82: 989.689 | G82: OTS | I82: 1894560
A84: Programação - Ciclo Ouro Produto
A86: 1 CICLO | T86: TOTAL ANO / CICLO
A87: Praça | B87: Exibidores | C87: Pen/Aff | D87: Canais | E87: Formato | F87: Range de volume ideal | G87: Qtdade | H87: Periodicidade | I87: Mês Base | M87: TT | N87: R$ Unit Bruto | O87: Desconto | P87: R$ Unit Bruto | Q87: R$ TT Bruto | R87: C.P.M. Formato | S87: % | T87: R$ Total | U87: AMBIENTES | Z87: FORMATO | AB87: EMPRESAS
I88: S1 | J88: S2 | K88: S3 | L88: S4 | M88: Flight | N88: Tabela | O88: (%) | P88: Negociado | Q88: Negociado | T88: ano
A89: OURO PRODUTO | U89: GDES | V89: MUB | W89: TRANSP | X89: AERO | Y89: OPORT | Z89: ESTÁTICO | AA89: DIGITAL | AB89: M2 | AC89: TELAS PROMO | AD89: KALLAS
A91: Boa Vista - RR | B91: M2 comunicações | C91: 50/156 | D91: Frontlight | E91: Estático | F91: 2/3 | G91: 2 | H91: Mensal | I91: 2 | M91: 1 | N91: 4480 | O91: 0.2 | P91: =N91*(1-O91) -> 3584 | Q91: =P91*M91*G91 -> 7168 | R91: =(Q91+Q92+#REF!+#REF!)/E67*1000 -> #REF! | S91: =Q91/$Q$99 -> 0.22545843 | T91: =Q91*4 -> 28672 | U91: =T91 -> 28672 | AA91: =T91 -> 28672 | AB91: =T91 -> 28672
A92: Boa Vista - RR | B92: Telas Promo | C92: 50/156 | D92: Painel de Led | E92: Digital | F92: 2/4 | G92: 2 | H92: Mensal | I92: 2 | M92: 1 | N92: 5000 | O92: 0.25 | P92: =N92*(1-O92) -> 3750 | Q92: =P92*M92*G92 -> 7500 | R92: =(Q92+Q93+#REF!+#REF!)/E68*1000 -> #REF! | S92: =Q92/$Q$99 -> 0.23590098 | T92: =Q92*4 -> 30000 | U92: =T92 -> 30000 | Z92: =T92 -> 30000 | AC92: =T92 -> 30000
A93: Boa Vista - RR | B93: Telas Promo | C93: 50/156 | D93: Circuito interno Led | E93: Digital | F93: 1/2 | G93: 2 | H93: Mensal | I93: 2 | M93: 1 | N93: 5000 | O93: 0.25 | P93: =N93*(1-O93) -> 3750 | Q93: =P93*M93*G93 -> 7500 | S93: =Q93/$Q$99 -> 0.23590098 | T93: =Q93*4 -> 30000 | V93: =T93 -> 30000 | Z93: =T93 -> 30000 | AC93: =T93 -> 30000
A94: Boa Vista - RR | B94: Telas Promo | C94: 50/156 | D94: Frontlight | E94: Estático | F94: 1/2 | G94: 1 | H94: Mensal | I94: 1 | M94: 1 | N94: 5500 | O94: 0.25 | P94: =N94*(1-O94) -> 4125 | Q94: =P94*M94*G94 -> 4125 | S94: =Q94/$Q$99 -> 0.12974554 | T94: =Q94*4 -> 16500 | U94: =T94 -> 16500 | AA94: =T94 -> 16500 | AC94: =T94 -> 16500
A96: Boa Vista - RR | B96: Aeroporto | T96: =Q96*4 -> 0 | X96: =T96 -> 0
A97: Boa Vista - RR | B97: Oportunidades | D97: Marítimos / Ativação | Q97: 5500 | S97: =Q97/Q99 -> 0.17299406 | T97: =Q97*4 -> 22000 | Y97: =T97 -> 22000
A99: Total faces compra | I99: =I94+I93+I92+I91 -> 7 | M99: =SUM(I99:L99) -> 7 | Q99: =SUM(Q91:Q98) -> 31793 | S99: =SUM(S91:S97) -> 1 | T99: =SUM(T88:T98) -> 127172 | U99: =SUM(U88:U97) -> 75172 | V99: =SUM(V88:V97) -> 30000 | W99: =SUM(W88:W97) -> 0 | X99: =SUM(X88:X97) -> 0 | Y99: =SUM(Y88:Y97) -> 22000 | Z99: =SUM(Z88:Z97) -> 60000 | AA99: =SUM(AA88:AA97) -> 45172 | AB99: =SUM(AB88:AB98) -> 28672 | AC99: =SUM(AC88:AC98) -> 76500 | AD99: =SUM(AD88:AD98) -> 0
A100: Total faces simulação | I100: =I94+I93+I92+I91 -> 7 | J100: =I94+I93+I92+I91 -> 7 | K100: =I94+I93+I92+I91 -> 7 | L100: =I94+I93+I92+I91 -> 7 | M100: =SUM(I100:L100) -> 28 | U100: =U99/T99 -> 0.59110496 | V100: =V99/T99 -> 0.23590098 | W100: =W99/T99 -> 0 | X100: =X99/T99 -> 0 | Y100: =Y99/T99 -> 0.17299406 | Z100: =Z99/T99 -> 0.47180197 | AA100: =AA99/T99 -> 0.35520398
A101: Grandes Formatos | Q101: =U99/4 -> 18793 | S101: =Q101/Q106 -> 0.59110496 | Y101: =SUM(U91:Y98) -> 127172 | Z101: =I92+I93 -> 4 | AA101: =I91+I94 -> 3
A102: MUB | Q102: =V99/4 -> 7500 | S102: =Q102/Q106 -> 0.23590098 | T102: =Q99/M99 -> 4541.8571 | U102: CPFACE | Z102: =Z101/M99 -> 0.57142857 | AA102: =AA101/M99 -> 0.42857143
A103: Transportes | Q103: =W99/4 -> 0 | S103: =Q103/Q106 -> 0 | Z103: SHARE FACES
A104: Oportunidades | Q104: =Y99/4 -> 5500 | S104: =Q104/Q106 -> 0.17299406
A105: Aeroporto | Q105: =X99/4 -> 0 | S105: =Q105/Q106 -> 0
Q106: =SUM(Q101:Q105) -> 31793 | S106: =SUM(S101:S105) -> 1
A112: Programação - Ciclo Ouro Promo
A114: 1 CICLO | T114: TOTAL ANO / CICLO
A115: Praça | B115: Exibidores | C115: Pen/Aff | D115: Tipo de Mídia | E115: Estático/Digital | F115: Range de volume ideal | G115: Qtde Sugerida | H115: Periodicidade | I115: Mês Base | M115: TT | N115: Valor Unit. Bruto | O115: Desconto | P115: Valor Unit. Bruto | Q115: Valor total | R115: C.P.M. Formato | S115: % | T115: R$ Total | U115: AMBIENTES | Z115: FORMATO | AB115: EMPRESAS
I116: S1 | J116: S2 | K116: S3 | L116: S4 | M116: Flight | N116: Tabela | O116: (%) | P116: Negociado | Q116: Bruto Negociado | T116: ano
A117: OURO PROMO | U117: GDES | V117: MUB | W117: TRANSP | X117: AERO | Y117: OPORT | Z117: ESTÁTICO | AA117: DIGITAL | AB117: M2 | AC117: TELAS PROMO | AD117: KALLAS
A119: Boa Vista - RR | B119: M2 comunicações | C119: 50/156 | D119: Frontlight | E119: Estático | F119: 2/3 | G119: 1 | H119: Mensal | I119: 1 | M119: 1 | N119: 4480 | O119: 0.2 | P119: =N119*(1-O119) -> 3584 | Q119: =P119*M119*G119 -> 3584 | R119: =(Q119+Q120+#REF!+#REF!)/E95*1000 -> #REF! | S119: =Q119/$Q$130 -> 0.10421937 | T119: =Q119 -> 3584 | U119: =T119 -> 3584 | AA119: =T119 -> 3584 | AB119: =T119 -> 3584
A120: Boa Vista - RR | B120: Telas Promo | C120: 50/156 | D120: Painel de Led | E120: Digital | F120: 2/4 | G120: 2 | H120: Mensal | I120: 2 | M120: 1 | N120: 5000 | O120: 0.25 | P120: =N120*(1-O120) -> 3750 | Q120: =P120*M120*G120 -> 7500 | R120: =(Q120+Q121+#REF!+#REF!)/E96*1000 -> #REF! | S120: =Q120/$Q$130 -> 0.21809299 | T120: =Q120 -> 7500 | U120: =T120 -> 7500 | Z120: =T120 -> 7500 | AC120: =T120 -> 7500
A121: Boa Vista - RR | B121: Telas Promo | C121: 50/156 | D121: Circuito interno Led | E121: Digital | F121: 1/2 | G121: 2 | H121: Mensal | I121: 2 | M121: 1 | N121: 5000 | O121: 0.25 | P121: =N121*(1-O121) -> 3750 | Q121: =P121*M121*G121 -> 7500 | S121: =Q121/$Q$130 -> 0.21809299 | T121: =Q121 -> 7500 | V121: =T121 -> 7500 | Z121: =T121 -> 7500 | AC121: =T121 -> 7500
A122: Boa Vista - RR | B122: Telas Promo | C122: 50/156 | D122: Frontlight | E122: Estático | F122: 1/2 | G122: 1 | H122: Mensal | I122: 1 | M122: 1 | N122: 5500 | O122: 0.25 | P122: =N122*(1-O122) -> 4125 | Q122: =P122*M122*G122 -> 4125 | S122: =Q122/$Q$130 -> 0.11995115 | T122: =Q122 -> 4125 | U122: =T122 -> 4125 | AA122: =T122 -> 4125 | AC122: =T122 -> 4125
A123: Boa Vista - RR | B123: Cartaxi | C123: 30/155 | D123: Vidro traseiro + interno | E123: Estático | F123: 3/8 | G123: 6 | H123: Mensal | I123: 6 | M123: 1 | N123: 1600 | O123: 0.7 | P123: =N123*(1-O123) -> 480 | Q123: =P123*M123*G123 -> 2880 | S123: =Q123/$Q$130 -> 0.08374771 | T123: =Q123 -> 2880 | W123: =T123 -> 2880 | AD123: =T123 -> 2880
A124: Boa Vista - RR | B124: Telas Promo | C124: 63/153 | D124: Busdoor | E124: Estático | F124: 2/5 | G124: 3 | H124: Mensal | I124: 3 | M124: 1 | N124: 2000 | O124: 0.45 | P124: =N124*(1-O124) -> 1100 | Q124: =P124*M124*G124 -> 3300 | S124: =Q124/$Q$130 -> 0.095960918 | T124: =Q124 -> 3300 | W124: =T124 -> 3300 | AC124: =T124 -> 3300
A127: Boa Vista - RR | B127: Aeroporto | T127: =Q127*2 -> 0 | X127: =T127 -> 0
A128: Boa Vista - RR | B128: Oportunidades | D128: Marítimos / Ativação | Q128: 5500 | S128: =Q128/Q130 -> 0.15993486 | T128: =Q128 -> 5500 | Y128: =T128 -> 5500
A130: Total faces compra | I130: =I122+I121+I120+I119+I123+I124 -> 15 | M130: =SUM(I130:L130) -> 15 | Q130: =SUM(Q119:Q129) -> 34389 | S130: =SUM(S119:S128) -> 1 | T130: =SUM(T119:T129) -> 34389 | U130: =SUM(U119:U128) -> 15209 | V130: =SUM(V119:V128) -> 7500 | W130: =SUM(W119:W128) -> 6180 | X130: =SUM(X119:X128) -> 0 | Y130: =SUM(Y119:Y128) -> 5500 | Z130: =SUM(Z119:Z128) -> 15000 | AA130: =SUM(AA119:AA128) -> 7709 | AB130: =SUM(AB119:AB129) -> 3584 | AC130: =SUM(AC119:AC129) -> 22425 | AD130: =SUM(AD119:AD129) -> 2880
A131: Total faces simulação | I131: =I122+I121+I120+I119+I123+I124 -> 15 | J131: =I122+I121+I120+I119+I123+I124 -> 15 | K131: =I122+I121+I120+I119+I123+I124 -> 15 | L131: =I122+I121+I120+I119+I123+I124 -> 15 | M131: =SUM(I131:L131) -> 60 | U131: =U130/T130 -> 0.44226351 | V131: =V130/T130 -> 0.21809299 | W131: =W130/T130 -> 0.17970863 | X131: =X130/T130 -> 0 | Y131: =Y130/T130 -> 0.15993486 | Z131: =Z130/T130 -> 0.43618599 | AA131: =AA130/T130 -> 0.22417052
A132: Grandes Formatos | Q132: =U130 -> 15209 | S132: =Q132/Q137 -> 0.44226351 | Y132: =SUM(U119:Y129) -> 34389 | Z132: =I120+I121+I123+I124 -> 13 | AA132: =I119+I122 -> 2
A133: MUB | Q133: =V130 -> 7500 | S133: =Q133/Q137 -> 0.21809299 | T133: =Q130/M130 -> 2292.6 | U133: CPFACE | Z133: =Z132/M130 -> 0.86666667 | AA133: =AA132/M130 -> 0.13333333
A134: Transportes | Q134: =W130 -> 6180 | S134: =Q134/Q137 -> 0.17970863 | Z134: SHARE FACES
...

Sheet BOA VISTA PLAN
A1: taxonomia | B1: regional_boticario | C1: uf | D1: praca | E1: exibidores | F1: formato | G1: ranking | H1: pesos | I1: estatico | J1: digital | K1: range_minimo | L1: range_maximo | M1: quantidade | N1: periodicidade | O1: s1 | P1: s2 | Q1: s3 | R1: s4 | S1: flight | T1: unitario_bruto_tabela | U1: desconto | V1: unitario_bruto_negociado | W1: total_bruto_negociado
A2: data produto | B2: norte | C2: rr | D2: boa vista | E2: M2 comunicações | F2: Frontlight | G2: 1 | H2: =VLOOKUP(G2,Pesos!A:B,2,0) -> 0.9 | I2: x | K2: 3 | L2: 5 | M2: 3 | N2: Mensal | O2: 3 | Q2: 1 | S2: 1 | T2: 4480 | U2: 0.2 | V2: =T2*(1-U2) -> 3584 | W2: =V2*S2*M2 -> 10752
A3: data produto | B3: norte | C3: rr | D3: boa vista | E3: Telas Promo | F3: Painel de Led | G3: 2 | H3: =VLOOKUP(G3,Pesos!A:B,2,0) -> 0.8 | J3: X | K3: 2 | L3: 4 | M3: 2 | N3: Mensal | O3: 2 | S3: 1 | T3: 5000 | U3: 0.25 | V3: =T3*(1-U3) -> 3750 | W3: =V3*S3*M3 -> 7500
A4: data produto | B4: norte | C4: rr | D4: boa vista | E4: Telas Promo | F4: Circuito interno Led | G4: 3 | H4: =VLOOKUP(G4,Pesos!A:B,2,0) -> 0.7 | J4: X | K4: 1 | L4: 2 | M4: 2 | N4: Mensal | O4: 2 | S4: 1 | T4: 5000 | U4: 0.25 | V4: =T4*(1-U4) -> 3750 | W4: =V4*S4*M4 -> 7500
A5: data produto | B5: norte | C5: rr | D5: boa vista | E5: Telas Promo | F5: Frontlight | G5: 1 | H5: =VLOOKUP(G5,Pesos!A:B,2,0) -> 0.9 | I5: X | K5: 3 | L5: 5 | M5: 2 | N5: Mensal | O5: 2 | S5: 1 | T5: 5500 | U5: 0.25 | V5: =T5*(1-U5) -> 4125 | W5: =V5*S5*M5 -> 8250
A7: data promo | B7: norte | C7: rr | D7: boa vista | E7: M2 comunicações | F7: Frontlight | G7: 3 | H7: =VLOOKUP(G7,Pesos!A:B,2,0) -> 0.7 | I7: x | K7: 2 | L7: 3 | M7: 2 | N7: Mensal | O7: 2 | S7: 1 | T7: 4480 | U7: 0.2 | V7: =T7*(1-U7) -> 3584 | W7: =V7*S7*M7 -> 7168
A8: data promo | B8: norte | C8: rr | D8: boa vista | E8: Telas Promo | F8: Painel de Led | G8: 1 | H8: =VLOOKUP(G8,Pesos!A:B,2,0) -> 0.9 | J8: x | K8: 2 | L8: 4 | M8: 2 | N8: Mensal | O8: 2 | S8: 1 | T8: 5000 | U8: 0.25 | V8: =T8*(1-U8) -> 3750 | W8: =V8*S8*M8 -> 7500
A9: data promo | B9: norte | C9: rr | D9: boa vista | E9: Telas Promo | F9: Circuito interno Led | G9: 4 | H9: =VLOOKUP(G9,Pesos!A:B,2,0) -> 0.6 | J9: x | K9: 1 | L9: 2 | M9: 2 | N9: Mensal | O9: 2 | S9: 1 | T9: 5000 | U9: 0.25 | V9: =T9*(1-U9) -> 3750 | W9: =V9*S9*M9 -> 7500
A10: data promo | B10: norte | C10: rr | D10: boa vista | E10: Telas Promo | F10: Frontlight | G10: 3 | H10: =VLOOKUP(G10,Pesos!A:B,2,0) -> 0.7 | I10: x | K10: 1 | L10: 2 | M10: 1 | N10: Mensal | O10: 1 | S10: 1 | T10: 5500 | U10: 0.25 | V10: =T10*(1-U10) -> 4125 | W10: =V10*S10*M10 -> 4125
A11: data promo | B11: norte | C11: rr | D11: boa vista | E11: Cartaxi | F11: Vidro traseiro + interno | G11: 5 | H11: =VLOOKUP(G11,Pesos!A:B,2,0) -> 0.5 | I11: x | K11: 3 | L11: 8 | M11: 8 | N11: Mensal | O11: 8 | S11: 1 | T11: 1600 | U11: 0.7 | V11: =T11*(1-U11) -> 480 | W11: =V11*S11*M11 -> 3840
A12: data promo | B12: norte | C12: rr | D12: boa vista | E12: Telas Promo | F12: Busdoor | G12: 2 | H12: =VLOOKUP(G12,Pesos!A:B,2,0) -> 0.8 | I12: x | K12: 2 | L12: 5 | M12: 4 | N12: Mensal | O12: 4 | S12: 1 | T12: 2000 | U12: 0.45 | V12: =T12*(1-U12) -> 1100 | W12: =V12*S12*M12 -> 4400
A14: ouro produto | B14: norte | C14: rr | D14: boa vista | E14: M2 comunicações | F14: Frontlight | G14: 1 | H14: =VLOOKUP(G14,Pesos!A:B,2,0) -> 0.9 | I14: x | K14: 2 | L14: 3 | M14: 2 | N14: Mensal | O14: 2 | S14: 1 | T14: 4480 | U14: 0.2 | V14: =T14*(1-U14) -> 3584 | W14: =V14*S14*M14 -> 7168
A15: ouro produto | B15: norte | C15: rr | D15: boa vista | E15: Telas Promo | F15: Painel de Led | G15: 2 | H15: =VLOOKUP(G15,Pesos!A:B,2,0) -> 0.8 | J15: x | K15: 2 | L15: 4 | M15: 2 | N15: Mensal | O15: 2 | S15: 1 | T15: 5000 | U15: 0.25 | V15: =T15*(1-U15) -> 3750 | W15: =V15*S15*M15 -> 7500
A16: ouro produto | B16: norte | C16: rr | D16: boa vista | E16: Telas Promo | F16: Circuito interno Led | G16: 3 | H16: =VLOOKUP(G16,Pesos!A:B,2,0) -> 0.7 | J16: x | K16: 1 | L16: 2 | M16: 2 | N16: Mensal | O16: 2 | S16: 1 | T16: 5000 | U16: 0.25 | V16: =T16*(1-U16) -> 3750 | W16: =V16*S16*M16 -> 7500
A17: ouro produto | B17: norte | C17: rr | D17: boa vista | E17: Telas Promo | F17: Frontlight | G17: 1 | H17: =VLOOKUP(G17,Pesos!A:B,2,0) -> 0.9 | I17: x | K17: 1 | L17: 2 | M17: 1 | N17: Mensal | O17: 1 | S17: 1 | T17: 5500 | U17: 0.25 | V17: =T17*(1-U17) -> 4125 | W17: =V17*S17*M17 -> 4125
A19: ouro promo | B19: norte | C19: rr | D19: boa vista | E19: M2 comunicações | F19: Frontlight | G19: 3 | H19: =VLOOKUP(G19,Pesos!A:B,2,0) -> 0.7 | I19: x | K19: 2 | L19: 3 | M19: 1 | N19: Mensal | O19: 1 | S19: 1 | T19: 4480 | U19: 0.2 | V19: =T19*(1-U19) -> 3584 | W19: =V19*S19*M19 -> 3584
A20: ouro promo | B20: norte | C20: rr | D20: boa vista | E20: Telas Promo | F20: Painel de Led | G20: 1 | H20: =VLOOKUP(G20,Pesos!A:B,2,0) -> 0.9 | J20: x | K20: 2 | L20: 4 | M20: 2 | N20: Mensal | O20: 2 | S20: 1 | T20: 5000 | U20: 0.25 | V20: =T20*(1-U20) -> 3750 | W20: =V20*S20*M20 -> 7500
A21: ouro promo | B21: norte | C21: rr | D21: boa vista | E21: Telas Promo | F21: Circuito interno Led | G21: 4 | H21: =VLOOKUP(G21,Pesos!A:B,2,0) -> 0.6 | J21: x | K21: 1 | L21: 2 | M21: 2 | N21: Mensal | O21: 2 | S21: 1 | T21: 5000 | U21: 0.25 | V21: =T21*(1-U21) -> 3750 | W21: =V21*S21*M21 -> 7500
A22: ouro promo | B22: norte | C22: rr | D22: boa vista | E22: Telas Promo | F22: Frontlight | G22: 3 | H22: =VLOOKUP(G22,Pesos!A:B,2,0) -> 0.7 | I22: x | K22: 1 | L22: 2 | M22: 1 | N22: Mensal | O22: 1 | S22: 1 | T22: 5500 | U22: 0.25 | V22: =T22*(1-U22) -> 4125 | W22: =V22*S22*M22 -> 4125
A23: ouro promo | B23: norte | C23: rr | D23: boa vista | E23: Cartaxi | F23: Vidro traseiro + interno | G23: 5 | H23: =VLOOKUP(G23,Pesos!A:B,2,0) -> 0.5 | I23: x | K23: 3 | L23: 8 | M23: 6 | N23: Mensal | O23: 6 | S23: 1 | T23: 1600 | U23: 0.7 | V23: =T23*(1-U23) -> 480 | W23: =V23*S23*M23 -> 2880
A24: ouro promo | B24: norte | C24: rr | D24: boa vista | E24: Telas Promo | F24: Busdoor | G24: 2 | H24: =VLOOKUP(G24,Pesos!A:B,2,0) -> 0.8 | I24: x | K24: 2 | L24: 5 | M24: 3 | N24: Mensal | O24: 3 | S24: 1 | T24: 2000 | U24: 0.45 | V24: =T24*(1-U24) -> 1100 | W24: =V24*S24*M24 -> 3300
A26: prata | B26: norte | C26: rr | D26: boa vista | E26: M2 comunicações | F26: Frontlight | G26: 3 | H26: =VLOOKUP(G26,Pesos!A:B,2,0) -> 0.7 | I26: x | K26: 2 | L26: 3 | M26: 1 | N26: Mensal | O26: 1 | S26: 1 | T26: 4480 | U26: 0.2 | V26: =T26*(1-U26) -> 3584 | W26: =V26*S26*M26 -> 3584
A27: prata | B27: norte | C27: rr | D27: boa vista | E27: Telas Promo | F27: Painel de Led | G27: 1 | H27: =VLOOKUP(G27,Pesos!A:B,2,0) -> 0.9 | J27: x | K27: 2 | L27: 4 | M27: 1 | N27: Mensal | O27: 1 | S27: 1 | T27: 5000 | U27: 0.25 | V27: =T27*(1-U27) -> 3750 | W27: =V27*S27*M27 -> 3750
A28: prata | B28: norte | C28: rr | D28: boa vista | E28: Telas Promo | F28: Circuito interno Led | G28: 4 | H28: =VLOOKUP(G28,Pesos!A:B,2,0) -> 0.6 | J28: x | K28: 1 | L28: 2 | M28: 1 | N28: Mensal | O28: 1 | S28: 1 | T28: 5000 | U28: 0.25 | V28: =T28*(1-U28) -> 3750 | W28: =V28*S28*M28 -> 3750
A29: prata | B29: norte | C29: rr | D29: boa vista | E29: Telas Promo | F29: Frontlight | G29: 3 | H29: =VLOOKUP(G29,Pesos!A:B,2,0) -> 0.7 | I29: x | K29: 1 | L29: 2 | M29: 1 | N29: Mensal | O29: 1 | S29: 1 | T29: 5500 | U29: 0.25 | V29: =T29*(1-U29) -> 4125 | W29: =V29*S29*M29 -> 4125
A30: prata | B30: norte | C30: rr | D30: boa vista | E30: Cartaxi | F30: Vidro traseiro + interno | G30: 5 | H30: =VLOOKUP(G30,Pesos!A:B,2,0) -> 0.5 | I30: x | K30: 3 | L30: 8 | M30: 2 | N30: Mensal | O30: 2 | S30: 1 | T30: 1600 | U30: 0.7 | V30: =T30*(1-U30) -> 480 | W30: =V30*S30*M30 -> 960
A31: prata | B31: norte | C31: rr | D31: boa vista | E31: Telas Promo | F31: Busdoor | G31: 2 | H31: =VLOOKUP(G31,Pesos!A:B,2,0) -> 0.8 | I31: x | K31: 2 | L31: 5 | M31: 1 | N31: Mensal | O31: 1 | S31: 1 | T31: 2000 | U31: 0.45 | V31: =T31*(1-U31) -> 1100 | W31: =V31*S31*M31 -> 1100
E36: cpf mínimo | F36: cpf plano | G36: cpf máximo
A37: DATA PRODUTO | E37: =F37*(1-10%) -> 4160.2 | F37: ='BOA VISTA'!T46 -> 4622.4444 | G37: =F37*(1+15%) -> 5315.8111
A38: DATA PROMO | E38: =F38*(1-25%) -> 1663.1447 | F38: ='BOA VISTA'!T73 -> 2217.5263 | G38: =F38*(1+5%) -> 2328.4026
A39: OURO PRODUTO | E39: =F39*(1-15%) -> 3860.5786 | F39: ='BOA VISTA'!T102 -> 4541.8571 | G39: =F39*(1+15%) -> 5223.1357
A40: OURO PROMO | E40: =F40*(1-25%) -> 1719.45 | F40: ='BOA VISTA'!T133 -> 2292.6 | G40: =F40*(1+5%) -> 2407.23
A41: PRATA | E41: =F41*(1-25%) -> 2118.1071 | F41: ='BOA VISTA'!T167 -> 2824.1429 | G41: =F41*(1+5%) -> 2965.35
E43: ranking semanas - distribuição investimento
A44: DATA PRODUTO | E44: 1
A45: DATA PROMO | E45: 1
A46: OURO PRODUTO | E46: 1
A47: OURO PROMO | E47: 1
A48: PRATA | E48: 1
E52: ranking semanas - distribuição audiência
A53: DATA PRODUTO | E53: 0.25 | F53: 0.25 | G53: 0.25 | H53: 0.25
A54: DATA PROMO | E54: 0.25 | F54: 0.25 | G54: 0.25 | H54: 0.25
A55: OURO PRODUTO | E55: 0.34 | F55: 0.33 | G55: 0.33
A56: OURO PROMO | E56: 0.34 | F56: 0.33 | G56: 0.33
A57: PRATA | E57: 0.34 | F57: 0.33 | G57: 0.33

Sheet MACAPA
A1: ESTUDO MACAPA
A2: IBGE 2024/ CENSO 2022
A6: INVESTIMENTO MACAPA CAPITAL OOH 2024 | B6: 393739.8
A7: INVESTIMENTO AMAPA OOH 2024 | B7: 393739.8
A9: R$ BRUTO MACAPA CAPITAL - 2025 OOH | B9: 1077573.8
A10: BUDGET BRUTO AMAPA 2025 OOH (100%) | B10: 1077573.8
A13: Exclusão de Bronze
A14: CICLOS/MEDALHAS | C14: % BUDGET/CICLO | D14: R$ MEDALHA | E14: R$ UNIT. MEDALHAS
A15: Datas (c6/c16/c17) | B15: 3 - 2 produto/1 promo | C15: 0.44 | D15: 474132.45 | E15: 158044.15
A16: Ouro (c1/c4/c11/c13) | B16: 5 - 4 produto/ 1 promo | C16: 0.48 | D16: 517235.4 | E16: 103447.08
A17: Prata (c3/c8/c10/c14) | B17: 2 | C17: 0.08 | D17: 86205.9 | E17: 43102.95
B18: 10 ciclos | C18: 1 | D18: 1077573.8
A21: População Capital | B21: 442933
A22: População Target - AS ABC 18/49 (logan) | B22: 249133 | E22: Cobertura total - Data Produto | F22: 32% | H22: Cobertura total - Data Promo | J22: 0.34
E23: Frequencia | F23: 23 | H23: Frequencia | J23: 25
E24: TRP | F24: 697 | H24: TRP | J24: 735
E25: OTS | F25: 1.735.289 | H25: OTS | J25: 1831500
A27: Programação - Ciclo Data Produto
A29: 1 CICLO | T29: TOTAL ANO / CICLO
A30: Praça | B30: Exibidores | C30: Pen/Aff | D30: Canais | E30: Formato | F30: Range de volume ideal | G30: Qtdade | H30: Periodicidade | I30: Mês Base | M30: TT | N30: R$ Unit Bruto | O30: Desconto | P30: R$ Unit Bruto | Q30: R$ TT Bruto | R30: C.P.M. Formato | S30: % | T30: R$ Total | U30: AMBIENTES | Z30: FORMATO | AB30: EMPRESAS
I31: S1 | J31: S2 | K31: S3 | L31: S4 | M31: Flight | N31: Tabela | O31: (%) | P31: Negociado | Q31: Negociado | T31: ano
A32: DATAS MÃES/NATAL | U32: GDES | V32: MUB | W32: TRANSP | X32: AERO | Y32: OPORT | Z32: ESTÁTICO | AA32: DIGITAL | AB32: BUREAU | AC32: ATOS
A34: Macapá - AP | B34: Bureau de mídia | C34: 50/156 | D34: Frontlight | E34: Estático | F34: 2/3 | G34: 2 | H34: Mensal | I34: 2 | M34: 1 | N34: 5200 | O34: 0.34 | P34: =N34*(1-O34) -> 3432 | Q34: =P34*M34*G34 -> 6864 | R34: =(Q34+Q35+Q39+#REF!)/E7*1000 -> #REF! | S34: =Q34/$Q$43 -> 0.11259843 | T34: =Q34*2 -> 13728 | U34: =T34 -> 13728 | AA34: =T34 -> 13728 | AB34: =T34 -> 13728
A35: Macapá - AP | B35: Bureau de mídia | C35: 50/156 | D35: Painel de Led | E35: Digital | F35: 2/4 | G35: 2 | H35: Mensal | I35: 2 | M35: 1 | N35: 7800 | O35: 0.34 | P35: =N35*(1-O35) -> 5148 | Q35: =P35*M35*G35 -> 10296 | R35: =(Q35+Q38+#REF!+#REF!)/E8*1000 -> #REF! | S35: =Q35/$Q$43 -> 0.16889764 | T35: =Q35*2 -> 20592 | U35: =T35 -> 20592 | AA35: =T35 -> 20592 | AB35: =T35 -> 20592
A36: Macapá - AP | B36: Atos | C36: 50/156 | D36: Frontlight | E36: Estático | F36: 2/4 | G36: 1 | H36: Mensal | I36: 1 | M36: 1 | N36: 3500 | O36: 0.2 | P36: =N36*(1-O36) -> 2800 | Q36: =P36*M36*G36 -> 2800 | S36: =Q36/$Q$43 -> 0.045931759 | T36: =Q36*2 -> 5600 | U36: =T36 -> 5600 | AA36: =T36 -> 5600 | AC36: =T36 -> 5600
A37: Macapá - AP | B37: Atos | C37: 50/156 | D37: Outdoor lonado | E37: Estático | F37: 8/13 | G37: 15 | H37: Mensal | I37: 15 | M37: 1 | N37: 1500 | O37: 0.2 | P37: =N37*(1-O37) -> 1200 | Q37: =P37*M37*G37 -> 18000 | R37: =(Q37+#REF!)/E6*1000 -> #REF! | S37: =Q37/$Q$43 -> 0.29527559 | T37: =Q37*2 -> 36000 | U37: =T37 -> 36000 | Z37: =T37 -> 36000 | AC37: =T37 -> 36000
A38: Macapá - AP | B38: Atos | C38: 50/156 | D38: Outdoor lonado | E38: Estático | F38: 10/25 | G38: 15 | H38: Mensal | K38: 15 | M38: 1 | N38: 1500 | O38: 0.2 | P38: =N38*(1-O38) -> 1200 | Q38: =P38*M38*G38 -> 18000 | R38: =(Q38+#REF!)/E8*1000 -> #REF! | S38: =Q38/$Q$43 -> 0.29527559 | T38: =Q38*2 -> 36000 | U38: =T38 -> 36000 | Z38: =T38 -> 36000 | AC38: =T38 -> 36000
A40: Macapá- AP | B40: Aeroporto | X40: =T40 -> 0
A41: Macapá-AP | B41: Oportunidades | D41: Marítimos / Ativação | Q41: 5000 | S41: =Q41/Q43 -> 0.082020997 | T41: =Q41*2 -> 10000 | Y41: =T41 -> 10000
I42: =I43/M43 -> 0.57142857 | K42: =K43/M43 -> 0.42857143
A43: Total faces compra | I43: =I37+I36+I35+I34 -> 20 | K43: =K38 -> 15 | M43: =SUM(I43:L43) -> 35 | Q43: =SUM(Q34:Q42) -> 60960 | S43: =SUM(S34:S41) -> 1 | T43: =SUM(T34:T42) -> 121920 | U43: =SUM(U34:U41) -> 111920 | V43: =SUM(V34:V41) -> 0 | W43: =SUM(W34:W41) -> 0 | X43: =SUM(X34:X41) -> 0 | Y43: =SUM(Y34:Y41) -> 10000 | Z43: =SUM(Z34:Z41) -> 72000 | AA43: =SUM(AA34:AA41) -> 39920 | AB43: =SUM(AB34:AB42) -> 34320 | AC43: =SUM(AC34:AC42) -> 77600
A44: Total faces simulação | I44: =I37+I36+I35+I34 -> 20 | J44: =I37+I36+I35+I34 -> 20 | K44: =K38+I36+I35+I34 -> 20 | L44: =K38+I36+I35+I34 -> 20 | M44: =SUM(I44:L44) -> 80 | U44: =U43/T43 -> 0.917979 | V44: =V43/T43 -> 0 | W44: =W43/T43 -> 0 | X44: =X43/T43 -> 0 | Y44: =Y43/T43 -> 0.082020997 | Z44: =Z43/T43 -> 0.59055118 | AA44: =AA43/T43 -> 0.32742782
A45: Grandes Formatos | Q45: =U43/2 -> 55960 | S45: =Q45/Q50 -> 0.917979 | Z45: =I34+I36+I37+K38 -> 33 | AA45: =I35 -> 2
A46: MUB | Q46: =V43/2 -> 0 | S46: =Q46/Q50 -> 0 | T46: =Q43/M43 -> 1741.7143 | U46: CPFACE | Z46: =Z45/M43 -> 0.94285714 | AA46: =AA45/M43 -> 0.057142857
A47: Transportes | Q47: =W43/2 -> 0 | S47: =Q47/Q50 -> 0 | Z47: SHARE FACES
A48: Oportunidades | Q48: =Y43/2 -> 5000 | S48: =Q48/Q50 -> 0.082020997
A49: Aeroporto | Q49: =X43/2 -> 0 | S49: =Q49/Q50 -> 0
Q50: =SUM(Q45:Q49) -> 60960 | S50: =SUM(S45:S49) -> 1
A52: Programação - Ciclo Data Promo
A54: 1 CICLO | T54: TOTAL ANO / CICLO
A55: Praça | B55: Exibidores | C55: Pen/Aff | D55: Canais | E55: Formato | F55: Range de volume ideal | G55: Qtdade | H55: Periodicidade | I55: Mês Base | M55: TT | N55: R$ Unit Bruto | O55: Desconto | P55: R$ Unit Bruto | Q55: R$ TT Bruto | R55: C.P.M. Formato | S55: % | T55: R$ Total | U55: AMBIENTES | Z55: FORMATO | AB55: EMPRESAS
I56: S1 | J56: S2 | K56: S3 | L56: S4 | M56: Flight | N56: Tabela | O56: (%) | P56: Negociado | Q56: Negociado | T56: ano
A57: DATAS BW | U57: GDES | V57: MUB | W57: TRANSP | X57: AERO | Y57: OPORT | Z57: ESTÁTICO | AA57: DIGITAL | AB57: BUREAU | AC57: ATOS
A59: Macapá - AP | B59: Bureau de mídia | C59: 50/156 | D59: Frontlight | E59: Estático | F59: 2/3 | G59: 1 | H59: Mensal | I59: 1 | M59: 1 | N59: 5200 | O59: 0.34 | P59: =N59*(1-O59) -> 3432 | Q59: =P59*M59*G59 -> 3432 | R59: =(Q59+Q60+Q64+#REF!)/E35*1000 -> #REF! | S59: =Q59/$Q$72 -> 0.051239176 | T59: =Q59 -> 3432 | U59: =T59 -> 3432 | AA59: =T59 -> 3432 | AB59: =T59 -> 3432
A60: Macapá - AP | B60: Bureau de mídia | C60: 50/156 | D60: Painel de Led | E60: Digital | F60: 2/4 | G60: 1 | H60: Mensal | I60: 1 | M60: 1 | N60: 7800 | O60: 0.34 | P60: =N60*(1-O60) -> 5148 | Q60: =P60*M60*G60 -> 5148 | R60: =(Q60+Q63+#REF!+#REF!)/E36*1000 -> #REF! | S60: =Q60/$Q$72 -> 0.076858764 | T60: =Q60 -> 5148 | U60: =T60 -> 5148 | AA60: =T60 -> 5148 | AB60: =T60 -> 5148
A61: Macapá - AP | B61: Bureau de mídia | C61: 63/153 | D61: Busdoor | E61: Estático | F61: 5/10 | G61: 3 | H61: Mensal | I61: 3 | M61: 1 | N61: 1550 | O61: 0.2 | P61: =N61*(1-O61) -> 1240 | Q61: =P61*M61*G61 -> 3720 | R61: =(Q61+Q64+#REF!+#REF!)/E37*1000 -> #REF! | S61: =Q61/$Q$72 -> 0.055538967 | T61: =Q61 -> 3720 | W61: =T61 -> 3720 | AB61: =T61 -> 3720
A62: Macapá - AP | B62: Bureau de mídia | D62: Bikedoor | E62: Estático | F62: 2/5 | G62: 4 | H62: Diaria | I62: 4 | K62: 4 | M62: 2 | N62: 2450 | O62: 0.2 | P62: =N62*(1-O62) -> 1960 | Q62: =P62*M62*G62 -> 15680 | R62: =(Q62+Q65+#REF!+#REF!)/E38*1000 -> #REF! | S62: =Q62/$Q$72 -> 0.23409973 | T62: =Q62 -> 15680 | W62: =T62 -> 15680 | AB62: =T62 -> 15680
A63: Macapá - AP | B63: Atos | C63: 50/156 | D63: Frontlight | E63: Estático | F63: 2/4 | G63: 1 | H63: Mensal | I63: 1 | M63: 1 | N63: 3500 | O63: 0.2 | P63: =N63*(1-O63) -> 2800 | Q63: =P63*M63*G63 -> 2800 | S63: =Q63/$Q$72 -> 0.041803523 | T63: =Q63 -> 2800 | U63: =T63 -> 2800 | AA63: =T63 -> 2800 | AC63: =T63 -> 2800
A64: Macapá - AP | B64: Atos | C64: 50/156 | D64: Outdoor lonado | E64: Estático | F64: 8/13 | G64: 13 | H64: Mensal | I64: 13 | M64: 1 | N64: 1500 | O64: 0.2 | P64: =N64*(1-O64) -> 1200 | Q64: =P64*M64*G64 -> 15600 | R64: =(Q64+#REF!)/E36*1000 -> #REF! | S64: =Q64/$Q$72 -> 0.23290534 | T64: =Q64 -> 15600 | U64: =T64 -> 15600 | Z64: =T64 -> 15600 | AC64: =T64 -> 15600
A65: Macapá - AP | B65: Atos | C65: 50/156 | D65: Outdoor lonado | E65: Estático | F65: 10/25 | G65: 13 | H65: Mensal | K65: 13 | M65: 1 | N65: 1500 | O65: 0.2 | P65: =N65*(1-O65) -> 1200 | Q65: =P65*M65*G65 -> 15600 | R65: =(Q65+#REF!)/E38*1000 -> #REF! | S65: =Q65/$Q$72 -> 0.23290534 | T65: =Q65 -> 15600 | U65: =T65 -> 15600 | Z65: =T65 -> 15600 | AC65: =T65 -> 15600
A69: Macapá- AP | B69: Aeroporto | X69: =T69 -> 0
A70: Macapá-AP | B70: Oportunidades | D70: Marítimos / Ativação | Q70: 5000 | S70: =Q70/Q72 -> 0.074649149 | T70: =Q70 -> 5000 | Y70: =T70 -> 5000
I71: =I72/M72 -> 0.575 | K71: =K72/M72 -> 0.425
A72: Total faces compra | I72: =I64+I63+I60+I59+I62+I61 -> 23 | K72: =K65+K62 -> 17 | M72: =SUM(I72:L72) -> 40 | Q72: =SUM(Q59:Q71) -> 66980 | S72: =SUM(S59:S70) -> 1 | T72: =SUM(T59:T71) -> 66980 | U72: =SUM(U59:U70) -> 42580 | V72: =SUM(V59:V70) -> 0 | W72: =SUM(W59:W70) -> 19400 | X72: =SUM(X59:X70) -> 0 | Y72: =SUM(Y59:Y70) -> 5000 | Z72: =SUM(Z59:Z70) -> 31200 | AA72: =SUM(AA59:AA70) -> 11380 | AB72: =SUM(AB59:AB71) -> 27980 | AC72: =SUM(AC59:AC71) -> 34000
A73: Total faces simulação | I73: =I64+I63+I60+I59+I62+I61 -> 23 | J73: =I64+I63+I60+I59+I61 -> 19 | K73: =K65+I63+I60+I59+K62+I61 -> 23 | L73: =K65+I63+I60+I59+I61 -> 19 | M73: =SUM(I73:L73) -> 84 | U73: =U72/T72 -> 0.63571215 | V73: =V72/T72 -> 0 | W73: =W72/T72 -> 0.2896387 | X73: =X72/T72 -> 0 | Y73: =Y72/T72 -> 0.074649149 | Z73: =Z72/T72 -> 0.46581069 | AA73: =AA72/T72 -> 0.16990146
A74: Grandes Formatos | I74: =I73/M73 -> 0.27380952 | J74: =J73/M73 -> 0.22619048 | K74: 0.27 | L74: 0.23 | Q74: =U72 -> 42580 | S74: =Q74/Q79 -> 0.63571215 | Z74: =I64+K65+I63 -> 27 | AA74: =I59+I60+I61+I62+K62 -> 13
A75: MUB | Q75: =V72 -> 0 | S75: =Q75/Q79 -> 0 | T75: =Q72/M72 -> 1674.5 | U75: CPFACE | Z75: =Z74/M72 -> 0.675 | AA75: =AA74/M72 -> 0.325
A76: Transportes | Q76: =W72 -> 19400 | S76: =Q76/Q79 -> 0.2896387 | Z76: SHARE FACES
A77: Oportunidades | Q77: =Y72 -> 5000 | S77: =Q77/Q79 -> 0.074649149
A78: Aeroporto | Q78: =X72 -> 0 | S78: =Q78/Q79 -> 0
Q79: =SUM(Q74:Q78) -> 66980 | S79: =SUM(S74:S78) -> 1
E84: Cobertura total - Ouro Produto | F84: 28% | G84: Cobertura total - Ouro Promo | I84: 0.29
E85: Frequencia | F85: 21 | G85: Frequencia | I85: 21
E86: TRP | F86: 576 | G86: TRP | I86: 600
E87: OTS | F87: 1.434.026 | G87: OTS | I87: 1595947
A89: Programação - Ciclo Ouro Produto
A91: 1 CICLO | T91: TOTAL ANO / CICLO
A92: Praça | B92: Exibidores | C92: Pen/Aff | D92: Canais | E92: Formato | F92: Range de volume ideal | G92: Qtdade | H92: Periodicidade | I92: Mês Base | M92: TT | N92: R$ Unit Bruto | O92: Desconto | P92: R$ Unit Bruto | Q92: R$ TT Bruto | R92: C.P.M. Formato | S92: % | T92: R$ Total | U92: AMBIENTES | Z92: FORMATO | AB92: EMPRESAS
I93: S1 | J93: S2 | K93: S3 | L93: S4 | M93: Flight | N93: Tabela | O93: (%) | P93: Negociado | Q93: Negociado | T93: ano
A94: OURO PRODUTO | U94: GDES | V94: MUB | W94: TRANSP | X94: AERO | Y94: OPORT | Z94: ESTÁTICO | AA94: DIGITAL | AB94: BUREAU | AC94: ATOS
A96: Macapá - AP | B96: Bureau de mídia | C96: 50/156 | D96: Frontlight | E96: Estático | F96: 2/3 | G96: 1 | H96: Mensal | I96: 1 | M96: 1 | N96: 5200 | O96: 0.34 | P96: =N96*(1-O96) -> 3432 | Q96: =P96*M96*G96 -> 3432 | R96: =(Q96+Q97+Q99+#REF!)/E72*1000 -> #REF! | S96: =Q96/$Q$105 -> 0.08726607 | T96: =Q96*4 -> 13728 | U96: =T96 -> 13728 | AA96: =T96 -> 13728 | AB96: =T96 -> 13728
A97: Macapá - AP | B97: Bureau de mídia | C97: 50/156 | D97: Painel de Led | E97: Digital | F97: 2/4 | G97: 2 | H97: Mensal | I97: 2 | M97: 1 | N97: 7800 | O97: 0.34 | P97: =N97*(1-O97) -> 5148 | Q97: =P97*M97*G97 -> 10296 | R97: =(Q97+Q98+#REF!+#REF!)/E73*1000 -> #REF! | S97: =Q97/$Q$105 -> 0.26179821 | T97: =Q97*4 -> 41184 | U97: =T97 -> 41184 | AA97: =T97 -> 41184 | AB97: =T97 -> 41184
A98: Macapá - AP | B98: Atos | C98: 50/156 | D98: Frontlight | E98: Estático | F98: 2/4 | G98: 1 | H98: Mensal | I98: 1 | M98: 1 | N98: 3500 | O98: 0.2 | P98: =N98*(1-O98) -> 2800 | Q98: =P98*M98*G98 -> 2800 | S98: =Q98/$Q$105 -> 0.071196094 | T98: =Q98*4 -> 11200 | U98: =T98 -> 11200 | AA98: =T98 -> 11200 | AC98: =T98 -> 11200
A99: Macapá - AP | B99: Atos | C99: 50/156 | D99: Outdoor lonado | E99: Estático | F99: 8/13 | G99: 8 | H99: Mensal | I99: 8 | M99: 1 | N99: 1500 | O99: 0.2 | P99: =N99*(1-O99) -> 1200 | Q99: =P99*M99*G99 -> 9600 | R99: =(Q99+#REF!)/E73*1000 -> #REF! | S99: =Q99/$Q$105 -> 0.2441009 | T99: =Q99*4 -> 38400 | U99: =T99 -> 38400 | Z99: =T99 -> 38400 | AC99: =T99 -> 38400
A100: Macapá - AP | B100: Atos | C100: 50/156 | D100: Outdoor lonado | E100: Estático | F100: 10/25 | G100: 8 | H100: Mensal | K100: 8 | M100: 1 | N100: 1500 | O100: 0.2 | P100: =N100*(1-O100) -> 1200 | Q100: =P100*M100*G100 -> 9600 | R100: =(Q100+#REF!)/E75*1000 -> #REF! | S100: =Q100/$Q$105 -> 0.2441009 | T100: =Q100*4 -> 38400 | U100: =T100 -> 38400 | Z100: =T100 -> 38400 | AC100: =T100 -> 38400
A102: Macapá- AP | B102: Aeroporto | T102: =Q102*2 -> 0 | X102: =T102 -> 0
A103: Macapá-AP | B103: Oportunidades | D103: Marítimos / Ativação | Q103: 3600 | S103: =Q103/Q105 -> 0.091537836 | T103: =Q103*4 -> 14400 | Y103: =T103 -> 14400
I104: =I105/M105 -> 0.6 | K104: =K105/M105 -> 0.4
A105: Total faces compra | I105: =I99+I98+I97+I96 -> 12 | K105: =K100 -> 8 | M105: =SUM(I105:L105) -> 20 | Q105: =SUM(Q96:Q104) -> 39328 | S105: =SUM(S96:S103) -> 1 | T105: =SUM(T96:T104) -> 157312 | U105: =SUM(U96:U103) -> 142912 | V105: =SUM(V96:V103) -> 0 | W105: =SUM(W96:W103) -> 0 | X105: =SUM(X96:X103) -> 0 | Y105: =SUM(Y96:Y103) -> 14400 | Z105: =SUM(Z96:Z103) -> 76800 | AA105: =SUM(AA96:AA103) -> 66112 | AB105: =SUM(AB96:AB104) -> 54912 | AC105: =SUM(AC96:AC104) -> 88000
A106: Total faces simulação | I106: =I99+I98+I97+I96 -> 12 | J106: =I99+I98+I97+I96 -> 12 | K106: =K100+I98+I97+I96 -> 12 | L106: =K100+I98+I97+I96 -> 12 | M106: =SUM(I106:L106) -> 48 | U106: =U105/T105 -> 0.90846216 | V106: =V105/T105 -> 0 | W106: =W105/T105 -> 0 | X106: =X105/T105 -> 0 | Y106: =Y105/T105 -> 0.091537836 | Z106: =Z105/T105 -> 0.48820179 | AA106: =AA105/T105 -> 0.42026037
A107: Grandes Formatos | I107: =I106/M106 -> 0.25 | Q107: =U105/4 -> 35728 | S107: =Q107/Q112 -> 0.90846216 | Z107: =I99+K100+I98+I96 -> 18 | AA107: =I97 -> 2
A108: MUB | Q108: =V105/4 -> 0 | S108: =Q108/Q112 -> 0 | T108: =Q105/M105 -> 1966.4 | U108: CPFACE | Z108: =Z107/M105 -> 0.9 | AA108: =AA107/M105 -> 0.1
A109: Transportes | Q109: =W105/4 -> 0 | S109: =Q109/Q112 -> 0 | Z109: SHARE FACES
A110: Oportunidades | Q110: =Y105/4 -> 3600 | S110: =Q110/Q112 -> 0.091537836
A111: Aeroporto | Q111: =X105/4 -> 0 | S111: =Q111/Q112 -> 0
Q112: =SUM(Q107:Q111) -> 39328 | S112: =SUM(S107:S111) -> 1
A118: Programação - Ciclo Ouro Promo
A120: 1 CICLO | T120: TOTAL ANO / CICLO
A121: Praça | B121: Exibidores | C121: Pen/Aff | D121: Tipo de Mídia | E121: Estático/Digital | F121: Range de volume ideal | G121: Qtde Sugerida | H121: Periodicidade | I121: Mês Base | M121: TT | N121: Valor Unit. Bruto | O121: Desconto | P121: Valor Unit. Bruto | Q121: Valor total | R121: C.P.M. Formato | S121: % | T121: R$ Total | U121: AMBIENTES | Z121: FORMATO | AB121: EMPRESAS
I122: S1 | J122: S2 | K122: S3 | L122: S4 | M122: Flight | N122: Tabela | O122: (%) | P122: Negociado | Q122: Bruto Negociado | T122: ano
A123: OURO PROMO | U123: GDES | V123: MUB | W123: TRANSP | X123: AERO | Y123: OPORT | Z123: ESTÁTICO | AA123: DIGITAL | AB123: BUREAU | AC123: ATOS
A125: Macapá - AP | B125: Bureau de mídia | C125: 50/156 | D125: Painel de Led | E125: Digital | F125: 2/4 | G125: 1 | H125: Mensal | I125: 1 | M125: 1 | N125: 7800 | O125: 0.34 | P125: =N125*(1-O125) -> 5148 | Q125: =P125*M125*G125 -> 5148 | R125: =(Q125+Q128+#REF!+#REF!)/E102*1000 -> #REF! | S125: =Q125/$Q$137 -> 0.12535307 | T125: =Q125 -> 5148 | U125: =T125 -> 5148 | AA125: =T125 -> 5148 | AB125: =T125 -> 5148
A126: Macapá - AP | B126: Bureau de mídia | C126: 63/153 | D126: Busdoor | E126: Estático | F126: 5/10 | G126: 2 | H126: Mensal | I126: 2 | M126: 1 | N126: 1550 | O126: 0.2 | P126: =N126*(1-O126) -> 1240 | Q126: =P126*M126*G126 -> 2480 | R126: =(Q126+Q129+#REF!+#REF!)/E103*1000 -> #REF! | S126: =Q126/$Q$137 -> 0.06038765 | T126: =Q126 -> 2480 | W126: =T126 -> 2480 | AB126: =T126 -> 2480
A127: Macapá - AP | B127: Bureau de mídia | D127: Bikedoor | E127: Estático | F127: 2/5 | G127: 2 | H127: Diaria | I127: 2 | K127: 2 | M127: 2 | N127: 2450 | O127: 0.2 | P127: =N127*(1-O127) -> 1960 | Q127: =P127*M127*G127 -> 7840 | R127: =(Q127+Q130+#REF!+#REF!)/E104*1000 -> #REF! | S127: =Q127/$Q$137 -> 0.19090289 | T127: =Q127 -> 7840 | W127: =T127 -> 7840 | AB127: =T127 -> 7840
A128: Macapá - AP | B128: Atos | C128: 50/156 | D128: Frontlight | E128: Estático | F128: 2/4 | G128: 1 | H128: Mensal | I128: 1 | M128: 1 | N128: 3500 | O128: 0.2 | P128: =N128*(1-O128) -> 2800 | Q128: =P128*M128*G128 -> 2800 | S128: =Q128/$Q$137 -> 0.068179605 | T128: =Q128 -> 2800 | U128: =T128 -> 2800 | AA128: =T128 -> 2800 | AC128: =T128 -> 2800
A129: Macapá - AP | B129: Atos | C129: 50/156 | D129: Outdoor lonado | E129: Estático | F129: 8/13 | G129: 8 | H129: Mensal | I129: 8 | M129: 1 | N129: 1500 | O129: 0.2 | P129: =N129*(1-O129) -> 1200 | Q129: =P129*M129*G129 -> 9600 | R129: =(Q129+#REF!)/E102*1000 -> #REF! | S129: =Q129/$Q$137 -> 0.23375864 | T129: =Q129 -> 9600 | U129: =T129 -> 9600 | Z129: =T129 -> 9600 | AC129: =T129 -> 9600
A130: Macapá - AP | B130: Atos | C130: 50/156 | D130: Outdoor lonado | E130: Estático | F130: 10/25 | G130: 8 | H130: Mensal | K130: 8 | M130: 1 | N130: 1500 | O130: 0.2 | P130: =N130*(1-O130) -> 1200 | Q130: =P130*M130*G130 -> 9600 | R130: =(Q130+#REF!)/E104*1000 -> #REF! | S130: =Q130/$Q$137 -> 0.23375864 | T130: =Q130 -> 9600 | U130: =T130 -> 9600 | Z130: =T130 -> 9600 | AC130: =T130 -> 9600
A134: Macapá- AP | B134: Aeroporto | T134: =Q134 -> 0 | X134: =T134 -> 0
A135: Macapá-AP | B135: Oportunidades | D135: Marítimos / Ativação | Q135: 3600 | S135: =Q135/Q137 -> 0.087659492 | T135: =Q135 -> 3600 | Y135: =T135 -> 3600
I136: =I137/M137 -> 0.58333333 | K136: =K137/M137 -> 0.41666667
...

Sheet MACAPA PLAN
A1: taxonomia | B1: regional_boticario | C1: uf | D1: praca | E1: exibidores | F1: formato | G1: ranking | H1: pesos | I1: estatico | J1: digital | K1: range_minimo | L1: range_maximo | M1: quantidade | N1: periodicidade | O1: s1 | P1: s2 | Q1: s3 | R1: s4 | S1: flight | T1: unitario_bruto_tabela | U1: desconto | V1: unitario_bruto_negociado | W1: total_bruto_negociado
A2: data produto | B2: norte | C2: ap | D2: macapa | E2: Bureau de mídia | F2: Frontlight | G2: 3 | H2: =VLOOKUP(G2,Pesos!A:B,2,0) -> 0.7 | I2: x | K2: 2 | L2: 3 | M2: 2 | N2: Mensal | O2: 2 | Q2: 1 | S2: 1 | T2: 5200 | U2: 0.34 | V2: =T2*(1-U2) -> 3432 | W2: =V2*S2*M2 -> 6864
A3: data produto | B3: norte | C3: ap | D3: macapa | E3: Bureau de mídia | F3: Painel de Led | G3: 2 | H3: =VLOOKUP(G3,Pesos!A:B,2,0) -> 0.8 | J3: X | K3: 2 | L3: 4 | M3: 2 | N3: Mensal | O3: 2 | S3: 1 | T3: 7800 | U3: 0.34 | V3: =T3*(1-U3) -> 5148 | W3: =V3*S3*M3 -> 10296
A4: data produto | B4: norte | C4: ap | D4: macapa | E4: Atos | F4: Frontlight | G4: 3 | H4: =VLOOKUP(G4,Pesos!A:B,2,0) -> 0.7 | I4: x | K4: 2 | L4: 4 | M4: 1 | N4: Mensal | O4: 1 | S4: 1 | T4: 3500 | U4: 0.2 | V4: =T4*(1-U4) -> 2800 | W4: =V4*S4*M4 -> 2800
A5: data produto | B5: norte | C5: ap | D5: macapa | E5: Atos | F5: Outdoor lonado | G5: 1 | H5: =VLOOKUP(G5,Pesos!A:B,2,0) -> 0.9 | I5: X | K5: 10 | L5: 20 | M5: 15 | N5: Mensal | O5: 15 | S5: 1 | T5: 1500 | U5: 0.2 | V5: =T5*(1-U5) -> 1200 | W5: =V5*S5*M5 -> 18000
A6: data produto | B6: norte | C6: ap | D6: macapa | E6: Atos | F6: Outdoor lonado | G6: 1 | H6: =VLOOKUP(G6,Pesos!A:B,2,0) -> 0.9 | I6: x | K6: 10 | L6: 20 | M6: 15 | N6: Mensal | Q6: 15 | S6: 1 | T6: 1500 | U6: 0.2 | V6: =T6*(1-U6) -> 1200 | W6: =V6*S6*M6 -> 18000
A8: data promo | B8: norte | C8: ap | D8: macapa | E8: Bureau de mídia | F8: Frontlight | G8: 4 | H8: =VLOOKUP(G8,Pesos!A:B,2,0) -> 0.6 | I8: x | K8: 2 | L8: 3 | M8: 1 | N8: Mensal | O8: 1 | S8: 1 | T8: 5200 | U8: 0.34 | V8: =T8*(1-U8) -> 3432 | W8: =V8*S8*M8 -> 3432
A9: data promo | B9: norte | C9: ap | D9: macapa | E9: Bureau de mídia | F9: Painel de Led | G9: 1 | H9: =VLOOKUP(G9,Pesos!A:B,2,0) -> 0.9 | J9: x | K9: 2 | L9: 4 | M9: 1 | N9: Mensal | O9: 1 | S9: 1 | T9: 7800 | U9: 0.34 | V9: =T9*(1-U9) -> 5148 | W9: =V9*S9*M9 -> 5148
A10: data promo | B10: norte | C10: ap | D10: macapa | E10: Bureau de mídia | F10: Busdoor | G10: 2 | H10: =VLOOKUP(G10,Pesos!A:B,2,0) -> 0.8 | I10: x | K10: 5 | L10: 10 | M10: 3 | N10: Mensal | O10: 3 | S10: 1 | T10: 1550 | U10: 0.2 | V10: =T10*(1-U10) -> 1240 | W10: =V10*S10*M10 -> 3720
A11: data promo | B11: norte | C11: ap | D11: macapa | E11: Bureau de mídia | F11: Bikedoor | G11: 5 | H11: =VLOOKUP(G11,Pesos!A:B,2,0) -> 0.5 | I11: x | K11: 2 | L11: 5 | M11: 4 | N11: Diaria | O11: 4 | Q11: 4 | S11: 2 | T11: 2450 | U11: 0.2 | V11: =T11*(1-U11) -> 1960 | W11: =V11*S11*M11 -> 15680
A12: data promo | B12: norte | C12: ap | D12: macapa | E12: Atos | F12: Frontlight | G12: 4 | H12: =VLOOKUP(G12,Pesos!A:B,2,0) -> 0.6 | I12: x | K12: 2 | L12: 4 | M12: 1 | N12: Mensal | O12: 1 | S12: 1 | T12: 3500 | U12: 0.2 | V12: =T12*(1-U12) -> 2800 | W12: =V12*S12*M12 -> 2800
A13: data promo | B13: norte | C13: ap | D13: macapa | E13: Atos | F13: Outdoor lonado | G13: 3 | H13: =VLOOKUP(G13,Pesos!A:B,2,0) -> 0.7 | I13: x | K13: 10 | L13: 20 | M13: 13 | N13: Mensal | O13: 13 | S13: 1 | T13: 1500 | U13: 0.2 | V13: =T13*(1-U13) -> 1200 | W13: =V13*S13*M13 -> 15600
A14: data promo | B14: norte | C14: ap | D14: macapa | E14: Atos | F14: Outdoor lonado | G14: 3 | H14: =VLOOKUP(G14,Pesos!A:B,2,0) -> 0.7 | I14: x | K14: 10 | L14: 20 | M14: 13 | N14: Mensal | Q14: 13 | S14: 1 | T14: 1500 | U14: 0.2 | V14: =T14*(1-U14) -> 1200 | W14: =V14*S14*M14 -> 15600
A16: ouro produto | B16: norte | C16: ap | D16: macapa | E16: Bureau de mídia | F16: Frontlight | G16: 3 | H16: =VLOOKUP(G16,Pesos!A:B,2,0) -> 0.7 | I16: x | K16: 2 | L16: 3 | M16: 1 | N16: Mensal | O16: 1 | S16: 1 | T16: 5200 | U16: 0.34 | V16: =T16*(1-U16) -> 3432 | W16: =V16*S16*M16 -> 3432
A17: ouro produto | B17: norte | C17: ap | D17: macapa | E17: Bureau de mídia | F17: Painel de Led | G17: 2 | H17: =VLOOKUP(G17,Pesos!A:B,2,0) -> 0.8 | J17: x | K17: 2 | L17: 4 | M17: 2 | N17: Mensal | O17: 1 | S17: 1 | T17: 7800 | U17: 0.34 | V17: =T17*(1-U17) -> 5148 | W17: =V17*S17*M17 -> 10296
A18: ouro produto | B18: norte | C18: ap | D18: macapa | E18: Atos | F18: Frontlight | G18: 3 | H18: =VLOOKUP(G18,Pesos!A:B,2,0) -> 0.7 | I18: x | K18: 2 | L18: 4 | M18: 1 | N18: Mensal | O18: 1 | S18: 1 | T18: 3500 | U18: 0.2 | V18: =T18*(1-U18) -> 2800 | W18: =V18*S18*M18 -> 2800
A19: ouro produto | B19: norte | C19: ap | D19: macapa | E19: Atos | F19: Outdoor lonado | G19: 1 | H19: =VLOOKUP(G19,Pesos!A:B,2,0) -> 0.9 | I19: x | K19: 8 | L19: 13 | M19: 8 | N19: Diaria | O19: 1 | S19: 1 | T19: 1500 | U19: 0.2 | V19: =T19*(1-U19) -> 1200 | W19: =V19*S19*M19 -> 9600
A20: ouro produto | B20: norte | C20: ap | D20: macapa | E20: Atos | F20: Outdoor lonado | G20: 1 | H20: =VLOOKUP(G20,Pesos!A:B,2,0) -> 0.9 | I20: x | K20: 10 | L20: 25 | M20: 8 | N20: Mensal | O20: 1 | S20: 1 | T20: 1500 | U20: 0.2 | V20: =T20*(1-U20) -> 1200 | W20: =V20*S20*M20 -> 9600
A22: ouro promo | B22: norte | C22: ap | D22: macapa | E22: Bureau de mídia | F22: Painel de Led | G22: 1 | H22: =VLOOKUP(G22,Pesos!A:B,2,0) -> 0.9 | J22: x | K22: 2 | L22: 4 | M22: 1 | N22: Mensal | O22: 1 | S22: 1 | T22: 5200 | U22: 0.34 | V22: =T22*(1-U22) -> 3432 | W22: =V22*S22*M22 -> 3432
A23: ouro promo | B23: norte | C23: ap | D23: macapa | E23: Bureau de mídia | F23: Busdoor | G23: 2 | H23: =VLOOKUP(G23,Pesos!A:B,2,0) -> 0.8 | I23: x | K23: 5 | L23: 10 | M23: 1 | N23: Mensal | O23: 1 | S23: 1 | T23: 7800 | U23: 0.34 | V23: =T23*(1-U23) -> 5148 | W23: =V23*S23*M23 -> 5148
A24: ouro promo | B24: norte | C24: ap | D24: macapa | E24: Bureau de mídia | F24: Bikedoor | G24: 5 | H24: =VLOOKUP(G24,Pesos!A:B,2,0) -> 0.5 | I24: x | K24: 2 | L24: 5 | M24: 3 | N24: Mensal | O24: 3 | S24: 1 | T24: 1550 | U24: 0.2 | V24: =T24*(1-U24) -> 1240 | W24: =V24*S24*M24 -> 3720
A25: ouro promo | B25: norte | C25: ap | D25: macapa | E25: Atos | F25: Frontlight | G25: 4 | H25: =VLOOKUP(G25,Pesos!A:B,2,0) -> 0.6 | I25: x | K25: 2 | L25: 4 | M25: 4 | N25: Diaria | O25: 4 | Q25: 4 | S25: 2 | T25: 2450 | U25: 0.2 | V25: =T25*(1-U25) -> 1960 | W25: =V25*S25*M25 -> 15680
A26: ouro promo | B26: norte | C26: ap | D26: macapa | E26: Atos | F26: Outdoor lonado | G26: 3 | H26: =VLOOKUP(G26,Pesos!A:B,2,0) -> 0.7 | I26: x | K26: 8 | L26: 13 | M26: 1 | N26: Mensal | O26: 1 | S26: 1 | T26: 3500 | U26: 0.2 | V26: =T26*(1-U26) -> 2800 | W26: =V26*S26*M26 -> 2800
A27: ouro promo | B27: norte | C27: ap | D27: macapa | E27: Atos | F27: Outdoor lonado | G27: 3 | H27: =VLOOKUP(G27,Pesos!A:B,2,0) -> 0.7 | I27: x | K27: 10 | L27: 25 | M27: 13 | N27: Mensal | O27: 13 | S27: 1 | T27: 1500 | U27: 0.2 | V27: =T27*(1-U27) -> 1200 | W27: =V27*S27*M27 -> 15600
A29: prata | B29: norte | C29: ap | D29: macapa | E29: Bureau de mídia | F29: Frontlight | G29: 3 | H29: =VLOOKUP(G29,Pesos!A:B,2,0) -> 0.7 | I29: x | K29: 2 | L29: 3 | M29: 1 | N29: Mensal | O29: 1 | S29: 1 | T29: 5200 | U29: 0.34 | V29: =T29*(1-U29) -> 3432 | W29: =V29*S29*M29 -> 3432
A30: prata | B30: norte | C30: ap | D30: macapa | E30: Bureau de mídia | F30: Painel de Led | G30: 1 | H30: =VLOOKUP(G30,Pesos!A:B,2,0) -> 0.9 | J30: x | K30: 2 | L30: 4 | M30: 1 | N30: Mensal | O30: 1 | S30: 1 | T30: 7800 | U30: 0.34 | V30: =T30*(1-U30) -> 5148 | W30: =V30*S30*M30 -> 5148
A31: prata | B31: norte | C31: ap | D31: macapa | E31: Atos | F31: Frontlight | G31: 3 | H31: =VLOOKUP(G31,Pesos!A:B,2,0) -> 0.7 | I31: x | K31: 2 | L31: 4 | M31: 1 | N31: Mensal | O31: 1 | S31: 1 | T31: 3500 | U31: 0.2 | V31: =T31*(1-U31) -> 2800 | W31: =V31*S31*M31 -> 2800
A32: prata | B32: norte | C32: ap | D32: macapa | E32: Atos | F32: Outdoor lonado | G32: 2 | H32: =VLOOKUP(G32,Pesos!A:B,2,0) -> 0.8 | I32: x | K32: 8 | L32: 13 | M32: 4 | N32: Mensal | O32: 4 | S32: 1 | T32: 1500 | U32: 0.2 | V32: =T32*(1-U32) -> 1200 | W32: =V32*S32*M32 -> 4800
A33: prata | B33: norte | C33: ap | D33: macapa | E33: Atos | F33: Outdoor lonado | G33: 2 | H33: =VLOOKUP(G33,Pesos!A:B,2,0) -> 0.8 | I33: x | K33: 10 | L33: 25 | M33: 4 | N33: Mensal | O33: 4 | S33: 1 | T33: 1500 | U33: 0.2 | V33: =T33*(1-U33) -> 1200 | W33: =V33*S33*M33 -> 4800
E38: cpf mínimo | F38: cpf plano | G38: cpf máximo
A39: DATA PRODUTO | E39: =F39*(1-10%) -> 1567.5429 | F39: =MACAPA!T46 -> 1741.7143 | G39: =F39*(1+15%) -> 2002.9714
A40: DATA PROMO | E40: =F40*(1-25%) -> 1255.875 | F40: =MACAPA!T75 -> 1674.5 | G40: =F40*(1+5%) -> 1758.225
A41: OURO PRODUTO | E41: =F41*(1-15%) -> 1671.44 | F41: =MACAPA!T108 -> 1966.4 | G41: =F41*(1+15%) -> 2261.36
A42: OURO PROMO | E42: =F42*(1-25%) -> 1283.375 | F42: =MACAPA!T140 -> 1711.1667 | G42: =F42*(1+5%) -> 1796.725
A43: PRATA | E43: =F43*(1-25%) -> 1600.9091 | F43: =MACAPA!T172 -> 2134.5455 | G43: =F43*(1+5%) -> 2241.2727
E45: ranking semanas - distribuição investimento
A46: DATA PRODUTO | E46: 0.57 | G46: 0.43
A47: DATA PROMO | E47: 0.57 | G47: 0.43
A48: OURO PRODUTO | E48: 0.6 | G48: 0.4
A49: OURO PROMO | E49: 0.58 | G49: 0.42
A50: PRATA | E50: 0.64 | G50: 0.36
E54: ranking semanas - distribuição audiência
A55: DATA PRODUTO | E55: 0.25 | F55: 0.25 | G55: 0.25 | H55: 0.25
A56: DATA PROMO | E56: 0.27 | F56: 0.23 | G56: 0.27 | H56: 0.23
A57: OURO PRODUTO | E57: 0.34 | F57: 0.33 | G57: 0.33
A58: OURO PROMO | E58: 0.34 | F58: 0.32 | G58: 0.34
A59: PRATA | E59: 0.34 | F59: 0.33 | G59: 0.33

Sheet MANAUS
A1: ESTUDO MANAUS
A2: IBGE 2024/ CENSO 2022
A7: INVESTIMENTO MANAUS CAPITAL OOH 2024 | B7: 1306076
A8: INVESTIMENTO AMAZONAS OOH 2024 | B8: 1306076
A10: R$ BRUTO MANAUS CAPITAL - 2025 OOH | B10: 2219458.8
A11: BUDGET BRUTO AMAZONAS - 2025 OOH (100%) | B11: 2219458.8
A14: Exclusão de Bronze
A15: CICLOS/MEDALHAS | C15: % BUDGET/CICLO | D15: R$ MEDALHA | E15: R$ UNIT. MEDALHAS
A16: Data | B16: 3 - 2 produto/1 promo | C16: 0.39 | D16: 865588.91 | E16: 288529.64
A17: Ouro | B17: 5 - 4 produto/ 1 promo | C17: 0.4 | D17: 887783.5 | E17: 221945.88
A18: Prata | B18: 3 | C18: 0.21 | D18: 466086.34 | E18: 116521.58
B19: 11 ciclos | C19: 1 | D19: 2219458.8
A21: População Capital - 2.063.689 | B21: 2063689
A22: População Target - AS ABC 18/49 (logan) | B22: 1160368
E23: Cobertura total - Data Produto | F23: 47% | H23: Cobertura total - Data Promo | J23: 62%
E24: Frequencia | F24: 21 | H24: Frequencia | J24: 27
E25: TRP | F25: 1686 | H25: TRP | J25: 1686
E26: OTS | F26: 11.298.463 | H26: OTS | J26: 19.564.087
A27: Programação - Ciclo Data Produto
A29: 1 CICLO | T29: TOTAL ANO / CICLO
A30: Praça | B30: Exibidores | C30: Pen/Aff | D30: Canais | E30: Formato | F30: Range de volume ideal | G30: Qtdade | H30: Periodicidade | I30: Mês Base | M30: TT | N30: R$ Unit Bruto | O30: Desconto | P30: R$ Unit Bruto | Q30: R$ TT Bruto | R30: C.P.M. Formato | S30: % | T30: R$ Total | U30: AMBIENTES | Z30: FORMATO | AB30: EMPRESAS
I31: S1 | J31: S2 | K31: S3 | L31: S4 | M31: Flight | N31: Tabela | O31: (%) | P31: Negociado | Q31: Negociado | T31: ano
A32: DATAS MÃES/NATAL | U32: GDES | V32: MUB | W32: TRANSP | X32: AERO | Y32: OPORT | Z32: ESTÁTICO | AA32: DIGITAL | AB32: WEOOH | AC32: BME | AD32: THE VOICE | AE32: VSP | AF32: WVK | AG32: PURAKA | AH32: BUREAU | AI32: S2X
A34: Manaus - AM | B34: WeOOH | C34: 50/156 | D34: Painel de Led | E34: Digital | F34: 6/12 | G34: 1 | H34: Mensal | I34: 1 | M34: 1 | N34: 35211.99 | O34: 0.55 | P34: =N34*(1-O34) -> 15845.395 | Q34: =P34*M34*G34 -> 15845.395 | R34: =(Q34+Q35+Q38+#REF!)/E12*1000 -> #REF! | S34: =Q34/$Q$51 -> 0.054921098 | T34: =Q34*2 -> 31690.791 | U34: =T34 -> 31690.791 | AA34: =T34 -> 31690.791 | AB34: =T34 -> 31690.791
A35: Manaus - AM | B35: Brasil Midia Exterior | C35: 50/156 | D35: Painel de Led | E35: Digital | F35: 6/12 | G35: 1 | H35: Mensal | I35: 1 | M35: 1 | N35: 7000 | O35: 0.1 | P35: =N35*(1-O35) -> 6300 | Q35: =P35*M35*G35 -> 6300 | S35: =Q35/$Q$51 -> 0.02183618 | T35: =Q35*2 -> 12600 | U35: =T35 -> 12600 | AA35: =T35 -> 12600 | AC35: =T35 -> 12600
A36: Manaus - AM | B36: Brasil Midia Exterior | C36: 50/156 | D36: Frontlight | E36: Estático | F36: 7/14 | G36: 1 | H36: Bisemanal | I36: 1 | M36: 1 | N36: 7500 | O36: 0.1 | P36: =N36*(1-O36) -> 6750 | Q36: =P36*M36*G36 -> 6750 | R36: =(Q36+#REF!)/E12*1000 -> #REF! | S36: =Q36/$Q$51 -> 0.023395908 | T36: =Q36*2 -> 13500 | U36: =T36 -> 13500 | Z36: =T36 -> 13500 | AC36: =T36 -> 13500
A37: Manaus - AM | B37: Brasil Midia Exterior | C37: 50/156 | D37: Outdoor lonado | E37: Estático | F37: 16/25 | G37: 20 | H37: Mensal | I37: 20 | M37: 1 | N37: 2900 | O37: 0.1 | P37: =N37*(1-O37) -> 2610 | Q37: =P37*M37*G37 -> 52200 | R37: =(Q37+#REF!)/E12*1000 -> #REF! | S37: =Q37/$Q$51 -> 0.18092835 | T37: =Q37*2 -> 104400 | U37: =T37 -> 104400 | Z37: =T37 -> 104400 | AC37: =T36 -> 13500
A38: Manaus - AM | B38: The Voice | C38: 50/156 | D38: Painel de Led | E38: Digital | F38: 6/12 | G38: 1 | H38: Mensal | I38: 1 | M38: 1 | N38: 17576 | O38: 0.55 | P38: =N38*(1-O38) -> 7909.2 | Q38: =P38*M38*G38 -> 7909.2 | S38: =Q38/$Q$51 -> 0.027413765 | T38: =Q38*2 -> 15818.4 | U38: =T38 -> 15818.4 | AA38: =T38 -> 15818.4 | AD38: =T37 -> 104400
A39: Manaus - AM | B39: VSP Midia | C39: 50/156 | D39: Frontlight | E39: Estático | F39: 7/14 | G39: 1 | H39: Mensal | I39: 1 | M39: 1 | N39: 5500 | O39: 0.15 | P39: =N39*(1-O39) -> 4675 | Q39: =P39*M39*G39 -> 4675 | R39: =(Q39+#REF!+Q40)/E12*1000 -> #REF! | S39: =Q39/$Q$51 -> 0.016203832 | T39: =Q39*2 -> 9350 | U39: =T39 -> 9350 | Z39: =T39 -> 9350 | AE39: =T39 -> 9350
A40: Manaus - AM | B40: WVK midias | C40: 50/156 | D40: Outdoor lonado | E40: Estática | F40: 16/25 | G40: 20 | H40: Mensal | K40: 20 | M40: 1 | N40: 3222.65 | O40: 0.2 | P40: =N40*(1-O40) -> 2578.12 | Q40: =P40*M40*G40 -> 51562.4 | S40: =Q40/$Q$51 -> 0.17871839 | T40: =Q40*2 -> 103124.8 | U40: =T40 -> 103124.8 | Z40: =T40 -> 103124.8 | AF40: =T40 -> 103124.8
A41: Manaus - AM | B41: Puraka | C41: 50/155 | D41: Painel de Led | E41: Digital | F41: 6/12 | G41: 5 | H41: Mensal | I41: 5 | M41: 1 | N41: 12150 | O41: 0.4 | P41: =N41*(1-O41) -> 7290 | Q41: =P41*M41*G41 -> 36450 | S41: =Q41/$Q$51 -> 0.1263379 | T41: =Q41*2 -> 72900 | U41: =T41 -> 72900 | AA41: =T41 -> 72900 | AG41: =T41 -> 72900
A42: Manaus - AM | B42: Puraka | C42: 50/155 | D42: Frontlight | E42: Estático | F42: 7/14 | G42: 4 | H42: Mensal | I42: 4 | M42: 1 | N42: 15000 | O42: 0.49 | P42: =N42*(1-O42) -> 7650 | Q42: =P42*M42*G42 -> 30600 | S42: =Q42/$Q$51 -> 0.10606145 | T42: =Q42*2 -> 61200 | U42: =T42 -> 61200 | Z42: =T42 -> 61200 | AG42: =T42 -> 61200
A43: Manaus - AM | B43: Bureau Midia OOH | C43: 50/155 | D43: Painel de Led | E43: Digital | F43: 6/12 | G43: 2 | H43: Mensal | I43: 2 | M43: 1 | N43: 8980 | O43: 0.25 | P43: =N43*(1-O43) -> 6735 | Q43: =P43*M43*G43 -> 13470 | S43: =Q43/$Q$51 -> 0.046687833 | T43: =Q43*2 -> 26940 | U43: =T43 -> 26940 | AA43: =T43 -> 26940 | AH43: =T43 -> 26940
A44: Manaus - AM | B44: Bureau Midia OOH | C44: 50/155 | D44: Frontlight | E44: Estático | F44: 7/14 | G44: 2 | H44: Mensal | I44: 2 | M44: 1 | N44: 14500 | O44: 0.25 | P44: =N44*(1-O44) -> 10875 | Q44: =P44*M44*G44 -> 21750 | S44: =Q44/$Q$51 -> 0.075386814 | T44: =Q44*2 -> 43500 | U44: =T44 -> 43500 | Z44: =T44 -> 43500 | AH44: =T44 -> 43500
A48: Manaus - AM | B48: Aeroporto | Q48: =P48*M48*G48 -> 0 | S48: =Q48/Q51 -> 0 | T48: =Q48*2 -> 0 | X48: =T48 -> 0 | AA48: =X48 -> 0
A49: Manaus - AM | B49: Oportunidades | Q49: 41000 | S49: =Q49/Q51 -> 0.14210848 | T49: =Q49*2 -> 82000 | Y49: =T49 -> 82000
I50: =I51/M51 -> 0.55555556 | K50: =K51/M51 -> 0.44444444
A51: Total faces compra | I51: =I39+I38+I37+I36+I35+I34 -> 25 | K51: =+K40 -> 20 | M51: =SUM(I51:L51) -> 45 | Q51: =SUM(Q34:Q50) -> 288512 | S51: =SUM(S34:S49) -> 1 | T51: =SUM(T34:T50) -> 577023.99 | U51: =SUM(U34:U49) -> 495023.99 | V51: =SUM(V34:V49) -> 0 | W51: =SUM(W34:W49) -> 0 | X51: =SUM(X34:X49) -> 0 | Y51: =SUM(Y34:Y49) -> 82000 | Z51: =SUM(Z34:Z49) -> 335074.8 | AA51: =SUM(AA34:AA49) -> 159949.19 | AB51: =SUM(AB34:AB50) -> 31690.791 | AC51: =SUM(AC34:AC50) -> 39600 | AD51: =SUM(AD34:AD50) -> 104400 | AE51: =SUM(AE34:AE50) -> 9350 | AF51: =SUM(AF34:AF50) -> 103124.8 | AG51: =SUM(AG34:AG50) -> 134100 | AH51: =SUM(AH34:AH50) -> 70440 | AI51: =SUM(AI33:AI50) -> 0
A52: Total faces simulação | I52: =I39+I38+I37+I36+I35+I34 -> 25 | J52: =I39+I38+I37+I36+I35+I34 -> 25 | K52: =+K40+I39+I38+I36+I35+I34 -> 25 | L52: =K40+I39+I38+I36+I35+I34 -> 25 | M52: =SUM(I52:L52) -> 100 | U52: =U51/T51 -> 0.85789152 | V52: =V51/T51 -> 0 | W52: =W51/T51 -> 0 | X52: =X51/T51 -> 0 | Y52: =Y51/T51 -> 0.14210848 | Z52: =Z51/T51 -> 0.58069475 | AA52: =AA51/T51 -> 0.27719678
A53: Grandes Formatos | I53: 0.25 | Q53: =U51/2 -> 247512 | S53: =Q53/Q58 -> 0.85789152 | Z53: =I36+I37+I39+K40 -> 42 | AA53: =I34+I35+I38 -> 3
A54: MUB | Q54: =V51/2 -> 0 | S54: =Q54/Q58 -> 0 | T54: =Q51/M51 -> 6411.3777 | U54: CPFACE | Z54: =Z53/M51 -> 0.93333333 | AA54: =AA53/M51 -> 0.066666667
A55: Transportes | Q55: =W51/2 -> 0 | S55: =Q55/Q58 -> 0 | Z55: SHARE FACES
A56: Oportunidades | Q56: =Y51/2 -> 41000 | S56: =Q56/Q58 -> 0.14210848
A57: Aeroporto | Q57: =X51/2 -> 0 | S57: =Q57/Q58 -> 0
Q58: =SUM(Q53:Q57) -> 288512 | S58: =SUM(S53:S57) -> 1
A60: Programação - Ciclo Data Promo
A62: 1 CICLO | T62: TOTAL ANO / CICLO
A63: Praça | B63: Exibidores | C63: Pen/Aff | D63: Canais | E63: Formato | F63: Range de volume ideal | G63: Qtdade | H63: Periodicidade | I63: Mês Base | M63: TT | N63: R$ Unit Bruto | O63: Desconto | P63: R$ Unit Bruto | Q63: R$ TT Bruto | R63: C.P.M. Formato | S63: % | T63: R$ Total | U63: AMBIENTES | Z63: FORMATO | AB63: EMPRESAS
I64: S1 | J64: S2 | K64: S3 | L64: S4 | M64: Flight | N64: Tabela | O64: (%) | P64: Negociado | Q64: Negociado | T64: ano
A65: DATAS BW | U65: GDES | V65: MUB | W65: TRANSP | X65: AERO | Y65: OPORT | Z65: ESTÁTICO | AA65: DIGITAL | AB65: WEOOH | AC65: BME | AD65: THE VOICE | AE65: VSP | AF65: WVK | AG65: PURAKA | AH65: BUREAU | AI65: S2X
A67: Manaus - AM | B67: WeOOH | C67: 50/156 | D67: Painel de Led | E67: Digital | F67: 6/12 | G67: 1 | H67: Mensal | I67: 1 | M67: 1 | N67: 35211.99 | O67: 0.55 | P67: =N67*(1-O67) -> 15845.395 | Q67: =P67*M67*G67 -> 15845.395 | R67: =(Q67+Q68+Q71+#REF!)/E44*1000 -> #REF! | S67: =Q67/$Q$51 -> 0.054921098 | T67: =Q67 -> 15845.395 | U67: =T67 -> 15845.395 | AA67: =T67 -> 15845.395 | AB67: =T67 -> 15845.395
A68: Manaus - AM | B68: Brasil Midia Exterior | C68: 50/156 | D68: Painel de Led | E68: Digital | F68: 6/12 | G68: 1 | H68: Mensal | I68: 1 | M68: 1 | N68: 7000 | O68: 0.1 | P68: =N68*(1-O68) -> 6300 | Q68: =P68*M68*G68 -> 6300 | S68: =Q68/$Q$51 -> 0.02183618 | T68: =Q68 -> 6300 | U68: =T68 -> 6300 | AA68: =T68 -> 6300 | AC68: =T68 -> 6300
A69: Manaus - AM | B69: Brasil Midia Exterior | C69: 50/156 | D69: Frontlight | E69: Estático | F69: 7/14 | G69: 1 | H69: Bisemanal | I69: 1 | M69: 1 | N69: 7500 | O69: 0.1 | P69: =N69*(1-O69) -> 6750 | Q69: =P69*M69*G69 -> 6750 | R69: =(Q69+#REF!)/E44*1000 -> #REF! | S69: =Q69/$Q$51 -> 0.023395908 | T69: =Q69 -> 6750 | U69: =T69 -> 6750 | Z69: =T69 -> 6750 | AC69: =T69 -> 6750
A70: Manaus - AM | B70: Brasil Midia Exterior | C70: 50/156 | D70: Outdoor lonado | E70: Estático | F70: 16/25 | G70: 21 | H70: Mensal | I70: 20 | M70: 1 | N70: 2900 | O70: 0.1 | P70: =N70*(1-O70) -> 2610 | Q70: =P70*M70*G70 -> 54810 | R70: =(Q70+#REF!)/E44*1000 -> #REF! | S70: =Q70/$Q$51 -> 0.18997477 | T70: =Q70 -> 54810 | U70: =T70 -> 54810 | Z70: =T70 -> 54810 | AC70: =T70 -> 54810
A71: Manaus - AM | B71: The Voice | C71: 50/156 | D71: Painel de Led | E71: Digital | F71: 6/12 | G71: 1 | H71: Mensal | I71: 1 | M71: 1 | N71: 17576 | O71: 0.55 | P71: =N71*(1-O71) -> 7909.2 | Q71: =P71*M71*G71 -> 7909.2 | S71: =Q71/$Q$51 -> 0.027413765 | T71: =Q71 -> 7909.2 | U71: =T71 -> 7909.2 | AA71: =T71 -> 7909.2 | AD71: =T71 -> 7909.2
A72: Manaus - AM | B72: VSP Midia | C72: 50/156 | D72: Frontlight | E72: Estático | F72: 7/14 | G72: 1 | H72: Mensal | I72: 1 | M72: 1 | N72: 5500 | O72: 0.15 | P72: =N72*(1-O72) -> 4675 | Q72: =P72*M72*G72 -> 4675 | R72: =(Q72+#REF!+Q73)/E44*1000 -> #REF! | S72: =Q72/$Q$51 -> 0.016203832 | T72: =Q72 -> 4675 | U72: =T72 -> 4675 | Z72: =T72 -> 4675 | AE72: =T72 -> 4675
A73: Manaus - AM | B73: WVK midias | C73: 50/156 | D73: Outdoor lonado | E73: Estática | F73: 16/25 | G73: 21 | H73: Mensal | K73: 20 | M73: 1 | N73: 3222.65 | O73: 0.2 | P73: =N73*(1-O73) -> 2578.12 | Q73: =P73*M73*G73 -> 54140.52 | S73: =Q73/$Q$51 -> 0.18765431 | T73: =Q73 -> 54140.52 | U73: =T73 -> 54140.52 | Z73: =T73 -> 54140.52 | AF73: =T73 -> 54140.52
A74: Manaus - AM | B74: S2X Promoções | C74: 30/155 | D74: Carro de Som | E74: Som | G74: 5 | H74: Diaria 8 horas | I74: 5 | J74: 5 | K74: 5 | L74: 5 | M74: 1 | N74: =265*8 -> 2120 | O74: 0.4 | P74: =N74*(1-O74) -> 1272 | Q74: =P74*M74*G74 -> 6360 | S74: =Q74/$Q$51 -> 0.022044144 | T74: =Q74 -> 6360 | W74: =T74 -> 6360 | Z74: =W74 -> 6360 | AI74: =T74 -> 6360
A75: Manaus - AM | B75: Puraka | C75: 50/155 | D75: Painel de Led | E75: Digital | F75: 6/12 | G75: 3 | H75: Mensal | I75: 3 | M75: 1 | N75: 12150 | O75: 0.4 | P75: =N75*(1-O75) -> 7290 | Q75: =P75*M75*G75 -> 21870 | S75: =Q75/$Q$51 -> 0.075802741 | T75: =Q75 -> 21870 | U75: =T75 -> 21870 | AA75: =T75 -> 21870 | AG75: =T75 -> 21870
A76: Manaus - AM | B76: Puraka | C76: 50/155 | D76: Frontlight | E76: Estático | F76: 7/14 | G76: 2 | H76: Mensal | I76: 2 | M76: 1 | N76: 15000 | O76: 0.49 | P76: =N76*(1-O76) -> 7650 | Q76: =P76*M76*G76 -> 15300 | S76: =Q76/$Q$51 -> 0.053030724 | T76: =Q76 -> 15300 | U76: =T76 -> 15300 | Z76: =T76 -> 15300 | AG76: =T76 -> 15300
A77: Manaus - AM | B77: Bureau Midia OOH | C77: 50/155 | D77: Painel de Led | E77: Digital | F77: 6/12 | G77: 2 | H77: Mensal | I77: 2 | M77: 1 | N77: 8980 | O77: 0.25 | P77: =N77*(1-O77) -> 6735 | Q77: =P77*M77*G77 -> 13470 | S77: =Q77/$Q$51 -> 0.046687833 | T77: =Q77 -> 13470 | U77: =T77 -> 13470 | AA77: =T77 -> 13470 | AH77: =T77 -> 13470
A78: Manaus - AM | B78: Bureau Midia OOH | C78: 50/155 | D78: Frontlight | E78: Estático | F78: 7/14 | G78: 2 | H78: Mensal | I78: 2 | M78: 1 | N78: 14500 | O78: 0.25 | P78: =N78*(1-O78) -> 10875 | Q78: =P78*M78*G78 -> 21750 | S78: =Q78/$Q$51 -> 0.075386814 | T78: =Q78 -> 21750 | U78: =T78 -> 21750 | Z78: =T78 -> 21750 | AH78: =T78 -> 21750
A79: Manaus - AM | B79: Bureau Midia OOH | C79: 63/153 | D79: BackBus | E79: Estático | F79: 6/15 | G79: 10 | H79: Mensal | I79: 10 | M79: 1 | N79: 1800 | O79: 0.2 | P79: =N79*(1-O79) -> 1440 | Q79: =P79*M79*G79 -> 14400 | S79: =Q79/$Q$51 -> 0.04991127 | T79: =Q79 -> 14400 | W79: =T79 -> 14400 | Z79: =T79 -> 14400 | AH79: =T79 -> 14400
A82: Manaus - AM | B82: Aeroporto | Q82: =P82*M82*G82 -> 0 | S82: =Q82/Q85 -> 0 | T82: =Q82 -> 0 | AA82: =X82 -> 0
A83: Manaus - AM | B83: Oportunidades | Q83: 45000 | S83: =Q83/Q85 -> 0.1559359 | T83: =Q83 -> 45000 | Y83: =T83 -> 45000
I84: =I85/M85 -> 0.58333333 | J84: =J85/M85 -> 0.05952381 | K84: =K85/M85 -> 0.29761905 | L84: =L85/M85 -> 0.05952381
A85: Total faces compra | I85: =I74+I72+I71+I70+I69+I68+I67+I75+I76+I77+I78+I79 -> 49 | J85: =J74 -> 5 | K85: =K74+K73 -> 25 | L85: =L74 -> 5 | M85: =SUM(I85:L85) -> 84 | Q85: =SUM(Q67:Q84) -> 288580.12 | S85: =SUM(S67:S83) -> 1.0001993 | T85: =SUM(T67:T84) -> 288580.12 | U85: =SUM(U67:U83) -> 222820.12 | V85: =SUM(V67:V83) -> 0 | W85: =SUM(W67:W83) -> 20760 | X85: =SUM(X67:X83) -> 0 | Y85: =SUM(Y67:Y83) -> 45000 | Z85: =SUM(Z67:Z83) -> 178185.52 | AA85: =SUM(AA67:AA83) -> 65394.595 | AB85: =SUM(AB67:AB83) -> 15845.395 | ... AD85: =SUM(AD67:AD83) -> 7909.2 | AE85: =SUM(AE67:AE84) -> 4675 | AF85: =SUM(AF67:AF84) -> 54140.52 | AG85: =SUM(AG67:AG84) -> 37170 | AH85: =SUM(AH67:AH84) -> 49620 | AI85: =SUM(AI67:AI84) -> 6360
A86: Total faces simulação | I86: =I74+I72+I71+I70+I69+I68+I67+I75+I76+I77+I78+I79 -> 49 | J86: =I72+I71+I70+I69+I68+I67+J74+I75+I76+I77+I78+I79 -> 49 | K86: =K74+K73+I72+I71+I69+I68+I67+I75+I76+I77+I78+I79 -> 49 | L86: =K73+I72+I71+I69+I68+I67+L74+I75+I76+I77+I78+I79 -> 49 | M86: =SUM(I86:L86) -> 196 | U86: =U85/T85 -> 0.77212567 | V86: =V85/T85 -> 0 | W86: =W85/T85 -> 0.071938428 | X86: =X85/T85 -> 0 | Y86: =Y85/T85 -> 0.1559359 | Z86: =Z85/T85 -> 0.61745599 | AA86: =AA85/T85 -> 0.22660811
A87: Grandes Formatos | I87: 0.25 | Q87: =U85 -> 222820.12 | S87: =Q87/Q92 -> 0.77212567 | Z87: =I69+I70+I72+K73+I76+I78+I79 -> 56 | AA87: =I67+I68+I71+I75+I77 -> 8
A88: MUB | Q88: =V85 -> 0 | S88: =Q88/Q92 -> 0 | T88: =Q85/M85 -> 3435.4776 | U88: CPFACE | Z88: =Z87/M85 -> 0.66666667 | AA88: =AA87/M85 -> 0.095238095
A89: Transportes | Q89: =W85 -> 20760 | S89: =Q89/Q92 -> 0.071938428 | Z89: SHARE FACES
A90: Oportunidades | Q90: =Y85 -> 45000 | S90: =Q90/Q92 -> 0.1559359
A91: Aeroporto | Q91: =X85 -> 0 | S91: =Q91/Q92 -> 0
Q92: =SUM(Q87:Q91) -> 288580.12 | S92: =SUM(S87:S91) -> 1
E96: Cobertura total - Ouro Produto | F96: 47% | G96: Cobertura total - Ouro Promo | I96: 0.56
E97: Frequencia | F97: 21 | G97: Frequencia | I97: 25
E98: TRP | F98: 1686 | G98: TRP | I98: 1407
E99: OTS | F99: 11.298.463 | G99: OTS | I99: 16333567
A101: Programação - Ciclo Ouro Produto
A103: 1 CICLO | T103: TOTAL ANO / CICLO
A104: Praça | B104: Exibidores | C104: Pen/Aff | D104: Tipo de Mídia | E104: Estático/Digital | F104: Range de volume ideal | G104: Qtde Sugerida | H104: Periodicidade | I104: Mês Base | M104: TT | N104: Valor Unit. Bruto | O104: Desconto | P104: Valor Unit. Bruto | Q104: Valor total | R104: C.P.M. Formato | S104: % | T104: R$ Total | U104: AMBIENTES | Z104: FORMATO | AB104: EMPRESAS
I105: S1 | J105: S2 | K105: S3 | L105: S4 | M105: Flight | N105: Tabela | O105: (%) | P105: Negociado | Q105: Bruto Negociado | T105: ano
A106: OURO PRODUTO | U106: GDES | V106: MUB | W106: TRANSP | X106: AERO | Y106: OPORT | Z106: ESTÁTICO | AA106: DIGITAL | AB106: WEOOH | AC106: BME | AD106: THE VOICE | AE106: VSP | AF106: WVK | AG106: PURAKA | AH106: BUREAU | AI106: S2X
A108: Manaus - AM | B108: WeOOH | C108: 50/156 | D108: Painel de Led | E108: Digital | F108: 4/8 | G108: 1 | H108: Mensal | I108: 1 | M108: 1 | N108: 35211.99 | O108: 0.55 | P108: =N108*(1-O108) -> 15845.395 | Q108: =P108*M108*G108 -> 15845.395 | R108: =(Q108+Q109+Q112+#REF!)/E89*1000 -> #REF! | S108: =Q108/$Q$125 -> 0.071568634 | T108: =Q108*4 -> 63381.582 | U108: =T108 -> 63381.582 | AA108: =T108 -> 63381.582 | AB108: =T108 -> 63381.582
A109: Manaus - AM | B109: Brasil Midia Exterior | C109: 50/156 | D109: Painel de Led | E109: Digital | F109: 4/8 | G109: 1 | H109: Mensal | I109: 1 | M109: 1 | N109: 7000 | O109: 0.1 | P109: =N109*(1-O109) -> 6300 | Q109: =P109*M109*G109 -> 6300 | S109: =Q109/$Q$125 -> 0.028455105 | T109: =Q109*4 -> 25200 | U109: =T109 -> 25200 | AA109: =T109 -> 25200 | AC109: =T109 -> 25200
A110: Manaus - AM | B110: Brasil Midia Exterior | C110: 50/156 | D110: Frontlight | E110: Estático | F110: 2/6 | G110: 1 | H110: Bisemanal | I110: 1 | M110: 1 | N110: 7500 | O110: 0.1 | P110: =N110*(1-O110) -> 6750 | Q110: =P110*M110*G110 -> 6750 | R110: =(Q110+#REF!)/E89*1000 -> #REF! | S110: =Q110/$Q$125 -> 0.030487613 | T110: =Q110*4 -> 27000 | U110: =T110 -> 27000 | Z110: =T110 -> 27000 | AC110: =T110 -> 27000
A111: Manaus - AM | B111: Brasil Midia Exterior | C111: 50/156 | D111: Outdoor lonado | E111: Estático | F111: 10/20 | G111: 15 | H111: Mensal | I111: 20 | M111: 1 | N111: 2900 | O111: 0.1 | P111: =N111*(1-O111) -> 2610 | Q111: =P111*M111*G111 -> 39150 | R111: =(Q111+#REF!)/E89*1000 -> #REF! | S111: =Q111/$Q$125 -> 0.17682815 | T111: =Q111*4 -> 156600 | U111: =T111 -> 156600 | Z111: =T111 -> 156600 | AC111: =T111 -> 156600
A112: Manaus - AM | B112: The Voice | C112: 50/156 | D112: Painel de Led | E112: Digital | F112: 4/8 | G112: 1 | H112: Mensal | I112: 1 | M112: 1 | N112: 17576 | O112: 0.55 | P112: =N112*(1-O112) -> 7909.2 | Q112: =P112*M112*G112 -> 7909.2 | S112: =Q112/$Q$125 -> 0.035723352 | T112: =Q112*4 -> 31636.8 | U112: =T112 -> 31636.8 | AA112: =T112 -> 31636.8 | AD112: =T112 -> 31636.8
A113: Manaus - AM | B113: VSP Midia | C113: 50/156 | D113: Frontlight | E113: Estático | F113: 2/6 | G113: 1 | H113: Mensal | I113: 1 | M113: 1 | N113: 5500 | O113: 0.15 | P113: =N113*(1-O113) -> 4675 | Q113: =P113*M113*G113 -> 4675 | R113: =(Q113+#REF!+Q114)/E89*1000 -> #REF! | S113: =Q113/$Q$125 -> 0.021115495 | T113: =Q113*4 -> 18700 | U113: =T113 -> 18700 | Z113: =T113 -> 18700 | AE113: =T113 -> 18700
A114: Manaus - AM | B114: WVK midias | C114: 50/156 | D114: Outdoor lonado | E114: Estática | F114: 10/20 | G114: 15 | H114: Mensal | K114: 20 | M114: 1 | N114: 3222.65 | O114: 0.2 | P114: =N114*(1-O114) -> 2578.12 | Q114: =P114*M114*G114 -> 38671.8 | S114: =Q114/$Q$125 -> 0.17466828 | T114: =Q114*4 -> 154687.2 | U114: =T114 -> 154687.2 | Z114: =T114 -> 154687.2 | AF114: =T114 -> 154687.2
A115: Manaus - AM | B115: Puraka | C115: 50/155 | D115: Painel de Led | E115: Digital | F115: 4/8 | G115: 2 | H115: Mensal | I115: 2 | M115: 1 | N115: 12150 | O115: 0.4 | P115: =N115*(1-O115) -> 7290 | Q115: =P115*M115*G115 -> 14580 | S115: =Q115/$Q$125 -> 0.065853243 | T115: =Q115*4 -> 58320 | U115: =T115 -> 58320 | AA115: =T115 -> 58320 | AG115: =T115 -> 58320
A116: Manaus - AM | B116: Puraka | C116: 50/155 | D116: Frontlight | E116: Estático | F116: 2/6 | G116: 2 | H116: Mensal | I116: 2 | M116: 1 | N116: 15000 | O116: 0.49 | P116: =N116*(1-O116) -> 7650 | Q116: =P116*M116*G116 -> 15300 | S116: =Q116/$Q$125 -> 0.069105255 | T116: =Q116*4 -> 61200 | U116: =T116 -> 61200 | Z116: =T116 -> 61200 | AG116: =T116 -> 61200
A117: Manaus - AM | B117: Bureau Midia OOH | C117: 50/155 | D117: Painel de Led | E117: Digital | F117: 4/8 | G117: 2 | H117: Mensal | I117: 2 | M117: 1 | N117: 8980 | O117: 0.25 | P117: =N117*(1-O117) -> 6735 | Q117: =P117*M117*G117 -> 13470 | S117: =Q117/$Q$125 -> 0.060839725 | T117: =Q117*4 -> 53880 | U117: =T117 -> 53880 | AA117: =T117 -> 53880 | AH117: =T117 -> 53880
A118: Manaus - AM | B118: Bureau Midia OOH | C118: 50/155 | D118: Frontlight | E118: Estático | F118: 2/6 | G118: 2 | H118: Mensal | I118: 2 | M118: 1 | N118: 14500 | O118: 0.25 | P118: =N118*(1-O118) -> 10875 | Q118: =P118*M118*G118 -> 21750 | S118: =Q118/$Q$125 -> 0.098237863 | T118: =Q118*4 -> 87000 | U118: =T118 -> 87000 | Z118: =T118 -> 87000 | AH118: =T118 -> 87000
A122: Manaus - AM | B122: Aeroporto | Q122: =P122*M122*G122 -> 0 | S122: =Q122/Q125 -> 0 | T122: =Q122*2 -> 0 | X122: =T122 -> 0 | AA122: =X122 -> 0
A123: Manaus - AM | B123: Oportunidades | Q123: 37000 | S123: =Q123/Q125 -> 0.16711728 | T123: =Q123*4 -> 148000 | Y123: =T123 -> 148000
I124: =I125/M125 -> 0.55555556 | K124: =K125/M125 -> 0.44444444
A125: Total faces compra | I125: =I113+I112+I111+I110+I109+I108 -> 25 | K125: =+K114 -> 20 | M125: =SUM(I125:L125) -> 45 | Q125: =SUM(Q108:Q124) -> 221401.4 | S125: =SUM(S108:S123) -> 1 | T125: =SUM(T108:T124) -> 885605.58 | U125: =SUM(U108:U123) -> 737605.58 | V125: =SUM(V108:V123) -> 0 | W125: =SUM(W108:W123) -> 0 | X125: =SUM(X108:X123) -> 0 | Y125: =SUM(Y108:Y123) -> 148000 | Z125: =SUM(Z108:Z123) -> 505187.2 | AA125: =SUM(AA108:AA123) -> 232418.38 | AB125: =SUM(AB107:AB124) -> 63381.582 | AC125: =SUM(AC107:AC124) -> 208800 | AD125: =SUM(AD107:AD124) -> 31636.8 | AE125: =SUM(AE107:AE124) -> 18700 | AF125: =SUM(AF107:AF124) -> 154687.2 | AG125: =SUM(AG107:AG124) -> 119520 | AH125: =SUM(AH107:AH124) -> 140880 | AI125: =SUM(AI107:AI124) -> 0
A126: Total faces simulação | I126: =I113+I112+I111+I110+I109+I108 -> 25 | J126: =I113+I112+I111+I110+I109+I108 -> 25 | K126: =+K114+I113+I112+I110+I109+I108 -> 25 | L126: =K114+I113+I112+I110+I109+I108 -> 25 | M126: =SUM(I126:L126) -> 100 | U126: =U125/T125 -> 0.83288272 | V126: =V125/T125 -> 0 | W126: =W125/T125 -> 0 | X126: =X125/T125 -> 0 | Y126: =Y125/T125 -> 0.16711728 | Z126: =Z125/T125 -> 0.57044266 | AA126: =AA125/T125 -> 0.26244006
A127: Grandes Formatos | I127: 0.25 | Q127: =U125/2 -> 368802.79 | S127: =Q127/Q132 -> 0.83288272 | Z127: =I110+I111+I113+K114 -> 42 | AA127: =I108+I109+I112 -> 3
...

Sheet MANAUS PLAN
A1: taxonomia | B1: regional_boticario | C1: uf | D1: praca | E1: exibidores | F1: formato | G1: ranking | H1: pesos | I1: estatico | J1: digital | K1: range_minimo | L1: range_maximo | M1: quantidade | N1: periodicidade | O1: s1 | P1: s2 | Q1: s3 | R1: s4 | S1: flight | T1: unitario_bruto_tabela | U1: desconto | V1: unitario_bruto_negociado | W1: total_bruto_negociado
A2: data produto | B2: norte | C2: am | D2: manaus | E2: WeOOH | F2: Painel de Led | G2: 2 | H2: =VLOOKUP(G2,Pesos!A:B,2,0) -> 0.8 | J2: x | K2: 2 | L2: 3 | M2: 2 | N2: Mensal | O2: 2 | Q2: 1 | S2: 1 | T2: 5200 | U2: 0.34 | V2: =T2*(1-U2) -> 3432 | W2: =V2*S2*M2 -> 6864
A3: data produto | B3: norte | C3: am | D3: manaus | E3: Brasil Midia Exterior | F3: Painel de Led | G3: 2 | H3: =VLOOKUP(G3,Pesos!A:B,2,0) -> 0.8 | J3: X | K3: 2 | L3: 4 | M3: 2 | N3: Mensal | O3: 2 | S3: 1 | T3: 7800 | U3: 0.34 | V3: =T3*(1-U3) -> 5148 | W3: =V3*S3*M3 -> 10296
A4: data produto | B4: norte | C4: am | D4: manaus | E4: Brasil Midia Exterior | F4: Frontlight | G4: 3 | H4: =VLOOKUP(G4,Pesos!A:B,2,0) -> 0.7 | I4: x | K4: 2 | L4: 4 | M4: 1 | N4: Mensal | O4: 1 | S4: 1 | T4: 3500 | U4: 0.2 | V4: =T4*(1-U4) -> 2800 | W4: =V4*S4*M4 -> 2800
A5: data produto | B5: norte | C5: am | D5: manaus | E5: Brasil Midia Exterior | F5: Outdoor lonado | G5: 1 | H5: =VLOOKUP(G5,Pesos!A:B,2,0) -> 0.9 | I5: X | K5: 10 | L5: 20 | M5: 15 | N5: Mensal | O5: 15 | S5: 1 | T5: 1500 | U5: 0.2 | V5: =T5*(1-U5) -> 1200 | W5: =V5*S5*M5 -> 18000
A6: data produto | B6: norte | C6: am | D6: manaus | E6: The Voice | F6: Painel de Led | G6: 2 | H6: =VLOOKUP(G6,Pesos!A:B,2,0) -> 0.8 | J6: x | K6: 10 | L6: 20 | M6: 15 | N6: Mensal | Q6: 15 | S6: 1 | T6: 1500 | U6: 0.2 | V6: =T6*(1-U6) -> 1200 | W6: =V6*S6*M6 -> 18000
A7: data produto | B7: norte | C7: am | D7: manaus | E7: VSP Midia | F7: Frontlight | G7: 3 | H7: =VLOOKUP(G7,Pesos!A:B,2,0) -> 0.7 | I7: x
A8: data produto | B8: norte | C8: am | D8: manaus | E8: WVK midias | F8: Outdoor lonado | G8: 1 | H8: =VLOOKUP(G8,Pesos!A:B,2,0) -> 0.9 | I8: x | K8: 2 | L8: 3 | M8: 1 | N8: Mensal | O8: 1 | S8: 1 | T8: 5200 | U8: 0.34 | V8: =T8*(1-U8) -> 3432 | W8: =V8*S8*M8 -> 3432
A9: data produto | B9: norte | C9: am | D9: manaus | E9: Puraka | F9: Painel de Led | G9: 2 | H9: =VLOOKUP(G9,Pesos!A:B,2,0) -> 0.8 | J9: x | K9: 2 | L9: 4 | M9: 1 | N9: Mensal | O9: 1 | S9: 1 | T9: 7800 | U9: 0.34 | V9: =T9*(1-U9) -> 5148 | W9: =V9*S9*M9 -> 5148
A10: data produto | B10: norte | C10: am | D10: manaus | E10: Puraka | F10: Frontlight | G10: 3 | H10: =VLOOKUP(G10,Pesos!A:B,2,0) -> 0.7 | I10: x | K10: 5 | L10: 10 | M10: 3 | N10: Mensal | O10: 3 | S10: 1 | T10: 1550 | U10: 0.2 | V10: =T10*(1-U10) -> 1240 | W10: =V10*S10*M10 -> 3720
A11: data produto | B11: norte | C11: am | D11: manaus | E11: Bureau Midia OOH | F11: Painel de Led | G11: 2 | H11: =VLOOKUP(G11,Pesos!A:B,2,0) -> 0.8 | J11: x | K11: 2 | L11: 5 | M11: 4 | N11: Diaria | O11: 4 | Q11: 4 | S11: 2 | T11: 2450 | U11: 0.2 | V11: =T11*(1-U11) -> 1960 | W11: =V11*S11*M11 -> 15680
A12: data produto | B12: norte | C12: am | D12: manaus | E12: Bureau Midia OOH | F12: Frontlight | G12: 3 | H12: =VLOOKUP(G12,Pesos!A:B,2,0) -> 0.7 | I12: x | K12: 2 | L12: 4 | M12: 1 | N12: Mensal | O12: 1 | S12: 1 | T12: 3500 | U12: 0.2 | V12: =T12*(1-U12) -> 2800 | W12: =V12*S12*M12 -> 2800
A14: data promo | B14: norte | C14: am | D14: manaus | E14: WeOOH | F14: Painel de Led | G14: 1 | H14: =VLOOKUP(G14,Pesos!A:B,2,0) -> 0.9 | J14: x | K14: 6 | L14: 12 | M14: 1 | N14: Mensal | O14: 1 | S14: 1 | T14: 35211.99 | U14: 0.55 | V14: =T14*(1-U14) -> 15845.395 | W14: =V14*S14*M14 -> 15845.395
A15: data promo | B15: norte | C15: am | D15: manaus | E15: Brasil Midia Exterior | F15: Painel de Led | G15: 1 | H15: =VLOOKUP(G15,Pesos!A:B,2,0) -> 0.9 | J15: x | K15: 6 | L15: 12 | M15: 1 | N15: Mensal | O15: 1 | S15: 1 | T15: 7000 | U15: 0.1 | V15: =T15*(1-U15) -> 6300 | W15: =V15*S15*M15 -> 6300
A16: data promo | B16: norte | C16: am | D16: manaus | E16: Brasil Midia Exterior | F16: Frontlight | G16: 4 | H16: =VLOOKUP(G16,Pesos!A:B,2,0) -> 0.6 | I16: x | K16: 7 | L16: 14 | M16: 1 | N16: Bisemanal | O16: 1 | S16: 1 | T16: 7500 | U16: 0.1 | V16: =T16*(1-U16) -> 6750 | W16: =V16*S16*M16 -> 6750
A17: data promo | B17: norte | C17: am | D17: manaus | E17: Brasil Midia Exterior | F17: Outdoor lonado | G17: 2 | H17: =VLOOKUP(G17,Pesos!A:B,2,0) -> 0.8 | I17: x | K17: 16 | L17: 25 | M17: 21 | N17: Mensal | O17: 20 | S17: 1 | T17: 2900 | U17: 0.1 | V17: =T17*(1-U17) -> 2610 | W17: =V17*S17*M17 -> 54810
A18: data promo | B18: norte | C18: am | D18: manaus | E18: The Voice | F18: Painel de Led | G18: 1 | H18: =VLOOKUP(G18,Pesos!A:B,2,0) -> 0.9 | J18: x | K18: 6 | L18: 12 | M18: 1 | N18: Mensal | O18: 1 | S18: 1 | T18: 17576 | U18: 0.55 | V18: =T18*(1-U18) -> 7909.2 | W18: =V18*S18*M18 -> 7909.2
A19: data promo | B19: norte | C19: am | D19: manaus | E19: VSP Midia | F19: Frontlight | G19: 4 | H19: =VLOOKUP(G19,Pesos!A:B,2,0) -> 0.6 | I19: x | K19: 7 | L19: 14 | M19: 1 | N19: Mensal | O19: 1 | S19: 1 | T19: 5500 | U19: 0.15 | V19: =T19*(1-U19) -> 4675 | W19: =V19*S19*M19 -> 4675
A20: data promo | B20: norte | C20: am | D20: manaus | E20: WVK midias | F20: Outdoor lonado | G20: 2 | H20: =VLOOKUP(G20,Pesos!A:B,2,0) -> 0.8 | I20: x | K20: 16 | L20: 25 | M20: 21 | N20: Mensal | O20: 20 | S20: 1 | T20: 3222.65 | U20: 0.2 | V20: =T20*(1-U20) -> 2578.12 | W20: =V20*S20*M20 -> 54140.52
A21: data promo | B21: norte | C21: am | D21: manaus | E21: S2X Promoções | F21: Carro de Som | G21: 5 | H21: =VLOOKUP(G21,Pesos!A:B,2,0) -> 0.5 | I21: x | K21: 5 | L21: 10 | M21: 5 | N21: Diaria 8 horas | O21: 5 | S21: 1 | T21: =265*8 -> 2120 | U21: 0.4 | V21: =T21*(1-U21) -> 1272 | W21: =V21*S21*M21 -> 6360
A22: data promo | B22: norte | C22: am | D22: manaus | E22: Puraka | F22: Painel de Led | G22: 1 | H22: =VLOOKUP(G22,Pesos!A:B,2,0) -> 0.9 | J22: x | K22: 6 | L22: 12 | M22: 3 | N22: Mensal | O22: 3 | S22: 1 | T22: 12150 | U22: 0.4 | V22: =T22*(1-U22) -> 7290 | W22: =V22*S22*M22 -> 21870
A23: data promo | B23: norte | C23: am | D23: manaus | E23: Puraka | F23: Frontlight | G23: 4 | H23: =VLOOKUP(G23,Pesos!A:B,2,0) -> 0.6 | I23: x | K23: 7 | L23: 14 | M23: 2 | N23: Mensal | O23: 2 | S23: 1 | T23: 15000 | U23: 0.49 | V23: =T23*(1-U23) -> 7650 | W23: =V23*S23*M23 -> 15300
A24: data promo | B24: norte | C24: am | D24: manaus | E24: Bureau Midia OOH | F24: Painel de Led | G24: 1 | H24: =VLOOKUP(G24,Pesos!A:B,2,0) -> 0.9 | J24: x | K24: 6 | L24: 12 | M24: 2 | N24: Mensal | O24: 2 | S24: 1 | T24: 8980 | U24: 0.25 | V24: =T24*(1-U24) -> 6735 | W24: =V24*S24*M24 -> 13470
A25: data promo | B25: norte | C25: am | D25: manaus | E25: Bureau Midia OOH | F25: Frontlight | G25: 4 | H25: =VLOOKUP(G25,Pesos!A:B,2,0) -> 0.6 | I25: x | K25: 7 | L25: 14 | M25: 2 | N25: Mensal | O25: 2 | S25: 1 | T25: 14500 | U25: 0.25 | V25: =T25*(1-U25) -> 10875 | W25: =V25*S25*M25 -> 21750
A26: data promo | B26: norte | C26: am | D26: manaus | E26: Bureau Midia OOH | F26: BackBus | G26: 3 | H26: =VLOOKUP(G26,Pesos!A:B,2,0) -> 0.7 | I26: x | K26: 6 | L26: 15 | M26: 10 | N26: Mensal | O26: 10 | S26: 1 | T26: 1800 | U26: 0.2 | V26: =T26*(1-U26) -> 1440 | W26: =V26*S26*M26 -> 14400
A28: ouro produto | B28: norte | C28: am | D28: manaus | E28: WeOOH | F28: Painel de Led | G28: 2 | H28: =VLOOKUP(G28,Pesos!A:B,2,0) -> 0.8 | J28: x | K28: 4 | L28: 8 | M28: 1 | N28: Mensal | O28: 1 | S28: 1 | T28: 35211.99 | U28: 0.55 | V28: =T28*(1-U28) -> 15845.395 | W28: =V28*S28*M28 -> 15845.395
A29: ouro produto | B29: norte | C29: am | D29: manaus | E29: Brasil Midia Exterior | F29: Painel de Led | G29: 2 | H29: =VLOOKUP(G29,Pesos!A:B,2,0) -> 0.8 | J29: x | K29: 4 | L29: 8 | M29: 1 | N29: Mensal | O29: 1 | S29: 1 | T29: 7000 | U29: 0.1 | V29: =T29*(1-U29) -> 6300 | W29: =V29*S29*M29 -> 6300
A30: ouro produto | B30: norte | C30: am | D30: manaus | E30: Brasil Midia Exterior | F30: Frontlight | G30: 3 | H30: =VLOOKUP(G30,Pesos!A:B,2,0) -> 0.7 | I30: x | K30: 2 | L30: 6 | M30: 1 | N30: Bisemanal | O30: 1 | S30: 1 | T30: 7500 | U30: 0.1 | V30: =T30*(1-U30) -> 6750 | W30: =V30*S30*M30 -> 6750
A31: ouro produto | B31: norte | C31: am | D31: manaus | E31: Brasil Midia Exterior | F31: Outdoor lonado | G31: 1 | H31: =VLOOKUP(G31,Pesos!A:B,2,0) -> 0.9 | I31: x | K31: 10 | L31: 20 | M31: 20 | N31: Mensal | O31: 20 | S31: 1 | T31: 2900 | U31: 0.1 | V31: =T31*(1-U31) -> 2610 | W31: =V31*S31*M31 -> 52200
A32: ouro produto | B32: norte | C32: am | D32: manaus | E32: The Voice | F32: Painel de Led | G32: 2 | H32: =VLOOKUP(G32,Pesos!A:B,2,0) -> 0.8 | J32: x | K32: 4 | L32: 8 | M32: 1 | N32: Mensal | O32: 1 | S32: 1 | T32: 17576 | U32: 0.55 | V32: =T32*(1-U32) -> 7909.2 | W32: =V32*S32*M32 -> 7909.2
A33: ouro produto | B33: norte | C33: am | D33: manaus | E33: VSP Midia | F33: Frontlight | G33: 3 | H33: =VLOOKUP(G33,Pesos!A:B,2,0) -> 0.7 | I33: x | K33: 2 | L33: 6 | M33: 1 | N33: Mensal | O33: 1 | S33: 1 | T33: 5500 | U33: 0.15 | V33: =T33*(1-U33) -> 4675 | W33: =V33*S33*M33 -> 4675
A34: ouro produto | B34: norte | C34: am | D34: manaus | E34: WVK midias | F34: Outdoor lonado | G34: 1 | H34: =VLOOKUP(G34,Pesos!A:B,2,0) -> 0.9 | I34: x | K34: 10 | L34: 20 | M34: 20 | N34: Mensal | O34: 20 | S34: 1 | T34: 3222.65 | U34: 0.2 | V34: =T34*(1-U34) -> 2578.12 | W34: =V34*S34*M34 -> 51562.4
A35: ouro produto | B35: norte | C35: am | D35: manaus | E35: Puraka | F35: Painel de Led | G35: 2 | H35: =VLOOKUP(G35,Pesos!A:B,2,0) -> 0.8 | J35: x | K35: 4 | L35: 8 | M35: 2 | N35: Mensal | O35: 2 | S35: 1 | T35: 12150 | U35: 0.4 | V35: =T35*(1-U35) -> 7290 | W35: =V35*S35*M35 -> 14580
A36: ouro produto | B36: norte | C36: am | D36: manaus | E36: Puraka | F36: Frontlight | G36: 3 | H36: =VLOOKUP(G36,Pesos!A:B,2,0) -> 0.7 | I36: x | K36: 2 | L36: 6 | M36: 2 | N36: Mensal | O36: 2 | S36: 1 | T36: 15000 | U36: 0.49 | V36: =T36*(1-U36) -> 7650 | W36: =V36*S36*M36 -> 15300
A37: ouro produto | B37: norte | C37: am | D37: manaus | E37: Bureau Midia OOH | F37: Painel de Led | G37: 2 | H37: =VLOOKUP(G37,Pesos!A:B,2,0) -> 0.8 | J37: x | K37: 4 | L37: 8 | M37: 2 | N37: Mensal | O37: 2 | S37: 1 | T37: 8980 | U37: 0.25 | V37: =T37*(1-U37) -> 6735 | W37: =V37*S37*M37 -> 13470
A38: ouro produto | B38: norte | C38: am | D38: manaus | E38: Bureau Midia OOH | F38: Frontlight | G38: 3 | H38: =VLOOKUP(G38,Pesos!A:B,2,0) -> 0.7 | I38: x | K38: 2 | L38: 6 | M38: 2 | N38: Mensal | O38: 2 | S38: 1 | T38: 14500 | U38: 0.25 | V38: =T38*(1-U38) -> 10875 | W38: =V38*S38*M38 -> 21750
A40: ouro promo | B40: norte | C40: am | D40: manaus | E40: WeOOH | F40: Painel de Led | G40: 1 | H40: =VLOOKUP(G40,Pesos!A:B,2,0) -> 0.9 | J40: x | K40: 4 | L40: 8 | M40: 1 | N40: Mensal | O40: 1 | S40: 1 | T40: 35211.99 | U40: 0.55 | V40: =T40*(1-U40) -> 15845.395 | W40: =V40*S40*M40 -> 15845.395
A41: ouro promo | B41: norte | C41: am | D41: manaus | E41: Brasil Midia Exterior | F41: Painel de Led | G41: 1 | H41: =VLOOKUP(G41,Pesos!A:B,2,0) -> 0.9 | J41: x | K41: 4 | L41: 8 | M41: 1 | N41: Mensal | O41: 1 | S41: 1 | T41: 7000 | U41: 0.1 | V41: =T41*(1-U41) -> 6300 | W41: =V41*S41*M41 -> 6300
A42: ouro promo | B42: norte | C42: am | D42: manaus | E42: Brasil Midia Exterior | F42: Frontlight | G42: 4 | H42: =VLOOKUP(G42,Pesos!A:B,2,0) -> 0.6 | I42: x | K42: 2 | L42: 6 | M42: 1 | N42: Bisemanal | O42: 1 | S42: 1 | T42: 7500 | U42: 0.1 | V42: =T42*(1-U42) -> 6750 | W42: =V42*S42*M42 -> 6750
A43: ouro promo | B43: norte | C43: am | D43: manaus | E43: Brasil Midia Exterior | F43: Outdoor lonado | G43: 2 | H43: =VLOOKUP(G43,Pesos!A:B,2,0) -> 0.8 | I43: x | K43: 10 | L43: 20 | M43: 15 | N43: Mensal | O43: 15 | S43: 1 | T43: 2900 | U43: 0.1 | V43: =T43*(1-U43) -> 2610 | W43: =V43*S43*M43 -> 39150
A44: ouro promo | B44: norte | C44: am | D44: manaus | E44: The Voice | F44: Painel de Led | G44: 1 | H44: =VLOOKUP(G44,Pesos!A:B,2,0) -> 0.9 | J44: x | K44: 4 | L44: 8 | M44: 1 | N44: Mensal | O44: 1 | S44: 1 | T44: 17576 | U44: 0.55 | V44: =T44*(1-U44) -> 7909.2 | W44: =V44*S44*M44 -> 7909.2
A45: ouro promo | B45: norte | C45: am | D45: manaus | E45: VSP Midia | F45: Frontlight | G45: 4 | H45: =VLOOKUP(G45,Pesos!A:B,2,0) -> 0.6 | I45: x | K45: 2 | L45: 6 | M45: 1 | N45: Mensal | O45: 1 | S45: 1 | T45: 5500 | U45: 0.15 | V45: =T45*(1-U45) -> 4675 | W45: =V45*S45*M45 -> 4675
A46: ouro promo | B46: norte | C46: am | D46: manaus | E46: WVK midias | F46: Outdoor lonado | G46: 2 | H46: =VLOOKUP(G46,Pesos!A:B,2,0) -> 0.8 | I46: x | K46: 10 | L46: 20 | M46: 15 | N46: Mensal | O46: 15 | S46: 1 | T46: 3222.65 | U46: 0.2 | V46: =T46*(1-U46) -> 2578.12 | W46: =V46*S46*M46 -> 38671.8
A47: ouro promo | B47: norte | C47: am | D47: manaus | E47: S2X Promoções | F47: Carro de Som | G47: 5 | H47: =VLOOKUP(G47,Pesos!A:B,2,0) -> 0.5 | I47: x | K47: 7 | L47: 30 | M47: 3 | N47: Diaria 8 horas | O47: 3 | P47: 3 | Q47: 3 | R47: 3 | S47: 1 | T47: =265*8 -> 2120 | U47: 0.4 | V47: =T47*(1-U47) -> 1272 | W47: =V47*S47*M47 -> 3816
A48: ouro promo | B48: norte | C48: am | D48: manaus | E48: Puraka | F48: Painel de Led | G48: 1 | H48: =VLOOKUP(G48,Pesos!A:B,2,0) -> 0.9 | J48: x | K48: 4 | L48: 8 | M48: 2 | N48: Mensal | O48: 2 | S48: 1 | T48: 12150 | U48: 0.4 | V48: =T48*(1-U48) -> 7290 | W48: =V48*S48*M48 -> 14580
A49: ouro promo | B49: norte | C49: am | D49: manaus | E49: Puraka | F49: Frontlight | G49: 4 | H49: =VLOOKUP(G49,Pesos!A:B,2,0) -> 0.6 | I49: x | K49: 2 | L49: 6 | M49: 2 | N49: Mensal | O49: 2 | S49: 1 | T49: 15000 | U49: 0.49 | V49: =T49*(1-U49) -> 7650 | W49: =V49*S49*M49 -> 15300
A50: ouro promo | B50: norte | C50: am | D50: manaus | E50: Bureau Midia OOH | F50: Painel de Led | G50: 1 | H50: =VLOOKUP(G50,Pesos!A:B,2,0) -> 0.9 | J50: x | K50: 4 | L50: 8 | M50: 1 | N50: Mensal | O50: 1 | S50: 1 | T50: 8980 | U50: 0.25 | V50: =T50*(1-U50) -> 6735 | W50: =V50*S50*M50 -> 6735
A51: ouro promo | B51: norte | C51: am | D51: manaus | E51: Bureau Midia OOH | F51: Frontlight | G51: 4 | H51: =VLOOKUP(G51,Pesos!A:B,2,0) -> 0.6 | I51: x | K51: 2 | L51: 6 | M51: 1 | N51: Mensal | O51: 1 | S51: 1 | T51: 14500 | U51: 0.25 | V51: =T51*(1-U51) -> 10875 | W51: =V51*S51*M51 -> 10875
A52: ouro promo | B52: norte | C52: am | D52: manaus | E52: Bureau Midia OOH | F52: BackBus | G52: 3 | H52: =VLOOKUP(G52,Pesos!A:B,2,0) -> 0.7 | I52: x | K52: 4 | L52: 10 | M52: 10 | N52: Mensal | O52: 10 | S52: 1 | T52: 1800 | U52: 0.2 | V52: =T52*(1-U52) -> 1440 | W52: =V52*S52*M52 -> 14400
A54: prata | B54: norte | C54: am | D54: manaus | E54: Brasil Midia Exterior | F54: Frontlight | G54: 3 | H54: =VLOOKUP(G54,Pesos!A:B,2,0) -> 0.7 | I54: x | K54: 1 | L54: 4 | M54: 1 | N54: Bisemanal | O54: 1 | S54: 1 | T54: 7500 | U54: 0.1 | V54: =T54*(1-U54) -> 6750 | W54: =V54*S54*M54 -> 6750
A55: prata | B55: norte | C55: am | D55: manaus | E55: Brasil Midia Exterior | F55: Outdoor lonado | G55: 2 | H55: =VLOOKUP(G55,Pesos!A:B,2,0) -> 0.8 | I55: x | K55: 6 | L55: 12 | M55: 10 | N55: Mensal | O55: 10 | S55: 1 | T55: 2900 | U55: 0.1 | V55: =T55*(1-U55) -> 2610 | W55: =V55*S55*M55 -> 26100
A56: prata | B56: norte | C56: am | D56: manaus | E56: The Voice | F56: Painel de Led | G56: 1 | H56: =VLOOKUP(G56,Pesos!A:B,2,0) -> 0.9 | J56: x | K56: 2 | L56: 4 | M56: 1 | N56: Mensal | O56: 1 | S56: 1 | T56: 17576 | U56: 0.55 | V56: =T56*(1-U56) -> 7909.2 | W56: =V56*S56*M56 -> 7909.2
A57: prata | B57: norte | C57: am | D57: manaus | E57: VSP Midia | F57: Frontlight | G57: 3 | H57: =VLOOKUP(G57,Pesos!A:B,2,0) -> 0.7 | I57: x | K57: 1 | L57: 3 | M57: 1 | N57: Mensal | O57: 1 | S57: 1 | T57: 5500 | U57: 0.15 | V57: =T57*(1-U57) -> 4675 | W57: =V57*S57*M57 -> 4675
A58: prata | B58: norte | C58: am | D58: manaus | E58: WVK midias | F58: Outdoor lonado | G58: 2 | H58: =VLOOKUP(G58,Pesos!A:B,2,0) -> 0.8 | I58: x | K58: 6 | L58: 12 | M58: 10 | N58: Mensal | O58: 10 | S58: 1 | T58: 3222.65 | U58: 0.2 | V58: =T58*(1-U58) -> 2578.12 | W58: =V58*S58*M58 -> 25781.2
A59: prata | B59: norte | C59: am | D59: manaus | E59: S2X Promoções | F59: Carro de Som | G59: 4 | H59: =VLOOKUP(G59,Pesos!A:B,2,0) -> 0.6 | I59: x | K59: 4 | L59: 15 | M59: 3 | N59: Diaria 8 horas | O59: 3 | Q59: 3 | S59: 2 | T59: =265*8 -> 2120 | U59: 0.4 | V59: =T59*(1-U59) -> 1272 | W59: =V59*S59*M59 -> 7632
A60: prata | B60: norte | C60: am | D60: manaus | E60: Puraka | F60: Painel de Led | G60: 1 | H60: =VLOOKUP(G60,Pesos!A:B,2,0) -> 0.9 | J60: x | K60: 2 | L60: 4 | M60: 1 | N60: Mensal | O60: 1 | S60: 1 | T60: 12150 | U60: 0.4 | V60: =T60*(1-U60) -> 7290 | W60: =V60*S60*M60 -> 7290
A61: prata | B61: norte | C61: am | D61: manaus | E61: Puraka | F61: Frontlight | G61: 3 | H61: =VLOOKUP(G61,Pesos!A:B,2,0) -> 0.7 | I61: x | K61: 1 | L61: 3 | M61: 1 | N61: Mensal | O61: 1 | S61: 1 | T61: 15000 | U61: 0.49 | V61: =T61*(1-U61) -> 7650 | W61: =V61*S61*M61 -> 7650
A62: prata | B62: norte | C62: am | D62: manaus | E62: Bureau Midia OOH | F62: Painel de Led | G62: 1 | H62: =VLOOKUP(G62,Pesos!A:B,2,0) -> 0.9 | J62: x | K62: 2 | L62: 4 | M62: 1 | N62: Mensal | O62: 1 | S62: 1 | T62: 8980 | U62: 0.25 | V62: =T62*(1-U62) -> 6735 | W62: =V62*S62*M62 -> 6735
E68: cpf mínimo | F68: cpf plano | G68: cpf máximo
A69: DATA PRODUTO | E69: =F69*(1-10%) -> 5770.2399 | F69: =MANAUS!T54 -> 6411.3777 | G69: =F69*(1+15%) -> 7373.0843
A70: DATA PROMO | E70: =F70*(1-25%) -> 2576.6082 | F70: =MANAUS!T88 -> 3435.4776 | G70: =F70*(1+5%) -> 3607.2514
A71: OURO PRODUTO | E71: =F71*(1-15%) -> 4182.0264 | F71: =MANAUS!T128 -> 4920.031 | G71: =F71*(1+15%) -> 5658.0357
A72: OURO PROMO | E72: =F72*(1-25%) -> 2642.9452 | F72: =MANAUS!T162 -> 3523.9269 | G72: =F72*(1+5%) -> 3700.1233
A73: PRATA | E73: =F73*(1-25%) -> 2735.3062 | F73: =MANAUS!T198 -> 3647.075 | G73: =F73*(1+5%) -> 3829.4288
E75: ranking semanas - distribuição investimento
A76: DATA PRODUTO | E76: 0.56 | G76: 0.44
A77: DATA PROMO | E77: 0.58 | F77: 0.06 | G77: 0.3 | H77: 0.06
A78: OURO PRODUTO | E78: 0.56 | G78: 0.44
A79: OURO PROMO | E79: 0.59 | G79: 0.41
A80: PRATA | E80: 0.59 | G80: 0.41
E84: ranking semanas - distribuição audiência
A85: DATA PRODUTO | E85: 0.25 | F85: 0.25 | G85: 0.25 | H85: 0.25
A86: DATA PROMO | E86: 0.25 | F86: 0.25 | G86: 0.25 | H86: 0.25
A87: OURO PRODUTO | E87: 0.35 | F87: 0.3 | G87: 0.35
A88: OURO PROMO | E88: 0.35 | F88: 0.3 | G88: 0.35
A89: PRATA | E89: 0.35 | F89: 0.3 | G89: 0.35

Sheet PALMAS
A1: ESTUDO PALMAS
A2: IBGE 2024/ CENSO 2022
A7: INVESTIMENTO PALMAS CAPITAL OOH 2024 | B7: 262287.97
A8: INVESTIMENTO TOCANTINS OOH 2024 | B8: 265487.97
A10: R$ BRUTO PALMAS CAPITAL - 2025 OOH | B10: 1001300
A11: BUDGET BRUTO TOCANTINS - 2025 OOH (100%) | B11: 1001300
A14: Exclusão de Bronze
A15: CICLOS/MEDALHAS | C15: % BUDGET/CICLO | D15: R$ MEDALHA | E15: R$ UNIT. MEDALHAS
A16: Datas | B16: 3 - 2 produto/1 promo | C16: 0.37 | D16: =B10*C16 -> 370481 | E16: =D16/3 -> 123493.67
A17: Ouro | B17: 5 - 4 produto/ 1 promo | C17: 0.49 | D17: =B10*C17 -> 490637 | E17: =D17/5 -> 98127.4
A18: Prata | B18: 2 | C18: 0.14 | D18: =B10*C18 -> 140182 | E18: =D18/2 -> 70091
B19: 10 ciclos | C19: =SUM(C16:C18) -> 1 | D19: =SUM(D16:D18) -> 1001300
A22: População Capital - 302.692 | B22: 302692
A23: População Target - AS ABC 18/49 (logan) | B23: 152438 | E23: Cobertura total - Data Produto | F23: 25% | H23: Cobertura total - Data Promo | J23: 0.26
E24: Frequencia | F24: 26 | H24: Frequencia | J24: 29
E25: TRP | F25: 644 | H25: TRP | J25: 665
E26: OTS | F26: 981.075 | H26: OTS | J26: 1054739
A27: Programação - Ciclo Data Produto
A29: 1 CICLO | T29: TOTAL ANO / CICLO
A30: Praça | B30: Exibidores | C30: Pen/Aff | D30: Canais | E30: Formato | F30: Range de volume ideal | G30: Qtdade | H30: Periodicidade | I30: Mês Base | M30: TT | N30: R$ Unit Bruto | O30: Desconto | P30: R$ Unit Bruto | Q30: R$ TT Bruto | R30: C.P.M. Formato | S30: % | T30: R$ Total | U30: AMBIENTES | Z30: FORMATO
I31: S1 | J31: S2 | K31: S3 | L31: S4 | M31: Flight | N31: Tabela | O31: (%) | P31: Negociado | Q31: Negociado | T31: ano
A32: DATAS MÃES/NATAL | U32: GDES | V32: MUB | W32: TRANSP | X32: AERO | Y32: OPORT | Z32: ESTÁTICO | AA32: DIGITAL | AB32: TOCANTINS | AC32: LED+ | AD32: BUREAU | AE32: ARTES | AF32: SX2 | AG32: KALLAS
A34: Palmas - TO | B34: Tocantis / Apice | C34: 50/156 | D34: Painel de Led | E34: Digital | F34: 5/10 | G34: 2 | H34: Mensal | I34: 2 | M34: 1 | N34: =15*48*30 -> 21600 | O34: 0.25 | P34: =N34*(1-O34) -> 16200 | Q34: =P34*M34*G34 -> 32400 | R34: =(Q34+Q35+Q37+#REF!)/E11*1000 -> #REF! | S34: =Q34/$Q$43 -> 0.37791418 | T34: =Q34*2 -> 64800 | U34: =T34 -> 64800 | AA34: =T34 -> 64800 | AB34: =T34 -> 64800
A35: Palmas - TO | B35: Led+ | C35: 50/156 | D35: Painel de Led | E35: Digital | F35: 5/10 | G35: 3 | H35: Mensal | I35: 3 | M35: 1 | N35: =3750*(1+45%) -> 5437.5 | O35: 0.3 | P35: =N35*(1-O35) -> 3806.25 | Q35: =P35*M35*G35 -> 11418.75 | R35: =(Q35+Q36+#REF!+#REF!)/E12*1000 -> #REF! | S35: =Q35/$Q$43 -> 0.13318851 | T35: =Q35*2 -> 22837.5 | U35: =T35 -> 22837.5 | AA35: =T35 -> 22837.5 | AC35: =T35 -> 22837.5
A36: Palmas - TO | B36: Bureau de Midia | C36: 50/156 | D36: Painel de Led | E36: Digital | F36: 5/10 | G36: 2 | H36: Mensal | I36: 2 | M36: 1 | N36: =(6600+7200)/2 -> 6900 | O36: 0.2 | P36: =N36*(1-O36) -> 5520 | Q36: =P36*M36*G36 -> 11040 | S36: =Q36/$Q$43 -> 0.12877076 | T36: =Q36*2 -> 22080 | U36: =T36 -> 22080 | AA36: =T36 -> 22080 | AD36: =T36 -> 22080
A37: Palmas - TO | B37: Tocantins / Apice | C37: 50/156 | D37: Outdoor lonado | E37: Estático | F37: 10/20 | G37: 15 | H37: Mensal | I37: 15 | M37: 1 | N37: =750*2 -> 1500 | O37: 0.4 | P37: =N37*(1-O37) -> 900 | Q37: =P37*M37*G37 -> 13500 | R37: =(Q37+#REF!)/E12*1000 -> #REF! | S37: =Q37/$Q$43 -> 0.15746424 | T37: =Q37*2 -> 27000 | U37: =T37 -> 27000 | Z37: =T37 -> 27000 | AB37: =T37 -> 27000
A38: Palmas - TO | B38: Artes Coloridas | C38: 50/156 | D38: Outdoor lonado | E38: Estático | F38: 10/20 | G38: 15 | H38: Mensal | K38: 15 | M38: 1 | N38: =750*2 -> 1500 | O38: 0.45 | P38: =N38*(1-O38) -> 825 | Q38: =P38*M38*G38 -> 12375 | R38: =(Q38+#REF!)/E14*1000 -> #REF! | S38: =Q38/$Q$43 -> 0.14434222 | T38: =Q38*2 -> 24750 | U38: =T38 -> 24750 | Z38: =T38 -> 24750 | AE38: =T38 -> 24750
A40: Palmas - TO | B40: Aeroporto | T40: =Q40*2 -> 0 | X40: =T40 -> 0
A41: Palmas - TO | B41: Oportunidades | D41: Marítimos / Ativação | Q41: 5000 | S41: =Q41/Q43 -> 0.05832009 | T41: =Q41*2 -> 10000 | Y41: =T41 -> 10000
I42: =I43/M43 -> 0.59459459 | K42: =K43/M43 -> 0.40540541
A43: Total faces compra | I43: =I37+I36+I35+I34 -> 22 | K43: =K38 -> 15 | M43: =SUM(I43:L43) -> 37 | Q43: =SUM(Q34:Q42) -> 85733.75 | S43: =SUM(S34:S41) -> 1 | T43: =SUM(T34:T42) -> 171467.5 | U43: =SUM(U34:U41) -> 161467.5 | V43: =SUM(V34:V41) -> 0 | W43: =SUM(W34:W41) -> 0 | X43: =SUM(X34:X41) -> 0 | Y43: =SUM(Y34:Y41) -> 10000 | Z43: =SUM(Z34:Z41) -> 51750 | AA43: =SUM(AA34:AA41) -> 109717.5 | AB43: =SUM(AB33:AB42) -> 91800 | AC43: =SUM(AC33:AC42) -> 22837.5 | AD43: =SUM(AD33:AD42) -> 22080 | AE43: =SUM(AE33:AE42) -> 24750
A44: Total faces simulação | I44: =I37+I36+I35+I34 -> 22 | J44: =I37+I36+I35+I34 -> 22 | K44: =K38+I36+I35+I34 -> 22 | L44: =K38+I36+I35+I34 -> 22 | M44: =SUM(I44:L44) -> 88 | U44: =U43/T43 -> 0.94167991 | V44: =V43/T43 -> 0 | W44: =W43/T43 -> 0 | X44: =X43/T43 -> 0 | Y44: =Y43/T43 -> 0.05832009 | Z44: =Z43/T43 -> 0.30180646 | AA44: =AA43/T43 -> 0.63987345
A45: Grandes Formatos | I45: 0.25 | Q45: =U43/2 -> 80733.75 | S45: =Q45/Q50 -> 0.94167991 | Z45: =I37+K38 -> 30 | AA45: =I34+I35+I36 -> 7
A46: MUB | Q46: =V43/2 -> 0 | S46: =Q46/Q50 -> 0 | T46: =Q43/M43 -> 2317.1284 | U46: CPFACE | Z46: =Z45/M43 -> 0.81081081 | AA46: =AA45/M43 -> 0.18918919
A47: Transportes | Q47: =W43/2 -> 0 | S47: =Q47/Q50 -> 0 | Z47: SHARE FACES
A48: Oportunidades | Q48: =Y43/2 -> 5000 | S48: =Q48/Q50 -> 0.05832009
A49: Aeroporto | Q49: =X43/2 -> 0 | S49: =Q49/Q50 -> 0
Q50: =SUM(Q45:Q49) -> 85733.75 | S50: =SUM(S45:S49) -> 1
A52: Programação - Ciclo Data Promo
A54: 1 CICLO | T54: TOTAL ANO / CICLO
A55: Praça | B55: Exibidores | C55: Pen/Aff | D55: Canais | E55: Formato | F55: Range de volume ideal | G55: Qtdade | H55: Periodicidade | I55: Mês Base | M55: TT | N55: R$ Unit Bruto | O55: Desconto | P55: R$ Unit Bruto | Q55: R$ TT Bruto | R55: C.P.M. Formato | S55: % | T55: R$ Total | U55: AMBIENTES | Z55: FORMATO
I56: S1 | J56: S2 | K56: S3 | L56: S4 | M56: Flight | N56: Tabela | O56: (%) | P56: Negociado | Q56: Negociado | T56: ano
A57: DATAS BW | U57: GDES | V57: MUB | W57: TRANSP | X57: AERO | Y57: OPORT | Z57: ESTÁTICO | AA57: DIGITAL | AB57: TOCANTINS | AC57: LED+ | AD57: BUREAU | AE57: ARTES | AF57: SX2 | AG57: KALLAS
A59: Palmas - TO | B59: Tocantis / Apice | C59: 50/156 | D59: Painel de Led | E59: Digital | F59: 5/10 | G59: 1 | H59: Mensal | I59: 1 | M59: 1 | N59: =15*48*30 -> 21600 | O59: 0.25 | P59: =N59*(1-O59) -> 16200 | Q59: =P59*M59*G59 -> 16200 | R59: =(Q59+Q60+Q62+#REF!)/E35*1000 -> #REF! | S59: =Q59/$Q$71 -> 0.20183521 | T59: =Q59 -> 16200 | U59: =T59 -> 16200 | AA59: =T59 -> 16200 | AB59: =T59 -> 16200
A60: Palmas - TO | B60: Led+ | C60: 50/156 | D60: Painel de Led | E60: Digital | F60: 5/10 | G60: 2 | H60: Mensal | I60: 2 | M60: 1 | N60: =3750*(1+45%) -> 5437.5 | O60: 0.3 | P60: =N60*(1-O60) -> 3806.25 | Q60: =P60*M60*G60 -> 7612.5 | R60: =(Q60+Q61+#REF!+#REF!)/E36*1000 -> #REF! | S60: =Q60/$Q$71 -> 0.094843858 | T60: =Q60 -> 7612.5 | U60: =T60 -> 7612.5 | AA60: =T60 -> 7612.5 | AC60: =T60 -> 7612.5
A61: Palmas - TO | B61: Bureau de Midia | C61: 50/156 | D61: Painel de Led | E61: Digital | F61: 5/10 | G61: 2 | H61: Mensal | I61: 2 | M61: 1 | N61: =(6600+7200)/2 -> 6900 | O61: 0.2 | P61: =N61*(1-O61) -> 5520 | Q61: =P61*M61*G61 -> 11040 | S61: =Q61/$Q$71 -> 0.13754695 | T61: =Q61 -> 11040 | U61: =T61 -> 11040 | AA61: =T61 -> 11040 | AD61: =T61 -> 11040
A62: Palmas - TO | B62: Tocantins / Apice | C62: 50/156 | D62: Outdoor lonado | E62: Estático | F62: 10/20 | G62: 15 | H62: Mensal | I62: 15 | M62: 1 | N62: =750*2 -> 1500 | O62: 0.4 | P62: =N62*(1-O62) -> 900 | Q62: =P62*M62*G62 -> 13500 | R62: =(Q62+#REF!)/E36*1000 -> #REF! | S62: =Q62/$Q$71 -> 0.168196 | T62: =Q62 -> 13500 | U62: =T62 -> 13500 | Z62: =T62 -> 13500 | AB62: =T62 -> 13500
A63: Palmas - TO | B63: Artes Coloridas | C63: 50/156 | D63: Outdoor lonado | E63: Estático | F63: 10/20 | G63: 15 | H63: Mensal | K63: 15 | M63: 1 | N63: =750*2 -> 1500 | O63: 0.45 | P63: =N63*(1-O63) -> 825 | Q63: =P63*M63*G63 -> 12375 | R63: =(Q63+#REF!)/E38*1000 -> #REF! | S63: =Q63/$Q$71 -> 0.15417967 | T63: =Q63 -> 12375 | U63: =T63 -> 12375 | Z63: =T63 -> 12375 | AE63: =T63 -> 12375
A64: Palmas - TO | B64: S2xPromoçoes | D64: Carro de Som | E64: Audio | G64: 4 | H64: Diaria | I64: 4 | K64: 4 | M64: 2 | N64: =265*8 -> 2120 | O64: 0.4 | P64: =N64*(1-O64) -> 1272 | Q64: =P64*G64*M64 -> 10176 | S64: =Q64/$Q$71 -> 0.12678241 | T64: =Q64 -> 10176 | U64: =T64 -> 10176 | AF64: =T64 -> 10176
A65: Palmas - TO | B65: Cartaxi | C65: 63/153 | D65: Vidro traseiro _ interno | E65: Estático | F65: 6/12 | G65: 7 | H65: Mensal | I65: 7 | M65: 1 | N65: 1600 | O65: 0.7 | P65: =N65*(1-O65) -> 480 | Q65: =P65*G65*M65 -> 3360 | S65: =Q65/$Q$71 -> 0.041862117 | T65: =Q65 -> 3360 | W65: =T65 -> 3360 | Z65: =T65 -> 3360 | AG65: =T65 -> 3360
A68: Palmas - TO | B68: Aeroporto | T68: =Q68 -> 0 | X68: =T68 -> 0
A69: Palmas - TO | B69: Oportunidades | D69: Marítimos / Ativação | Q69: 6000 | S69: =Q69/Q71 -> 0.07475378 | T69: =Q69 -> 6000 | Y69: =T69 -> 6000
I70: =I71/M71 -> 0.62 | K70: =K71/M71 -> 0.38
A71: Total faces compra | I71: =I65+I64+I62+I61+I60+I59 -> 31 | K71: =K64+K63 -> 19 | M71: =SUM(I71:L71) -> 50 | Q71: =SUM(Q59:Q70) -> 80263.5 | S71: =SUM(S59:S69) -> 1 | T71: =SUM(T59:T70) -> 80263.5 | U71: =SUM(U59:U69) -> 70903.5 | V71: =SUM(V59:V69) -> 0 | W71: =SUM(W59:W69) -> 3360 | X71: =SUM(X59:X69) -> 0 | Y71: =SUM(Y59:Y69) -> 6000 | Z71: =SUM(Z59:Z69) -> 29235 | AA71: =SUM(AA59:AA69) -> 34852.5 | AB71: =SUM(AB58:AB70) -> 29700 | AC71: =SUM(AC58:AC70) -> 7612.5 | AD71: =SUM(AD58:AD70) -> 11040 | AE71: =SUM(AE58:AE70) -> 12375 | AF71: =SUM(AF58:AF70) -> 10176 | AG71: =SUM(AG58:AG70) -> 3360
A72: Total faces simulação | I72: =I65+I64+I62+I61+I60+I59 -> 31 | J72: =I65+I62+I61+I60+I59 -> 27 | K72: =I65+K64+K63+I61+I60+I59 -> 31 | L72: =I65+K63+I61+I60+I59 -> 27 | M72: =SUM(I72:L72) -> 116 | U72: =U71/T71 -> 0.8833841 | V72: =V71/T71 -> 0 | W72: =W71/T71 -> 0.041862117 | X72: =X71/T71 -> 0 | Y72: =Y71/T71 -> 0.07475378 | Z72: =Z71/T71 -> 0.36423779 | AA72: =AA71/T71 -> 0.43422602
A73: Grandes Formatos | I73: =I72/M72 -> 0.26724138 | J73: =J72/M72 -> 0.23275862 | Q73: =U71 -> 70903.5 | S73: =Q73/Q78 -> 0.8833841 | Z73: =I62+K63+I65 -> 37 | AA73: =I59+I60+I61 -> 5
A74: MUB | Q74: =V71 -> 0 | S74: =Q74/Q78 -> 0 | T74: =Q71/M71 -> 1605.27 | U74: CPFACE | Z74: =Z73/M71 -> 0.74 | AA74: =AA73/M71 -> 0.1
A75: Transportes | Q75: =W71 -> 3360 | S75: =Q75/Q78 -> 0.041862117 | Z75: SHARE FACES
A76: Oportunidades | Q76: =Y71 -> 6000 | S76: =Q76/Q78 -> 0.07475378
A77: Aeroporto | Q77: =X71 -> 0 | S77: =Q77/Q78 -> 0
Q78: =SUM(Q73:Q77) -> 80263.5 | S78: =SUM(S73:S77) -> 1
E82: Cobertura total - Ouro Produto | F82: 24% | G82: Cobertura total - Ouro Promo | I82: 0.25
E83: Frequencia | F83: 24 | G83: Frequencia | I83: 24
E84: TRP | F84: 562 | G84: TRP | I84: 636
E85: OTS | F85: 857.447 | G85: OTS | I85: 969324
A87: Programação - Ciclo Ouro Produto
A89: 1 CICLO | T89: TOTAL ANO / CICLO
A90: Praça | B90: Exibidores | C90: Pen/Aff | D90: Canais | E90: Formato | F90: Range de volume ideal | G90: Qtdade | H90: Periodicidade | I90: Mês Base | M90: TT | N90: R$ Unit Bruto | O90: Desconto | P90: R$ Unit Bruto | Q90: R$ TT Bruto | R90: C.P.M. Formato | S90: % | T90: R$ Total | U90: AMBIENTES | Z90: FORMATO
I91: S1 | J91: S2 | K91: S3 | L91: S4 | M91: Flight | N91: Tabela | O91: (%) | P91: Negociado | Q91: Negociado | T91: ano
A92: OURO PRODUTO | U92: GDES | V92: MUB | W92: TRANSP | X92: AERO | Y92: OPORT | Z92: ESTÁTICO | AA92: DIGITAL | AB92: TOCANTINS | AC92: LED+ | AD92: BUREAU | AE92: ARTES | AF92: SX2 | AG92: KALLAS
A94: Palmas - TO | B94: Tocantis / Apice | C94: 50/156 | D94: Painel de Led | E94: Digital | F94: 3/7 | G94: 1 | H94: Mensal | I94: 1 | M94: 1 | N94: =15*48*30 -> 21600 | O94: 0.25 | P94: =N94*(1-O94) -> 16200 | Q94: =P94*M94*G94 -> 16200 | R94: =(Q94+Q95+Q97+#REF!)/E73*1000 -> #REF! | S94: =Q94/$Q$103 -> 0.29591068 | T94: =Q94*4 -> 64800 | U94: =T94 -> 64800 | AA94: =T94 -> 64800 | AB94: =T94 -> 64800
A95: Palmas - TO | B95: Led+ | C95: 50/156 | D95: Painel de Led | E95: Digital | F95: 3/7 | G95: 1 | H95: Mensal | I95: 1 | M95: 1 | N95: =3750*(1+45%) -> 5437.5 | O95: 0.3 | P95: =N95*(1-O95) -> 3806.25 | Q95: =P95*M95*G95 -> 3806.25 | R95: =(Q95+Q96+#REF!+#REF!)/E74*1000 -> #REF! | S95: =Q95/$Q$103 -> 0.06952531 | T95: =Q95*4 -> 15225 | U95: =T95 -> 15225 | AA95: =T95 -> 15225 | AC95: =T95 -> 15225
A96: Palmas - TO | B96: Bureau de Midia | C96: 50/156 | D96: Painel de Led | E96: Digital | F96: 3/7 | G96: 2 | H96: Mensal | I96: 2 | M96: 1 | N96: =(6600+7200)/2 -> 6900 | O96: 0.2 | P96: =N96*(1-O96) -> 5520 | Q96: =P96*M96*G96 -> 11040 | S96: =Q96/$Q$103 -> 0.20165765 | T96: =Q96*4 -> 44160 | U96: =T96 -> 44160 | AA96: =T96 -> 44160 | AD96: =T96 -> 44160
A97: Palmas - TO | B97: Tocantins / Apice | C97: 50/156 | D97: Outdoor lonado | E97: Estático | F97: 8/15 | G97: 12 | H97: Mensal | I97: 12 | M97: 1 | N97: =750*2 -> 1500 | O97: 0.4 | P97: =N97*(1-O97) -> 900 | Q97: =P97*M97*G97 -> 10800 | R97: =(Q97+#REF!)/E74*1000 -> #REF! | S97: =Q97/$Q$103 -> 0.19727379 | T97: =Q97*4 -> 43200 | U97: =T97 -> 43200 | Z97: =T97 -> 43200 | AB97: =T97 -> 43200
A98: Palmas - TO | B98: Artes Coloridas | C98: 50/156 | D98: Outdoor lonado | E98: Estático | F98: 8/15 | G98: 12 | H98: Mensal | K98: 12 | M98: 1 | N98: =750*2 -> 1500 | O98: 0.45 | P98: =N98*(1-O98) -> 825 | Q98: =P98*M98*G98 -> 9900 | R98: =(Q98+#REF!)/E76*1000 -> #REF! | S98: =Q98/$Q$103 -> 0.1808343 | T98: =Q98*4 -> 39600 | U98: =T98 -> 39600 | Z98: =T98 -> 39600 | AE98: =T98 -> 39600
A100: Palmas - TO | B100: Aeroporto | X100: =T100 -> 0
A101: Palmas - TO | B101: Oportunidades | D101: Marítimos / Ativação | Q101: 3000 | S101: =Q101/Q103 -> 0.054798274 | T101: =Q101*4 -> 12000 | Y101: =T101 -> 12000
I102: =I103/M103 -> 0.57142857 | K102: =K103/M103 -> 0.42857143
A103: Total faces compra | I103: =I97+I96+I95+I94 -> 16 | K103: =K98 -> 12 | M103: =SUM(I103:L103) -> 28 | Q103: =SUM(Q94:Q102) -> 54746.25 | S103: =SUM(S94:S101) -> 1 | T103: =SUM(T94:T102) -> 218985 | U103: =SUM(U94:U101) -> 206985 | V103: =SUM(V94:V101) -> 0 | W103: =SUM(W94:W101) -> 0 | X103: =SUM(X94:X101) -> 0 | Y103: =SUM(Y94:Y101) -> 12000 | Z103: =SUM(Z94:Z101) -> 82800 | AA103: =SUM(AA94:AA101) -> 124185 | AB103: =SUM(AB93:AB102) -> 108000 | AC103: =SUM(AC93:AC102) -> 15225 | AD103: =SUM(AD93:AD102) -> 44160 | AE103: =SUM(AE93:AE102) -> 39600
A104: Total faces simulação | I104: =I97+I96+I95+I94 -> 16 | J104: =I97+I96+I95+I94 -> 16 | K104: =K98+I96+I95+I94 -> 16 | L104: =K98+I96+I95+I94 -> 16 | M104: =SUM(I104:L104) -> 64 | U104: =U103/T103 -> 0.94520173 | V104: =V103/T103 -> 0 | W104: =W103/T103 -> 0 | X104: =X103/T103 -> 0 | Y104: =Y103/T103 -> 0.054798274 | Z104: =Z103/T103 -> 0.37810809 | AA104: =AA103/T103 -> 0.56709364
A105: Grandes Formatos | I105: 0.25 | Q105: =U103/4 -> 51746.25 | S105: =Q105/Q110 -> 0.94520173 | Z105: =I97+K98 -> 24 | AA105: =I94+I95+I96 -> 4
A106: MUB | Q106: =V103/4 -> 0 | S106: =Q106/Q110 -> 0 | T106: =Q103/M103 -> 1955.2232 | U106: CPFACE | Z106: =Z105/M103 -> 0.85714286 | AA106: =AA105/M103 -> 0.14285714
A107: Transportes | Q107: =W103/4 -> 0 | S107: =Q107/Q110 -> 0 | Z107: SHARE FACES
A108: Oportunidades | Q108: =Y103/4 -> 3000 | S108: =Q108/Q110 -> 0.054798274
A109: Aeroporto | Q109: =X103/4 -> 0 | S109: =Q109/Q110 -> 0
Q110: =SUM(Q105:Q109) -> 54746.25 | S110: =SUM(S105:S109) -> 1
A112: Programação - Ciclo Ouro Promo
A114: 1 CICLO | T114: TOTAL ANO / CICLO
A115: Praça | B115: Exibidores | C115: Pen/Aff | D115: Canais | E115: Formato | F115: Range de volume ideal | G115: Qtdade | H115: Periodicidade | I115: Mês Base | M115: TT | N115: R$ Unit Bruto | O115: Desconto | P115: R$ Unit Bruto | Q115: R$ TT Bruto | R115: C.P.M. Formato | S115: % | T115: R$ Total | U115: AMBIENTES | Z115: FORMATO
I116: S1 | J116: S2 | K116: S3 | L116: S4 | M116: Flight | N116: Tabela | O116: (%) | P116: Negociado | Q116: Negociado | T116: ano
A117: OURO PRODUTO | U117: GDES | V117: MUB | W117: TRANSP | X117: AERO | Y117: OPORT | Z117: ESTÁTICO | AA117: DIGITAL | AB117: TOCANTINS | AC117: LED+ | AD117: BUREAU | AE117: ARTES | AF117: SX2 | AG117: KALLAS
A119: Palmas - TO | B119: Tocantis / Apice | C119: 50/156 | D119: Painel de Led | E119: Digital | F119: 3/7 | G119: 1 | H119: Mensal | I119: 1 | M119: 1 | N119: =15*48*30 -> 21600 | O119: 0.25 | P119: =N119*(1-O119) -> 16200 | Q119: =P119*M119*G119 -> 16200 | R119: =(Q119+Q120+Q122+#REF!)/E99*1000 -> #REF! | S119: =Q119/$Q$131 -> 0.2856425 | T119: =Q119 -> 16200 | U119: =T119 -> 16200 | AA119: =T119 -> 16200 | AB119: =T119 -> 16200
A120: Palmas - TO | B120: Led+ | C120: 50/156 | D120: Painel de Led | E120: Digital | F120: 3/7 | G120: 1 | H120: Mensal | I120: 1 | M120: 1 | N120: =3750*(1+45%) -> 5437.5 | O120: 0.3 | P120: =N120*(1-O120) -> 3806.25 | Q120: =P120*M120*G120 -> 3806.25 | R120: =(Q120+Q121+#REF!+#REF!)/E100*1000 -> #REF! | S120: =Q120/$Q$131 -> 0.067112763 | T120: =Q120 -> 3806.25 | U120: =T120 -> 3806.25 | AA120: =T120 -> 3806.25 | AC120: =T120 -> 3806.25
A121: Palmas - TO | B121: Bureau de Midia | C121: 50/156 | D121: Painel de Led | E121: Digital | F121: 3/7 | G121: 1 | H121: Mensal | I121: 1 | M121: 1 | N121: =(6600+7200)/2 -> 6900 | O121: 0.2 | P121: =N121*(1-O121) -> 5520 | Q121: =P121*M121*G121 -> 5520 | S121: =Q121/$Q$131 -> 0.097330036 | T121: =Q121 -> 5520 | U121: =T121 -> 5520 | AA121: =T121 -> 5520 | AD121: =T121 -> 5520
A122: Palmas - TO | B122: Tocantins / Apice | C122: 50/156 | D122: Outdoor lonado | E122: Estático | F122: 8/15 | G122: 12 | H122: Mensal | I122: 12 | M122: 1 | N122: =750*2 -> 1500 | O122: 0.4 | P122: =N122*(1-O122) -> 900 | Q122: =P122*M122*G122 -> 10800 | R122: =(Q122+#REF!)/E100*1000 -> #REF! | S122: =Q122/$Q$131 -> 0.19042833 | T122: =Q122 -> 10800 | U122: =T122 -> 10800 | Z122: =T122 -> 10800 | AB122: =T122 -> 10800
A123: Palmas - TO | B123: Artes Coloridas | C123: 50/156 | D123: Outdoor lonado | E123: Estático | F123: 8/15 | G123: 12 | H123: Mensal | K123: 12 | M123: 1 | N123: =750*2 -> 1500 | O123: 0.45 | P123: =N123*(1-O123) -> 825 | Q123: =P123*M123*G123 -> 9900 | R123: =(Q123+#REF!)/E102*1000 -> #REF! | S123: =Q123/$Q$131 -> 0.1745593 | T123: =Q123 -> 9900 | U123: =T123 -> 9900 | Z123: =T123 -> 9900 | AE123: =T123 -> 9900
A124: Palmas - TO | B124: S2xPromoçoes | D124: Carro de Som | E124: Audio | G124: 2 | H124: Diaria | I124: 2 | K124: 2 | M124: 2 | N124: =265*8 -> 2120 | O124: 0.4 | P124: =N124*(1-O124) -> 1272 | Q124: =P124*G124*M124 -> 5088 | S124: =Q124/$Q$131 -> 0.089712903 | T124: =Q124 -> 5088 | U124: =T124 -> 5088 | AF124: =T124 -> 5088
A125: Palmas - TO | B125: Cartaxi | C125: 30/155 | D125: Vidro traseiro _ interno | E125: Estático | F125: 5/10 | G125: 5 | H125: Mensal | I125: 5 | M125: 1 | N125: 1600 | O125: 0.7 | P125: =N125*(1-O125) -> 480 | Q125: =P125*G125*M125 -> 2400 | S125: =Q125/$Q$131 -> 0.042317407 | T125: =Q125 -> 2400 | W125: =T125 -> 2400 | Z125: =T125 -> 2400 | AG125: =T125 -> 2400
A128: Palmas - TO | B128: Aeroporto | T128: =Q128 -> 0 | X128: =T128 -> 0
A129: Palmas - TO | B129: Oportunidades | D129: Marítimos / Ativação | Q129: 3000 | S129: =Q129/Q131 -> 0.052896759 | T129: =Q129 -> 3000 | Y129: =T129 -> 3000
...

Sheet PALMAS PLAN
A1: taxonomia | B1: regional_boticario | C1: uf | D1: praca | E1: exibidores | F1: formato | G1: ranking | H1: pesos | I1: estatico | J1: digital | K1: range_minimo | L1: range_maximo | M1: quantidade | N1: periodicidade | O1: s1 | P1: s2 | Q1: s3 | R1: s4 | S1: flight | T1: unitario_bruto_tabela | U1: desconto | V1: unitario_bruto_negociado | W1: total_bruto_negociado
A2: data produto | B2: norte | C2: to | D2: palmas | E2: Tocantis / Apice | F2: Painel de Led | G2: 2 | H2: =VLOOKUP(G2,Pesos!A:B,2,0) -> 0.8 | J2: x | K2: 5 | L2: 10 | M2: 2 | N2: Mensal | O2: 2 | Q2: 1 | S2: 1 | T2: =15*48*30 -> 21600 | U2: 0.25 | V2: =T2*(1-U2) -> 16200 | W2: =V2*S2*M2 -> 32400
A3: data produto | B3: norte | C3: to | D3: palmas | E3: Led+ | F3: Painel de Led | G3: 2 | H3: =VLOOKUP(G3,Pesos!A:B,2,0) -> 0.8 | J3: x | K3: 5 | L3: 10 | M3: 3 | N3: Mensal | O3: 3 | S3: 1 | T3: =3750*(1+45%) -> 5437.5 | U3: 0.3 | V3: =T3*(1-U3) -> 3806.25 | W3: =V3*S3*M3 -> 11418.75
A4: data produto | B4: norte | C4: to | D4: palmas | E4: Bureau de Midia | F4: Painel de Led | G4: 2 | H4: =VLOOKUP(G4,Pesos!A:B,2,0) -> 0.8 | J4: x | K4: 5 | L4: 10 | M4: 2 | N4: Mensal | O4: 2 | S4: 1 | T4: =(6600+7200)/2 -> 6900 | U4: 0.2 | V4: =T4*(1-U4) -> 5520 | W4: =V4*S4*M4 -> 11040
A5: data produto | B5: norte | C5: to | D5: palmas | E5: Tocantins / Apice | F5: Outdoor lonado | G5: 1 | H5: =VLOOKUP(G5,Pesos!A:B,2,0) -> 0.9 | I5: x | K5: 10 | L5: 20 | M5: 15 | N5: Mensal | O5: 15 | S5: 1 | T5: =750*2 -> 1500 | U5: 0.4 | V5: =T5*(1-U5) -> 900 | W5: =V5*S5*M5 -> 13500
A6: data produto | B6: norte | C6: to | D6: palmas | E6: Artes Coloridas | F6: Outdoor lonado | G6: 1 | H6: =VLOOKUP(G6,Pesos!A:B,2,0) -> 0.9 | I6: x | K6: 10 | L6: 20 | M6: 15 | N6: Mensal | Q6: 15 | S6: 1 | T6: =750*2 -> 1500 | U6: 0.45 | V6: =T6*(1-U6) -> 825 | W6: =V6*S6*M6 -> 12375
A8: data promo | B8: norte | C8: to | D8: palmas | E8: Tocantis / Apice | F8: Painel de Led | G8: 1 | H8: =VLOOKUP(G8,Pesos!A:B,2,0) -> 0.9 | J8: x | K8: 5 | L8: 10 | M8: 1 | N8: Mensal | O8: 1 | S8: 1 | T8: =15*48*30 -> 21600 | U8: 0.25 | V8: =T8*(1-U8) -> 16200 | W8: =V8*S8*M8 -> 16200
A9: data promo | B9: norte | C9: to | D9: palmas | E9: Led+ | F9: Painel de Led | G9: 1 | H9: =VLOOKUP(G9,Pesos!A:B,2,0) -> 0.9 | J9: x | K9: 5 | L9: 10 | M9: 2 | N9: Mensal | O9: 2 | S9: 1 | T9: =3750*(1+45%) -> 5437.5 | U9: 0.3 | V9: =T9*(1-U9) -> 3806.25 | W9: =V9*S9*M9 -> 7612.5
A10: data promo | B10: norte | C10: to | D10: palmas | E10: Bureau de Midia | F10: Painel de Led | G10: 1 | H10: =VLOOKUP(G10,Pesos!A:B,2,0) -> 0.9 | J10: x | K10: 5 | L10: 10 | M10: 2 | N10: Mensal | O10: 2 | S10: 1 | T10: =(6600+7200)/2 -> 6900 | U10: 0.2 | V10: =T10*(1-U10) -> 5520 | W10: =V10*S10*M10 -> 11040
A11: data promo | B11: norte | C11: to | D11: palmas | E11: Tocantins / Apice | F11: Outdoor lonado | G11: 2 | H11: =VLOOKUP(G11,Pesos!A:B,2,0) -> 0.8 | I11: x | K11: 10 | L11: 20 | M11: 15 | N11: Mensal | O11: 15 | S11: 1 | T11: =750*2 -> 1500 | U11: 0.4 | V11: =T11*(1-U11) -> 900 | W11: =V11*S11*M11 -> 13500
A12: data promo | B12: norte | C12: to | D12: palmas | E12: Artes Coloridas | F12: Outdoor lonado | G12: 2 | H12: =VLOOKUP(G12,Pesos!A:B,2,0) -> 0.8 | I12: x | K12: 10 | L12: 20 | M12: 15 | N12: Mensal | Q12: 15 | S12: 1 | T12: =750*2 -> 1500 | U12: 0.45 | V12: =T12*(1-U12) -> 825 | W12: =V12*S12*M12 -> 12375
A13: data promo | B13: norte | C13: to | D13: palmas | E13: S2xPromoçoes | F13: Carro de Som | G13: 3 | H13: =VLOOKUP(G13,Pesos!A:B,2,0) -> 0.7 | I13: x | K13: 4 | L13: 10 | M13: 4 | N13: Diaria | O13: 4 | Q13: 4 | S13: 2 | T13: =265*8 -> 2120 | U13: 0.4 | V13: =T13*(1-U13) -> 1272 | W13: =V13*S13*M13 -> 10176
A14: data promo | B14: norte | C14: to | D14: palmas | E14: Cartaxi | F14: Vidro traseiro _ interno | G14: 4 | H14: =VLOOKUP(G14,Pesos!A:B,2,0) -> 0.6 | I14: x | K14: 6 | L14: 12 | M14: 7 | N14: Mensal | O14: 7 | S14: 1 | T14: 1600 | U14: 0.7 | V14: =T14*(1-U14) -> 480 | W14: =V14*S14*M14 -> 3360
A16: ouro produto | B16: norte | C16: to | D16: palmas | E16: Tocantis / Apice | F16: Painel de Led | G16: 2 | H16: =VLOOKUP(G16,Pesos!A:B,2,0) -> 0.8 | J16: x | K16: 3 | L16: 7 | M16: 1 | N16: Mensal | O16: 1 | S16: 1 | T16: =15*48*30 -> 21600 | U16: 0.25 | V16: =T16*(1-U16) -> 16200 | W16: =V16*S16*M16 -> 16200
A17: ouro produto | B17: norte | C17: to | D17: palmas | E17: Led+ | F17: Painel de Led | G17: 2 | H17: =VLOOKUP(G17,Pesos!A:B,2,0) -> 0.8 | J17: x | K17: 3 | L17: 7 | M17: 1 | N17: Mensal | O17: 1 | S17: 1 | T17: =3750*(1+45%) -> 5437.5 | U17: 0.3 | V17: =T17*(1-U17) -> 3806.25 | W17: =V17*S17*M17 -> 3806.25
A18: ouro produto | B18: norte | C18: to | D18: palmas | E18: Bureau de Midia | F18: Painel de Led | G18: 2 | H18: =VLOOKUP(G18,Pesos!A:B,2,0) -> 0.8 | J18: x | K18: 3 | L18: 7 | M18: 2 | N18: Mensal | O18: 2 | S18: 1 | T18: =(6600+7200)/2 -> 6900 | U18: 0.2 | V18: =T18*(1-U18) -> 5520 | W18: =V18*S18*M18 -> 11040
A19: ouro produto | B19: norte | C19: to | D19: palmas | E19: Tocantins / Apice | F19: Outdoor lonado | G19: 1 | H19: =VLOOKUP(G19,Pesos!A:B,2,0) -> 0.9 | I19: x | K19: 8 | L19: 15 | M19: 12 | N19: Mensal | O19: 12 | S19: 1 | T19: =750*2 -> 1500 | U19: 0.4 | V19: =T19*(1-U19) -> 900 | W19: =V19*S19*M19 -> 10800
A20: ouro produto | B20: norte | C20: to | D20: palmas | E20: Artes Coloridas | F20: Outdoor lonado | G20: 1 | H20: =VLOOKUP(G20,Pesos!A:B,2,0) -> 0.9 | I20: x | K20: 8 | L20: 15 | M20: 12 | N20: Mensal | Q20: 12 | S20: 1 | T20: =750*2 -> 1500 | U20: 0.45 | V20: =T20*(1-U20) -> 825 | W20: =V20*S20*M20 -> 9900
A22: ouro promo | B22: norte | C22: to | D22: palmas | E22: Tocantis / Apice | F22: Painel de Led | G22: 1 | H22: =VLOOKUP(G22,Pesos!A:B,2,0) -> 0.9 | J22: x | K22: 3 | L22: 7 | M22: 1 | N22: Mensal | O22: 1 | S22: 1 | T22: =15*48*30 -> 21600 | U22: 0.25 | V22: =T22*(1-U22) -> 16200 | W22: =V22*S22*M22 -> 16200
A23: ouro promo | B23: norte | C23: to | D23: palmas | E23: Led+ | F23: Painel de Led | G23: 1 | H23: =VLOOKUP(G23,Pesos!A:B,2,0) -> 0.9 | J23: x | K23: 3 | L23: 7 | M23: 1 | N23: Mensal | O23: 1 | S23: 1 | T23: =3750*(1+45%) -> 5437.5 | U23: 0.3 | V23: =T23*(1-U23) -> 3806.25 | W23: =V23*S23*M23 -> 3806.25
A24: ouro promo | B24: norte | C24: to | D24: palmas | E24: Bureau de Midia | F24: Painel de Led | G24: 1 | H24: =VLOOKUP(G24,Pesos!A:B,2,0) -> 0.9 | J24: x | K24: 3 | L24: 7 | M24: 1 | N24: Mensal | O24: 1 | S24: 1 | T24: =(6600+7200)/2 -> 6900 | U24: 0.2 | V24: =T24*(1-U24) -> 5520 | W24: =V24*S24*M24 -> 5520
A25: ouro promo | B25: norte | C25: to | D25: palmas | E25: Tocantins / Apice | F25: Outdoor lonado | G25: 2 | H25: =VLOOKUP(G25,Pesos!A:B,2,0) -> 0.8 | I25: x | K25: 8 | L25: 15 | M25: 12 | N25: Mensal | O25: 12 | S25: 1 | T25: =750*2 -> 1500 | U25: 0.4 | V25: =T25*(1-U25) -> 900 | W25: =V25*S25*M25 -> 10800
A26: ouro promo | B26: norte | C26: to | D26: palmas | E26: Artes Coloridas | F26: Outdoor lonado | G26: 2 | H26: =VLOOKUP(G26,Pesos!A:B,2,0) -> 0.8 | I26: x | K26: 8 | L26: 15 | M26: 12 | N26: Mensal | Q26: 12 | S26: 1 | T26: =750*2 -> 1500 | U26: 0.45 | V26: =T26*(1-U26) -> 825 | W26: =V26*S26*M26 -> 9900
A27: ouro promo | B27: norte | C27: to | D27: palmas | E27: S2xPromoçoes | F27: Carro de Som | G27: 3 | H27: =VLOOKUP(G27,Pesos!A:B,2,0) -> 0.7 | I27: x | K27: 2 | L27: 6 | M27: 2 | N27: Diaria | O27: 2 | Q27: 2 | S27: 2 | T27: =265*8 -> 2120 | U27: 0.4 | V27: =T27*(1-U27) -> 1272 | W27: =V27*S27*M27 -> 5088
A28: ouro promo | B28: norte | C28: to | D28: palmas | E28: Cartaxi | F28: Vidro traseiro _ interno | G28: 4 | H28: =VLOOKUP(G28,Pesos!A:B,2,0) -> 0.6 | I28: x | K28: 5 | L28: 10 | M28: 5 | N28: Mensal | O28: 5 | S28: 1 | T28: 1600 | U28: 0.7 | V28: =T28*(1-U28) -> 480 | W28: =V28*S28*M28 -> 2400
A30: prata | B30: norte | C30: to | D30: palmas | E30: Led+ | F30: Painel de Led | G30: 1 | H30: =VLOOKUP(G30,Pesos!A:B,2,0) -> 0.9 | J30: x | K30: 2 | L30: 5 | M30: 1 | N30: Mensal | O30: 1 | S30: 1 | T30: =3750*(1+45%) -> 5437.5 | U30: 0.3 | V30: =T30*(1-U30) -> 3806.25 | W30: =V30*S30*M30 -> 3806.25
A31: prata | B31: norte | C31: to | D31: palmas | E31: Bureau de Midia | F31: Painel de Led | G31: 1 | H31: =VLOOKUP(G31,Pesos!A:B,2,0) -> 0.9 | J31: x | K31: 2 | L31: 5 | M31: 1 | N31: Mensal | O31: 1 | S31: 1 | T31: =(6600+7200)/2 -> 6900 | U31: 0.2 | V31: =T31*(1-U31) -> 5520 | W31: =V31*S31*M31 -> 5520
A32: prata | B32: norte | C32: to | D32: palmas | E32: Tocantins / Apice | F32: Outdoor lonado | G32: 2 | H32: =VLOOKUP(G32,Pesos!A:B,2,0) -> 0.8 | I32: x | K32: 6 | L32: 12 | M32: 8 | N32: Mensal | O32: 8 | S32: 1 | T32: =750*2 -> 1500 | U32: 0.4 | V32: =T32*(1-U32) -> 900 | W32: =V32*S32*M32 -> 7200
A33: prata | B33: norte | C33: to | D33: palmas | E33: Artes Coloridas | F33: Outdoor lonado | G33: 2 | H33: =VLOOKUP(G33,Pesos!A:B,2,0) -> 0.8 | I33: x | K33: 6 | L33: 12 | M33: 8 | N33: Mensal | Q33: 8 | S33: 1 | T33: =750*2 -> 1500 | U33: 0.45 | V33: =T33*(1-U33) -> 825 | W33: =V33*S33*M33 -> 6600
A34: prata | B34: norte | C34: to | D34: palmas | E34: S2xPromoçoes | F34: Carro de Som | G34: 3 | H34: =VLOOKUP(G34,Pesos!A:B,2,0) -> 0.7 | I34: x | K34: 1 | L34: 4 | M34: 1 | N34: Diaria | O34: 1 | Q34: 1 | S34: 2 | T34: =265*8 -> 2120 | U34: 0.4 | V34: =T34*(1-U34) -> 1272 | W34: =V34*S34*M34 -> 2544
A35: prata | B35: norte | C35: to | D35: palmas | E35: Cartaxi | F35: Vidro traseiro _ interno | G35: 4 | H35: =VLOOKUP(G35,Pesos!A:B,2,0) -> 0.6 | I35: x | K35: 2 | L35: 6 | M35: 3 | N35: Mensal | O35: 2 | S35: 1 | T35: 1600 | U35: 0.7 | V35: =T35*(1-U35) -> 480 | W35: =V35*S35*M35 -> 1440
E39: cpf mínimo | F39: cpf plano | G39: cpf máximo
A40: DATA PRODUTO | E40: =F40*(1-10%) -> 2085.4155 | F40: =PALMAS!T46 -> 2317.1284 | G40: =F40*(1+15%) -> 2664.6976
A41: DATA PROMO | E41: =F41*(1-25%) -> 1203.9525 | F41: =PALMAS!T74 -> 1605.27 | G41: =F41*(1+5%) -> 1685.5335
A42: OURO PRODUTO | E42: =F42*(1-15%) -> 1661.9397 | F42: =PALMAS!T106 -> 1955.2232 | G42: =F42*(1+15%) -> 2248.5067
A43: OURO PROMO | E43: =F43*(1-25%) -> 1181.5469 | F43: =PALMAS!T134 -> 1575.3958 | G43: =F43*(1+5%) -> 1654.1656
A44: PRATA | E44: =F44*(1-25%) -> 981.85598 | F44: =PALMAS!T168 -> 1309.1413 | G44: =F44*(1+5%) -> 1374.5984
E46: ranking semanas - distribuição investimento
A47: DATA PRODUTO | E47: 0.56 | G47: 0.41
A48: DATA PROMO | E48: 0.62 | G48: 0.38
A49: OURO PRODUTO | E49: 0.57 | G49: 0.43
A50: OURO PROMO | E50: 0.61 | G50: 0.39
A51: PRATA | E51: 0.61 | G51: 0.39
E55: ranking semanas - distribuição audiência
A56: DATA PRODUTO | E56: 0.25 | F56: 0.25 | G56: 0.25 | H56: 0.25
A57: DATA PROMO | E57: 0.27 | F57: 0.23 | G57: 0.27 | H57: 0.23
A58: OURO PRODUTO | E58: 0.34 | F58: 0.33 | G58: 0.33
A59: OURO PROMO | E59: 0.35 | F59: 0.32 | G59: 0.33
A60: PRATA | E60: 0.35 | F60: 0.32 | G60: 0.33

Sheet PORTO VELHO
A1: ESTUDO PORTO VELHO
A2: IBGE 2024/ CENSO 2022
A7: INVESTIMENTO PORTO VELHO CAPITAL OOH 2024 | B7: 329386.2
A8: INVESTIMENTO RONDONIA OOH 2024 | B8: 371112.41
A10: R$ BRUTO PORTO VELHO CAPITAL - 2025 OOH | B10: 636049.05
A11: BUDGET BRUTO RONDONIA - 2025 OOH (100%) | B11: 757201.25
A14: Exclusão de Bronze
A15: CICLOS/MEDALHAS | C15: % BUDGET/CICLO | D15: R$ MEDALHA | E15: R$ UNIT. MEDALHAS
A16: Data | B16: 3 - 2 produto/1 promo | C16: 0.37 | D16: =B10*C16 -> 235338.15 | E16: =D16/3 -> 78446.049
A17: Ouro | B17: 5 - 4 produto/ 1 promo | C17: 0.49 | D17: =B10*C17 -> 311664.03 | E17: =D17/5 -> 62332.807
A18: Prata | B18: 2 | C18: 0.14 | D18: =B10*C18 -> 89046.867 | E18: =D18/2 -> 44523.433
B19: 10 ciclos | C19: =SUM(C16:C18) -> 1 | D19: =SUM(D16:D18) -> 636049.05
A22: População Capital | B22: 460434
A23: População Target - AS ABC 18/49 (logan) | B23: 138526 | E23: Cobertura total - Data Produto | F23: 74% | H23: Cobertura total - Data Promo | J23: 0.87
E24: Frequencia | F24: 21 | H24: Frequencia | J24: 34
E25: TRP | F25: 533 | H25: TRP | J25: 890
E26: OTS | F26: 1.463.330 | H26: OTS | J26: 2560213
A27: Programação - Ciclo Data Produto
A29: 1 CICLO | T29: TOTAL ANO / CICLO
A30: Praça | B30: Exibidores | C30: Pen/Aff | D30: Canais | E30: Formato | F30: Range de volume ideal | G30: Qtdade | H30: Periodicidade | I30: Mês Base | M30: TT | N30: R$ Unit Bruto | O30: Desconto | P30: R$ Unit Bruto | Q30: R$ TT Bruto | R30: C.P.M. Formato | S30: % | T30: R$ Total | U30: AMBIENTES | Z30: FORMATO | AB30: EMPRESAS
I31: S1 | J31: S2 | K31: S3 | L31: S4 | M31: Flight | N31: Tabela | O31: (%) | P31: Negociado | Q31: Negociado | T31: ano
A32: DATAS MÃES/NATAL | U32: GDES | V32: MUB | W32: TRANSP | X32: AERO | Y32: OPORT | Z32: ESTÁTICO | AA32: DIGITAL | AB32: M2 | AC32: S2X | AD32: KALLAS
A34: Porto Velho - RO | B34: M2Comunicações | C34: 50/156 | D34: Painel de Led | E34: Digital | F34: 3/6 | G34: 2 | H34: Mensal | I34: 2 | M34: 1 | N34: 4480 | O34: 0.25 | P34: =N34*(1-O34) -> 3360 | Q34: =P34*M34*G34 -> 6720 | R34: =(Q34+Q35+Q37+#REF!)/E11*1000 -> #REF! | S34: =Q34/$Q$44 -> 0.085396228 | T34: =Q34*2 -> 13440 | U34: =T34 -> 13440 | AA34: =T34 -> 13440 | AB34: =T34 -> 13440
A35: Porto Velho - RO | B35: M2Comunicações | C35: 50/156 | D35: Painel de Led | E35: Digital | F35: 3/6 | G35: 1 | H35: Mensal | I35: 1 | M35: 1 | N35: 15000 | O35: 0.25 | P35: =N35*(1-O35) -> 11250 | Q35: =P35*M35*G35 -> 11250 | R35: =(Q35+Q36+#REF!+#REF!)/E12*1000 -> #REF! | S35: =Q35/$Q$44 -> 0.14296244 | T35: =Q35*2 -> 22500 | U35: =T35 -> 22500 | AA35: =T35 -> 22500 | AB35: =T35 -> 22500
A36: Porto Velho - RO | B36: M2Comunicações | C36: 50/156 | D36: Painel de Led | E36: Digital | F36: 3/6 | G36: 1 | H36: Mensal | I36: 1 | M36: 1 | N36: 32960 | O36: 0.25 | P36: =N36*(1-O36) -> 24720 | Q36: =P36*M36*G36 -> 24720 | S36: =Q36/$Q$44 -> 0.31413613 | T36: =Q36*2 -> 49440 | U36: =T36 -> 49440 | AA36: =T36 -> 49440 | AB36: =T36 -> 49440
A37: Porto Velho - RO | B37: M2Comunicações | C37: 50/156 | D37: Outdoor lonado | E37: Estático | F37: 8/15 | G37: 10 | H37: Mensal | I37: 10 | M37: 1 | N37: 1560 | O37: 0.25 | P37: =N37*(1-O37) -> 1170 | Q37: =P37*M37*G37 -> 11700 | R37: =(Q37+#REF!)/E12*1000 -> #REF! | S37: =Q37/$Q$44 -> 0.14868093 | T37: =Q37*2 -> 23400 | U37: =T37 -> 23400 | Z37: =T37 -> 23400 | AB37: =T37 -> 23400
A38: Porto Velho - RO | B38: M2Comunicações | C38: 50/156 | D38: Frontlight | E38: Estático | F38: 2/5 | G38: 2 | H38: Mensal | I38: 2 | M38: 1 | N38: 4068 | O38: 0.25 | P38: =N38*(1-O38) -> 3051 | Q38: =P38*M38*G38 -> 6102 | R38: =(Q38+#REF!+#REF!)/E12*1000 -> #REF! | S38: =Q38/$Q$44 -> 0.077542825 | T38: =Q38*2 -> 12204 | U38: =T38 -> 12204 | Z38: =T38 -> 12204 | AB38: =T38 -> 12204
A39: Porto Velho - RO | B39: M2Comunicações | C39: 50/156 | D39: Outdoor lonado | E39: Estático | F39: 8/15 | G39: 10 | H39: Mensal | K39: 10 | M39: 1 | N39: 1560 | O39: 0.25 | P39: =N39*(1-O39) -> 1170 | Q39: =P39*M39*G39 -> 11700 | R39: =(Q39+#REF!)/E14*1000 -> #REF! | S39: =Q39/$Q$44 -> 0.14868093 | T39: =Q39*2 -> 23400 | U39: =T39 -> 23400 | Z39: =T39 -> 23400 | AB39: =T39 -> 23400
AB40: =T40 -> 0
A41: Porto Velho - RO | B41: Aeroporto | T41: =Q41*2 -> 0 | X41: =T41 -> 0
A42: Porto Velho - RO | B42: Oportunidades | D42: Marítimos / Ativação | Q42: 6500 | S42: =Q42/Q44 -> 0.082600518 | T42: =Q42*2 -> 13000 | Y42: =T42 -> 13000
I43: =I44/M44 -> 0.61538462 | K43: =K44/M44 -> 0.38461538
A44: Total faces compra | I44: =I38+I37+I36+I35+I34 -> 16 | K44: =K39 -> 10 | M44: =SUM(I44:L44) -> 26 | Q44: =SUM(Q34:Q43) -> 78692 | S44: =SUM(S34:S42) -> 1 | T44: =SUM(T34:T43) -> 157384 | U44: =SUM(U34:U42) -> 144384 | V44: =SUM(V34:V42) -> 0 | W44: =SUM(W34:W42) -> 0 | X44: =SUM(X34:X42) -> 0 | Y44: =SUM(Y34:Y42) -> 13000 | Z44: =SUM(Z34:Z42) -> 59004 | AA44: =SUM(AA34:AA42) -> 85380 | AB44: =SUM(AB34:AB43) -> 144384
A45: Total faces simulação | I45: =I38+I37+I36+I35+I34 -> 16 | J45: =I38+I37+I36+I35+I34 -> 16 | K45: =I38+I36+I35+I34+K39 -> 16 | L45: =I38+I36+I35+I34+K39 -> 16 | M45: =SUM(I45:L45) -> 64 | U45: =U44/T44 -> 0.91739948 | V45: =V44/T44 -> 0 | W45: =W44/T44 -> 0 | X45: =X44/T44 -> 0 | Y45: =Y44/T44 -> 0.082600518 | Z45: =Z44/T44 -> 0.37490469 | AA45: =AA44/T44 -> 0.54249479
A46: Grandes Formatos | I46: 0.25 | Q46: =U44/2 -> 72192 | S46: =Q46/Q51 -> 0.91739948 | Z46: =I37+I38+K39 -> 22 | AA46: =I34+I35+I36 -> 4
A47: MUB | Q47: =V44/2 -> 0 | S47: =Q47/Q51 -> 0 | T47: =Q44/M44 -> 3026.6154 | U47: CPFACE | Z47: =Z46/M44 -> 0.84615385 | AA47: =AA46/M44 -> 0.15384615
A48: Transportes | Q48: =W44/2 -> 0 | S48: =Q48/Q51 -> 0 | Z48: SHARE FACES
A49: Oportunidades | Q49: =Y44/2 -> 6500 | S49: =Q49/Q51 -> 0.082600518
A50: Aeroporto | Q50: =X44/2 -> 0 | S50: =Q50/Q51 -> 0
Q51: =SUM(Q46:Q50) -> 78692 | S51: =SUM(S46:S50) -> 1
A53: Programação - Ciclo Data Promo
A55: 1 CICLO | T55: TOTAL ANO / CICLO
A56: Praça | B56: Exibidores | C56: Pen/Aff | D56: Canais | E56: Formato | F56: Range de volume ideal | G56: Qtdade | H56: Periodicidade | I56: Mês Base | M56: TT | N56: R$ Unit Bruto | O56: Desconto | P56: R$ Unit Bruto | Q56: R$ TT Bruto | R56: C.P.M. Formato | S56: % | T56: R$ Total | U56: AMBIENTES | Z56: FORMATO | AB56: EMPRESAS
I57: S1 | J57: S2 | K57: S3 | L57: S4 | M57: Flight | N57: Tabela | O57: (%) | P57: Negociado | Q57: Negociado | T57: ano
A58: DATAS MÃES/NATAL | U58: GDES | V58: MUB | W58: TRANSP | X58: AERO | Y58: OPORT | Z58: ESTÁTICO | AA58: DIGITAL | AB58: M2 | AC58: S2X | AD58: KALLAS
A60: Porto Velho - RO | B60: M2Comunicações | C60: 50/156 | D60: Painel de Led | E60: Digital | F60: 3/6 | G60: 1 | H60: Mensal | I60: 1 | M60: 1 | N60: 4480 | O60: 0.25 | P60: =N60*(1-O60) -> 3360 | Q60: =P60*M60*G60 -> 3360 | R60: =(Q60+Q61+Q62+#REF!)/E36*1000 -> #REF! | S60: =Q60/$Q$73 -> 0.043897468 | T60: =Q60 -> 3360 | U60: =T60 -> 3360 | AA60: =T60 -> 3360 | AB60: =T60 -> 3360
A61: Porto Velho - RO | B61: M2Comunicações | C61: 50/156 | D61: Painel de Led | E61: Digital | F61: 3/6 | G61: 1 | H61: Mensal | I61: 1 | M61: 1 | N61: 15000 | O61: 0.25 | P61: =N61*(1-O61) -> 11250 | Q61: =P61*M61*G61 -> 11250 | R61: =(Q61+#REF!+#REF!+#REF!)/E37*1000 -> #REF! | S61: =Q61/$Q$73 -> 0.14697813 | T61: =Q61 -> 11250 | U61: =T61 -> 11250 | AA61: =T61 -> 11250 | AB61: =T61 -> 11250
A62: Porto Velho - RO | B62: M2Comunicações | C62: 50/156 | D62: Outdoor lonado | E62: Estático | F62: 8/15 | G62: 13 | H62: Mensal | I62: 13 | M62: 1 | N62: 1560 | O62: 0.25 | P62: =N62*(1-O62) -> 1170 | Q62: =P62*M62*G62 -> 15210 | R62: =(Q62+#REF!)/E37*1000 -> #REF! | S62: =Q62/$Q$73 -> 0.19871443 | T62: =Q62 -> 15210 | U62: =T62 -> 15210 | Z62: =T62 -> 15210 | AB62: =T62 -> 15210
A63: Porto Velho - RO | B63: M2Comunicações | C63: 50/156 | D63: Frontlight | E63: Estático | F63: 2/5 | G63: 2 | H63: Mensal | I63: 2 | M63: 1 | N63: 4068 | O63: 0.25 | P63: =N63*(1-O63) -> 3051 | Q63: =P63*M63*G63 -> 6102 | R63: =(Q63+#REF!+#REF!)/E37*1000 -> #REF! | S63: =Q63/$Q$73 -> 0.079720938 | T63: =Q63 -> 6102 | U63: =T63 -> 6102 | Z63: =T63 -> 6102 | AB63: =T63 -> 6102
A64: Porto Velho - RO | B64: M2Comunicações | C64: 50/156 | D64: Outdoor lonado | E64: Estático | F64: 8/15 | G64: 13 | H64: Mensal | K64: 13 | M64: 1 | N64: 1560 | O64: 0.25 | P64: =N64*(1-O64) -> 1170 | Q64: =P64*M64*G64 -> 15210 | R64: =(Q64+#REF!)/E39*1000 -> #REF! | S64: =Q64/$Q$73 -> 0.19871443 | T64: =Q64 -> 15210 | U64: =T64 -> 15210 | Z64: =T64 -> 15210 | AB64: =T64 -> 15210
A65: Porto Velho - RO | B65: M2Comunicações | C65: 63/153 | D65: Busdoor | E65: Estático | F65: 5/10 | G65: 7 | H65: Mensal | I65: 7 | M65: 1 | N65: 1016 | O65: 0.25 | P65: =N65*(1-O65) -> 762 | Q65: =P65*M65*G65 -> 5334 | S65: =Q65/$Q$73 -> 0.069687231 | T65: =Q65 -> 5334 | W65: =T65 -> 5334 | Z65: =T65 -> 5334 | AB65: =T65 -> 5334
A66: Porto Velho - RO | B66: S2xPromoçoes | D66: Carro de Som | E66: Audio | G66: 4 | H66: Diaria | I66: 4 | K66: 4 | M66: 2 | N66: =265*8 -> 2120 | O66: 0.4 | P66: =N66*(1-O66) -> 1272 | Q66: =P66*G66*M66 -> 10176 | S66: =Q66/$Q$73 -> 0.13294662 | T66: =Q66 -> 10176 | U66: =T66 -> 10176 | AC66: =T66 -> 10176
A67: Porto Velho - RO | B67: Cartaxi | C67: 30/155 | D67: Vidro traseiro _ interno | E67: Estático | F67: 5/10 | G67: 5 | H67: Mensal | I67: 5 | M67: 1 | N67: 1600 | O67: 0.7 | P67: =N67*(1-O67) -> 480 | Q67: =P67*G67*M67 -> 2400 | S67: =Q67/$Q$73 -> 0.031355334 | T67: =Q67 -> 2400 | W67: =T67 -> 2400 | Z67: =T67 -> 2400 | AD67: =T67 -> 2400
A70: Porto Velho - RO | B70: Aeroporto | T70: =Q70*2 -> 0 | X70: =T70 -> 0
A71: Porto Velho - RO | B71: Oportunidades | D71: Marítimos / Ativação | Q71: 7500 | S71: =Q71/Q73 -> 0.09798542 | T71: =Q71 -> 7500 | Y71: =T71 -> 7500
I72: =I73/M73 -> 0.66 | K72: =K73/M73 -> 0.34
A73: Total faces compra | I73: =I63+I62+I61+I60+I65+I66+I67 -> 33 | K73: =K66+K64 -> 17 | M73: =SUM(I73:L73) -> 50 | Q73: =SUM(Q60:Q72) -> 76542 | S73: =SUM(S60:S71) -> 1 | T73: =SUM(T60:T72) -> 76542 | U73: =SUM(U60:U71) -> 61308 | V73: =SUM(V60:V71) -> 0 | W73: =SUM(W60:W71) -> 7734 | X73: =SUM(X60:X71) -> 0 | Y73: =SUM(Y60:Y71) -> 7500 | Z73: =SUM(Z60:Z71) -> 44256 | AA73: =SUM(AA60:AA71) -> 14610 | AB73: =SUM(AB60:AB72) -> 56466 | AC73: =SUM(AC60:AC72) -> 10176 | AD73: =SUM(AD60:AD72) -> 2400
A74: Total faces simulação | I74: =I63+I62+I61+I60+I65+I66+I67 -> 33 | J74: =I63+I62+I61+I60+I65+I67 -> 29 | K74: =I63+I61+I60+K64+I65+K66+I67 -> 33 | L74: =I63+I61+I60+K64+I65+I67 -> 29 | M74: =SUM(I74:L74) -> 124 | U74: =U73/T73 -> 0.80097202 | V74: =V73/T73 -> 0 | W74: =W73/T73 -> 0.10104256 | X74: =X73/T73 -> 0 | Y74: =Y73/T73 -> 0.09798542 | Z74: =Z73/T73 -> 0.57819236 | AA74: =AA73/T73 -> 0.1908756
A75: Grandes Formatos | I75: =I74/M74 -> 0.26612903 | J75: =J74/M74 -> 0.23387097 | Q75: =U73 -> 61308 | S75: =Q75/Q80 -> 0.80097202 | Z75: =I62+I63+K64+I67+I65 -> 40 | AA75: =I60+I61 -> 2
A76: MUB | Q76: =V73 -> 0 | S76: =Q76/Q80 -> 0 | T76: =Q73/M73 -> 1530.84 | U76: CPFACE | Z76: =Z75/M73 -> 0.8 | AA76: =AA75/M73 -> 0.04
A77: Transportes | Q77: =W73 -> 7734 | S77: =Q77/Q80 -> 0.10104256 | Z77: SHARE FACES
A78: Oportunidades | Q78: =Y73 -> 7500 | S78: =Q78/Q80 -> 0.09798542
A79: Aeroporto | Q79: =X73 -> 0 | S79: =Q79/Q80 -> 0
Q80: =SUM(Q75:Q79) -> 76542 | S80: =SUM(S75:S79) -> 1
E84: Cobertura total - Ouro Produto | F84: 73% | G84: Cobertura total - Ouro Promo | I84: 0.85
E85: Frequencia | F85: 21 | G85: Frequencia | I85: 32
E86: TRP | F86: 528 | G86: TRP | I86: 679
E87: OTS | F87: 1.400.123 | G87: OTS | I87: 2315789
A89: Programação - Ciclo Ouro Produto
A91: 1 CICLO | T91: TOTAL ANO / CICLO
A92: Praça | B92: Exibidores | C92: Pen/Aff | D92: Canais | E92: Formato | F92: Range de volume ideal | G92: Qtdade | H92: Periodicidade | I92: Mês Base | M92: TT | N92: R$ Unit Bruto | O92: Desconto | P92: R$ Unit Bruto | Q92: R$ TT Bruto | R92: C.P.M. Formato | S92: % | T92: R$ Total | U92: AMBIENTES | Z92: FORMATO | AB92: EMPRESAS
I93: S1 | J93: S2 | K93: S3 | L93: S4 | M93: Flight | N93: Tabela | O93: (%) | P93: Negociado | Q93: Negociado | T93: ano
A94: OURO PRODUTO | U94: GDES | V94: MUB | W94: TRANSP | X94: AERO | Y94: OPORT | Z94: ESTÁTICO | AA94: DIGITAL | AB94: M2 | AC94: S2X | AD94: KALLAS
A96: Porto Velho - RO | B96: M2Comunicações | C96: 50/156 | D96: Painel de Led | E96: Digital | F96: 2/4 | G96: 2 | H96: Mensal | I96: 2 | M96: 1 | N96: 4480 | O96: 0.25 | P96: =N96*(1-O96) -> 3360 | Q96: =P96*M96*G96 -> 6720 | R96: =(Q96+Q97+Q98+#REF!)/E75*1000 -> #REF! | S96: =Q96/$Q$105 -> 0.1280683 | T96: =Q96*4 -> 26880 | U96: =T96 -> 26880 | AA96: =T96 -> 26880 | AB96: =T96 -> 26880
A97: Porto Velho - RO | B97: M2Comunicações | C97: 50/156 | D97: Painel de Led | E97: Digital | F97: 2/4 | G97: 1 | H97: Mensal | I97: 1 | M97: 1 | N97: 15000 | O97: 0.25 | P97: =N97*(1-O97) -> 11250 | Q97: =P97*M97*G97 -> 11250 | R97: =(Q97+#REF!+#REF!+#REF!)/E76*1000 -> #REF! | S97: =Q97/$Q$105 -> 0.21440006 | T97: =Q97*4 -> 45000 | U97: =T97 -> 45000 | AA97: =T97 -> 45000 | AB97: =T97 -> 45000
A98: Porto Velho - RO | B98: M2Comunicações | C98: 50/156 | D98: Outdoor lonado | E98: Estático | F98: 6/12 | G98: 10 | H98: Mensal | I98: 10 | M98: 1 | N98: 1560 | O98: 0.25 | P98: =N98*(1-O98) -> 1170 | Q98: =P98*M98*G98 -> 11700 | R98: =(Q98+#REF!)/E76*1000 -> #REF! | S98: =Q98/$Q$105 -> 0.22297606 | T98: =Q98*4 -> 46800 | U98: =T98 -> 46800 | Z98: =T98 -> 46800 | AB98: =T98 -> 46800
A99: Porto Velho - RO | B99: M2Comunicações | C99: 50/156 | D99: Frontlight | E99: Estático | F99: 1/3 | G99: 2 | H99: Mensal | I99: 2 | M99: 1 | N99: 4068 | O99: 0.25 | P99: =N99*(1-O99) -> 3051 | Q99: =P99*M99*G99 -> 6102 | R99: =(Q99+#REF!+#REF!)/E76*1000 -> #REF! | S99: =Q99/$Q$105 -> 0.11629059 | T99: =Q99*4 -> 24408 | U99: =T99 -> 24408 | Z99: =T99 -> 24408 | AB99: =T99 -> 24408
A100: Porto Velho - RO | B100: M2Comunicações | C100: 50/156 | D100: Outdoor lonado | E100: Estático | F100: 6/12 | G100: 10 | H100: Mensal | K100: 10 | M100: 1 | N100: 1560 | O100: 0.25 | P100: =N100*(1-O100) -> 1170 | Q100: =P100*M100*G100 -> 11700 | R100: =(Q100+#REF!)/E78*1000 -> #REF! | S100: =Q100/$Q$105 -> 0.22297606 | T100: =Q100*4 -> 46800 | U100: =T100 -> 46800 | Z100: =T100 -> 46800 | AB100: =T100 -> 46800
A102: Porto Velho - RO | B102: Aeroporto | T102: =Q102*2 -> 0 | X102: =T102 -> 0
A103: Porto Velho - RO | B103: Oportunidades | D103: Marítimos / Ativação | Q103: 5000 | S103: =Q103/Q105 -> 0.095288916 | T103: =Q103*4 -> 20000 | Y103: =T103 -> 20000
I104: =I105/M105 -> 0.6 | K104: =K105/M105 -> 0.4
A105: Total faces compra | I105: =I99+I98+I97+I96 -> 15 | K105: =K100 -> 10 | M105: =SUM(I105:L105) -> 25 | Q105: =SUM(Q96:Q104) -> 52472 | S105: =SUM(S96:S103) -> 1 | T105: =SUM(T96:T104) -> 209888 | U105: =SUM(U96:U103) -> 189888 | V105: =SUM(V96:V103) -> 0 | W105: =SUM(W96:W103) -> 0 | X105: =SUM(X96:X103) -> 0 | Y105: =SUM(Y96:Y103) -> 20000 | Z105: =SUM(Z96:Z103) -> 118008 | AA105: =SUM(AA96:AA103) -> 71880 | AB105: =SUM(AB96:AB103) -> 189888
A106: Total faces simulação | I106: =I99+I98+I97+I96 -> 15 | J106: =I99+I98+I97+I96 -> 15 | K106: =I99+I97+I96+K100 -> 15 | L106: =I99+I97+I96+K100 -> 15 | M106: =SUM(I106:L106) -> 60 | U106: =U105/T105 -> 0.90471108 | V106: =V105/T105 -> 0 | W106: =W105/T105 -> 0 | X106: =X105/T105 -> 0 | Y106: =Y105/T105 -> 0.095288916 | Z106: =Z105/T105 -> 0.56224272 | AA106: =AA105/T105 -> 0.34246836
A107: Grandes Formatos | I107: 0.25 | Q107: =U105/4 -> 47472 | S107: =Q107/Q112 -> 0.90471108 | Z107: =I98+I99+K100 -> 22 | AA107: =I96+I97 -> 3
A108: MUB | Q108: =V105/4 -> 0 | S108: =Q108/Q112 -> 0 | T108: =Q105/M105 -> 2098.88 | U108: CPFACE | Z108: =Z107/M105 -> 0.88 | AA108: =AA107/M105 -> 0.12
A109: Transportes | Q109: =V106/4 -> 0 | S109: =Q109/Q112 -> 0 | Z109: SHARE FACES
A110: Oportunidades | Q110: =Y105/4 -> 5000 | S110: =Q110/Q112 -> 0.095288916
A111: Aeroporto | Q111: =X105/4 -> 0 | S111: =Q111/Q112 -> 0
Q112: =SUM(Q107:Q111) -> 52472 | S112: =SUM(S107:S111) -> 1
A116: Programação - Ciclo Ouro Promo
A118: 1 CICLO | T118: TOTAL ANO / CICLO
A119: Praça | B119: Exibidores | C119: Pen/Aff | D119: Tipo de Mídia | E119: Estático/Digital | F119: Range de volume ideal | G119: Qtde Sugerida | H119: Periodicidade | I119: Mês Base | M119: TT | N119: Valor Unit. Bruto | O119: Desconto | P119: Valor Unit. Bruto | Q119: Valor total | R119: C.P.M. Formato | S119: % | T119: R$ Total | U119: AMBIENTES | Z119: FORMATO | AB119: EMPRESAS
I120: S1 | J120: S2 | K120: S3 | L120: S4 | M120: Flight | N120: Tabela | O120: (%) | P120: Negociado | Q120: Bruto Negociado | T120: ano
A121: OURO PROMO | U121: GDES | V121: MUB | W121: TRANSP | X121: AERO | Y121: OPORT | Z121: ESTÁTICO | AA121: DIGITAL | AB121: M2 | AC121: S2X | AD121: KALLAS
A123: Porto Velho - RO | B123: M2Comunicações | C123: 50/156 | D123: Painel de Led | E123: Digital | F123: 2/4 | G123: 1 | H123: Mensal | I123: 1 | M123: 1 | N123: 4480 | O123: 0.25 | P123: =N123*(1-O123) -> 3360 | Q123: =P123*M123*G123 -> 3360 | R123: =(Q123+#REF!+Q124+#REF!)/E100*1000 -> #REF! | S123: =Q123/$Q$135 -> 0.057204147 | T123: =Q123 -> 3360 | U123: =T123 -> 3360 | AA123: =T123 -> 3360 | AB123: =T123 -> 3360
A124: Porto Velho - RO | B124: M2Comunicações | C124: 50/156 | D124: Outdoor lonado | E124: Estático | F124: 6/12 | G124: 13 | H124: Mensal | I124: 13 | M124: 1 | N124: 1560 | O124: 0.25 | P124: =N124*(1-O124) -> 1170 | Q124: =P124*M124*G124 -> 15210 | R124: =(Q124+#REF!)/E101*1000 -> #REF! | S124: =Q124/$Q$135 -> 0.25895092 | T124: =Q124 -> 15210 | U124: =T124 -> 15210 | Z124: =T124 -> 15210 | AB124: =T124 -> 15210
A125: Porto Velho - RO | B125: M2Comunicações | C125: 50/156 | D125: Frontlight | E125: Estático | F125: 1/3 | G125: 1 | H125: Mensal | I125: 1 | M125: 1 | N125: 4068 | O125: 0.25 | P125: =N125*(1-O125) -> 3051 | Q125: =P125*M125*G125 -> 3051 | R125: =(Q125+#REF!+#REF!)/E101*1000 -> #REF! | S125: =Q125/$Q$135 -> 0.051943409 | T125: =Q125 -> 3051 | U125: =T125 -> 3051 | Z125: =T125 -> 3051 | AB125: =T125 -> 3051
A126: Porto Velho - RO | B126: M2Comunicações | C126: 50/156 | D126: Outdoor lonado | E126: Estático | F126: 6/12 | G126: 13 | H126: Mensal | K126: 13 | M126: 1 | N126: 1560 | O126: 0.25 | P126: =N126*(1-O126) -> 1170 | Q126: =P126*M126*G126 -> 15210 | R126: =(Q126+#REF!)/E103*1000 -> #REF! | S126: =Q126/$Q$135 -> 0.25895092 | T126: =Q126 -> 15210 | U126: =T126 -> 15210 | Z126: =T126 -> 15210 | AB126: =T126 -> 15210
A127: Porto Velho - RO | B127: M2Comunicações | C127: 63/153 | D127: Busdoor | E127: Estático | F127: 3/6 | G127: 5 | H127: Mensal | I127: 5 | M127: 1 | N127: 1016 | O127: 0.25 | P127: =N127*(1-O127) -> 762 | Q127: =P127*M127*G127 -> 3810 | S127: =Q127/$Q$135 -> 0.064865417 | T127: =Q127 -> 3810 | W127: =T127 -> 3810 | Z127: =T127 -> 3810 | AB127: =T127 -> 3810
A128: Porto Velho - RO | B128: S2xPromoçoes | D128: Carro de Som | E128: Audio | G128: 4 | H128: Diaria | I128: 4 | K128: 4 | M128: 2 | N128: =265*8 -> 2120 | O128: 0.4 | P128: =N128*(1-O128) -> 1272 | Q128: =P128*G128*M128 -> 10176 | S128: =Q128/$Q$135 -> 0.17324685 | T128: =Q128 -> 10176 | U128: =T128 -> 10176 | AC128: =T128 -> 10176
...

Sheet PORTO VELHO PLAN
A1: taxonomia | B1: regional_boticario | C1: uf | D1: praca | E1: exibidores | F1: formato | G1: ranking | H1: pesos | I1: estatico | J1: digital | K1: range_minimo | L1: range_maximo | M1: quantidade | N1: periodicidade | O1: s1 | P1: s2 | Q1: s3 | R1: s4 | S1: flight | T1: unitario_bruto_tabela | U1: desconto | V1: unitario_bruto_negociado | W1: total_bruto_negociado
A2: data produto | B2: norte | C2: ro | D2: porto velho | E2: m2 comunicações | F2: Painel de Led | G2: 2 | H2: =VLOOKUP(G2,Pesos!A:B,2,0) -> 0.8 | J2: x | K2: 3 | L2: 6 | M2: 2 | N2: Mensal | O2: 2 | S2: 1 | T2: 4480 | U2: 0.25 | V2: =T2*(1-U2) -> 3360 | W2: =V2*S2*M2 -> 6720
A3: data produto | B3: norte | C3: ro | D3: porto velho | E3: m2 comunicações | F3: Painel de Led | G3: 2 | H3: =VLOOKUP(G3,Pesos!A:B,2,0) -> 0.8 | J3: x | K3: 3 | L3: 6 | M3: 1 | N3: Mensal | O3: 1 | S3: 1 | T3: 15000 | U3: 0.25 | V3: =T3*(1-U3) -> 11250 | W3: =V3*S3*M3 -> 11250
A4: data produto | B4: norte | C4: ro | D4: porto velho | E4: m2 comunicações | F4: Painel de Led | G4: 2 | H4: =VLOOKUP(G4,Pesos!A:B,2,0) -> 0.8 | J4: x | K4: 3 | L4: 6 | M4: 1 | N4: Mensal | O4: 1 | S4: 1 | T4: 32960 | U4: 0.25 | V4: =T4*(1-U4) -> 24720 | W4: =V4*S4*M4 -> 24720
A5: data produto | B5: norte | C5: ro | D5: porto velho | E5: m2 comunicações | F5: Outdoor lonado | G5: 1 | H5: =VLOOKUP(G5,Pesos!A:B,2,0) -> 0.9 | I5: x | K5: 8 | L5: 15 | M5: 10 | N5: Bisemanal | O5: 10 | S5: 1 | T5: 1560 | U5: 0.25 | V5: =T5*(1-U5) -> 1170 | W5: =V5*S5*M5 -> 11700
A6: data produto | B6: norte | C6: ro | D6: porto velho | E6: m2 comunicações | F6: Frontlight | G6: 3 | H6: =VLOOKUP(G6,Pesos!A:B,2,0) -> 0.7 | I6: x | K6: 2 | L6: 5 | M6: 2 | N6: Mensal | O6: 2 | S6: 1 | T6: 4068 | U6: 0.25 | V6: =T6*(1-U6) -> 3051 | W6: =V6*S6*M6 -> 6102
A7: data produto | B7: norte | C7: ro | D7: porto velho | E7: m2 comunicações | F7: Outdoor lonado | G7: 1 | H7: =VLOOKUP(G7,Pesos!A:B,2,0) -> 0.9 | I7: x | K7: 8 | L7: 15 | M7: 10 | N7: Bisemanal | O7: 10 | S7: 1 | T7: 1560 | U7: 0.25 | V7: =T7*(1-U7) -> 1170 | W7: =V7*S7*M7 -> 11700
A9: data promo | B9: norte | C9: ro | D9: porto velho | E9: m2 comunicações | F9: Painel de Led | G9: 1 | H9: =VLOOKUP(G9,Pesos!A:B,2,0) -> 0.9 | J9: x | K9: 3 | L9: 6 | M9: 1 | N9: Mensal | O9: 1 | S9: 1 | T9: 4480 | U9: 0.25 | V9: =T9*(1-U9) -> 3360 | W9: =V9*S9*M9 -> 3360
A10: data promo | B10: norte | C10: ro | D10: porto velho | E10: m2 comunicações | F10: Painel de Led | G10: 1 | H10: =VLOOKUP(G10,Pesos!A:B,2,0) -> 0.9 | J10: x | K10: 3 | L10: 6 | M10: 1 | N10: Mensal | O10: 1 | S10: 1 | T10: 15000 | U10: 0.25 | V10: =T10*(1-U10) -> 11250 | W10: =V10*S10*M10 -> 11250
A11: data promo | B11: norte | C11: ro | D11: porto velho | E11: m2 comunicações | F11: Outdoor lonado | G11: 2 | H11: =VLOOKUP(G11,Pesos!A:B,2,0) -> 0.8 | I11: x | K11: 8 | L11: 15 | M11: 13 | N11: Bisemanal | O11: 13 | S11: 1 | T11: 1560 | U11: 0.25 | V11: =T11*(1-U11) -> 1170 | W11: =V11*S11*M11 -> 15210
A12: data promo | B12: norte | C12: ro | D12: porto velho | E12: m2 comunicações | F12: Frontlight | G12: 5 | H12: =VLOOKUP(G12,Pesos!A:B,2,0) -> 0.5 | I12: x | K12: 2 | L12: 5 | M12: 2 | N12: Diaria | O12: 2 | S12: 1 | T12: 4068 | U12: 0.25 | V12: =T12*(1-U12) -> 3051 | W12: =V12*S12*M12 -> 6102
A13: data promo | B13: norte | C13: ro | D13: porto velho | E13: m2 comunicações | F13: Outdoor lonado | G13: 2 | H13: =VLOOKUP(G13,Pesos!A:B,2,0) -> 0.8 | I13: x | K13: 8 | L13: 15 | M13: 13 | N13: Bisemanal | Q13: 13 | S13: 1 | T13: 1560 | U13: 0.25 | V13: =T13*(1-U13) -> 1170 | W13: =V13*S13*M13 -> 15210
A14: data promo | B14: norte | C14: ro | D14: porto velho | E14: m2 comunicações | F14: Busdoor | G14: 3 | H14: =VLOOKUP(G14,Pesos!A:B,2,0) -> 0.7 | I14: x | K14: 5 | L14: 10 | M14: 7 | N14: Mensal | O14: 7 | S14: 1 | T14: 1016 | U14: 0.25 | V14: =T14*(1-U14) -> 762 | W14: =V14*S14*M14 -> 5334
A15: data promo | B15: norte | C15: ro | D15: porto velho | E15: m2 comunicações | F15: Carro de Som | G15: 4 | H15: =VLOOKUP(G15,Pesos!A:B,2,0) -> 0.6 | I15: x | K15: 3 | L15: 7 | M15: 4 | N15: Diária | O15: 4 | Q15: 4 | S15: 2 | T15: =265*8 -> 2120 | U15: 0.4 | V15: =T15*(1-U15) -> 1272 | W15: =V15*S15*M15 -> 10176
A16: data promo | B16: norte | C16: ro | D16: porto velho | E16: Cartaxi | F16: Vidro traseiro _ interno | G16: 6 | H16: =VLOOKUP(G16,Pesos!A:B,2,0) -> 0.4 | I16: x | K16: 5 | L16: 10 | M16: 5 | N16: Mensal | O16: 5 | S16: 1 | T16: 1600 | U16: 0.7 | V16: =T16*(1-U16) -> 480 | W16: =V16*S16*M16 -> 2400
A18: ouro produto | B18: norte | C18: ro | D18: porto velho | E18: M2Comunicações | F18: Painel de Led | G18: 2 | H18: =VLOOKUP(G18,Pesos!A:B,2,0) -> 0.8 | J18: x | K18: 2 | L18: 4 | M18: 2 | N18: Mensal | O18: 2 | S18: 1 | T18: 4480 | U18: 0.25 | V18: =T18*(1-U18) -> 3360 | W18: =V18*S18*M18 -> 6720
A19: ouro produto | B19: norte | C19: ro | D19: porto velho | E19: M2Comunicações | F19: Painel de Led | G19: 2 | H19: =VLOOKUP(G19,Pesos!A:B,2,0) -> 0.8 | J19: x | K19: 2 | L19: 4 | M19: 1 | N19: Mensal | O19: 1 | S19: 1 | T19: 15000 | U19: 0.25 | V19: =T19*(1-U19) -> 11250 | W19: =V19*S19*M19 -> 11250
A20: ouro produto | B20: norte | C20: ro | D20: porto velho | E20: M2Comunicações | F20: Outdoor lonado | G20: 1 | H20: =VLOOKUP(G20,Pesos!A:B,2,0) -> 0.9 | I20: x | K20: 6 | L20: 12 | M20: 10 | N20: Bisemanal | O20: 10 | S20: 1 | T20: 1560 | U20: 0.25 | V20: =T20*(1-U20) -> 1170 | W20: =V20*S20*M20 -> 11700
A21: ouro produto | B21: norte | C21: ro | D21: porto velho | E21: M2Comunicações | F21: Frontlight | G21: 3 | H21: =VLOOKUP(G21,Pesos!A:B,2,0) -> 0.7 | I21: x | K21: 1 | L21: 3 | M21: 2 | N21: Mensal | O21: 2 | S21: 1 | T21: 4068 | U21: 0.25 | V21: =T21*(1-U21) -> 3051 | W21: =V21*S21*M21 -> 6102
A22: ouro produto | B22: norte | C22: ro | D22: porto velho | E22: M2Comunicações | F22: Outdoor lonado | G22: 1 | H22: =VLOOKUP(G22,Pesos!A:B,2,0) -> 0.9 | I22: x | K22: 6 | L22: 12 | M22: 10 | N22: Bisemanal | O22: 10 | S22: 1 | T22: 1560 | U22: 0.25 | V22: =T22*(1-U22) -> 1170 | W22: =V22*S22*M22 -> 11700
A24: ouro promo | B24: norte | C24: ro | D24: porto velho | E24: M2Comunicações | F24: Painel de Led | G24: 1 | H24: =VLOOKUP(G24,Pesos!A:B,2,0) -> 0.9 | J24: x | K24: 2 | L24: 4 | M24: 1 | N24: Mensal | O24: 1 | S24: 1 | T24: 4480 | U24: 0.25 | V24: =T24*(1-U24) -> 3360 | W24: =V24*S24*M24 -> 3360
A25: ouro promo | B25: norte | C25: ro | D25: porto velho | E25: M2Comunicações | F25: Outdoor lonado | G25: 2 | H25: =VLOOKUP(G25,Pesos!A:B,2,0) -> 0.8 | I25: x | K25: 6 | L25: 12 | M25: 13 | N25: Bisemanal | O25: 13 | S25: 1 | T25: 1560 | U25: 0.25 | V25: =T25*(1-U25) -> 1170 | W25: =V25*S25*M25 -> 15210
A26: ouro promo | B26: norte | C26: ro | D26: porto velho | E26: M2Comunicações | F26: Frontlight | G26: 4 | H26: =VLOOKUP(G26,Pesos!A:B,2,0) -> 0.6 | I26: x | K26: 1 | L26: 3 | M26: 1 | N26: Mensal | O26: 1 | S26: 1 | T26: 4068 | U26: 0.25 | V26: =T26*(1-U26) -> 3051 | W26: =V26*S26*M26 -> 3051
A27: ouro promo | B27: norte | C27: ro | D27: porto velho | E27: M2Comunicações | F27: Outdoor lonado | G27: 2 | H27: =VLOOKUP(G27,Pesos!A:B,2,0) -> 0.8 | I27: x | K27: 6 | L27: 12 | M27: 13 | N27: Bisemanal | Q27: 13 | S27: 1 | T27: 1560 | U27: 0.25 | V27: =T27*(1-U27) -> 1170 | W27: =V27*S27*M27 -> 15210
A28: ouro promo | B28: norte | C28: ro | D28: porto velho | E28: M2Comunicações | F28: Busdoor | G28: 3 | H28: =VLOOKUP(G28,Pesos!A:B,2,0) -> 0.7 | I28: x | K28: 3 | L28: 6 | M28: 5 | N28: Mensal | O28: 5 | S28: 1 | T28: 1016 | U28: 0.25 | V28: =T28*(1-U28) -> 762 | W28: =V28*S28*M28 -> 3810
A29: ouro promo | B29: norte | C29: ro | D29: porto velho | E29: S2xPromoçoes | F29: Carro de Som | G29: 5 | H29: =VLOOKUP(G29,Pesos!A:B,2,0) -> 0.5 | I29: x | K29: 2 | L29: 6 | M29: 4 | N29: Diaria | O29: 4 | Q29: 4 | S29: 2 | T29: =265*8 -> 2120 | U29: 0.4 | V29: =T29*(1-U29) -> 1272 | W29: =V29*S29*M29 -> 10176
A30: ouro promo | B30: norte | C30: ro | D30: porto velho | E30: Cartaxi | F30: Vidro traseiro _ interno | G30: 6 | H30: =VLOOKUP(G30,Pesos!A:B,2,0) -> 0.4 | I30: x | K30: 4 | L30: 8 | M30: 4 | N30: Mensal | O30: 4 | S30: 1 | T30: 1600 | U30: 0.7 | V30: =T30*(1-U30) -> 480 | W30: =V30*S30*M30 -> 1920
